Workbook

Sheet CRES
A1: 2024 Actuals | B1: Jul 2024 | C1: Aug 2024 | D1: Sep 2024 | E1: Oct 2024 | F1: Nov 2024 | G1: Dec 2024 | H1: Jan 2025 | I1: Feb 2025 | J1: Mar 2025 | K1: Apr 2025 | L1: May 2025 | M1: Jun 2025 | N1: YTD
A2: Property Asking Rent | B2: 271.161 | C2: 271.161 | D2: 236.61 | E2: 235.91 | F2: 236.41 | G2: 236.295 | H2: 235.911 | I2: 235.895 | J2: 235.45 | K2: 235.014 | L2: 234.0793 | M2: 234.33196 | N2: 2898.2283
A3: Loss to lease | B3: -52.711 | C3: -52.58 | D3: -15.80087 | E3: -16.69427 | F3: -15.46522 | G3: -15.87041 | H3: -15.37974 | I3: -15.43153 | J3: -15.36058 | K3: -14.87067 | L3: -14.57557 | M3: -14.74146 | N3: -259.48132
A4: Gross Scheduled Rent | B4: 218.45 | C4: 218.581 | D4: 220.80913 | E4: 219.21573 | F4: 220.94478 | G4: 220.42459 | H4: 220.53126 | I4: 220.46347 | J4: 220.08942 | K4: 220.14333 | L4: 219.50373 | M4: 219.5905 | N4: 2638.7469
A5: Vacancy | B5: -13.7097 | C5: -12.02063 | D5: -15.93635 | E5: -19.86242 | F5: -18.00432 | G5: -21.63113 | H5: -21.85842 | I5: -27.98297 | J5: -24.76219 | K5: -24.46553 | L5: -27.11695 | M5: -27.68306 | N5: -255.03367
A6: Non Revenue Units | B6: -1.732 | C6: -1.732 | D6: -1.565 | E6: -1.565 | F6: -2.03995 | G6: -2.1845 | H6: -2.1845 | I6: -2.1845 | J6: -2.1845 | K6: -2.1845 | L6: -2.1845 | M6: -2.1845 | N6: -23.92545
A7: Concessions | B7: -0.5333 | C7: -0.1599 | D7: -4.69872 | E7: -1.68635 | F7: -1.1599 | G7: -3.1599 | H7: -3.2599 | I7: -1.4599 | J7: -1.9599 | K7: -4.4229 | L7: -3.1663 | M7: -7.42739 | N7: -33.09436
A8: Delinquency | B8: -23.19915 | C8: -7.63524 | D8: -5.76954 | E8: -1.79466 | F8: -15.75804 | G8: -10.16156 | H8: -15.78407 | I8: -2.39172 | J8: -8.47726 | K8: -4.35736 | L8: -9.7091 | M8: -3.86133 | N8: -108.89903
A9: Effective Rental Income | B9: 179.27585 | C9: 197.03323 | D9: 192.83952 | E9: 194.3073 | F9: 183.98257 | G9: 183.2875 | H9: 177.44437 | I9: 186.44438 | J9: 182.70557 | K9: 184.71304 | L9: 177.32688 | M9: 178.43422 | N9: 2217.7944
A10: Parking Garage Income | B10: 0 | C10: 0 | D10: 0 | E10: 0 | F10: 0 | G10: 0 | H10: 0 | I10: 0 | J10: 0 | K10: 0 | L10: 0 | M10: 0 | N10: 0
A11: Utility Income | B11: 6.79827 | C11: 6.37379 | D11: 4.84895 | E11: 5.30191 | F11: 5.34961 | G11: 9.51241 | H11: 9.14551 | I11: 10.34277 | J11: 7.56977 | K11: 8.21454 | L11: 7.76315 | M11: 8.08883 | N11: 89.30951
A12: Other - Income | B12: 19.95066 | C12: 18.48254 | D12: 7.5554 | E12: 9.15565 | F12: 11.65817 | G12: 17.317 | H12: 11.02487 | I12: 11.23292 | J12: 25.01947 | K12: 16.48196 | L12: 19.31162 | M12: 10.04436 | N12: 177.23462
A13: Total Other Income | B13: 26.74893 | C13: 24.85633 | D13: 12.40435 | E13: 14.45756 | F13: 17.00778 | G13: 26.82941 | H13: 20.17038 | I13: 21.57569 | J13: 32.58924 | K13: 24.6965 | L13: 27.07477 | M13: 18.13319 | N13: 266.54413
A14: Net Eff. Gross Income | B14: 206.02478 | C14: 221.88956 | D14: 205.24387 | E14: 208.76486 | F14: 200.99035 | G14: 210.11691 | H14: 197.61475 | I14: 208.02007 | J14: 215.29481 | K14: 209.40954 | L14: 204.40165 | M14: 196.56741 | N14: 2484.3386
B16: Jul 2024 | C16: Aug 2024 | D16: Sep 2024 | E16: Oct 2024 | F16: Nov 2024 | G16: Dec 2024 | H16: Jan 2025 | I16: Feb 2025 | J16: Mar 2025 | K16: Apr 2025 | L16: May 2025 | M16: Jun 2025 | N16: YTD
A17: General & Admin. | B17: -9.55162 | C17: -6.38157 | D17: -6.15476 | E17: -1.10669 | F17: -2.859 | G17: -5.57187 | H17: -1.72641 | I17: -7.63021 | J17: -23.41802 | K17: -4.83545 | L17: 20.72103 | M17: -5.40826 | N17: -53.92283
A18: Management Fee | B18: -6.43959 | C18: -7.81744 | D18: -10.89911 | E18: -7.533 | F18: -13.79983 | G18: -7.5 | H18: -7.5 | I18: -7.5 | J18: -7.5 | K18: -7.5 | L18: -7.5 | M18: -7.5 | N18: -98.98897
A19: Payroll | B19: -27.55898 | C19: -13.43476 | D19: -29.36487 | E19: -27.81409 | F19: -32.08065 | G19: -24.22299 | H19: -29.51785 | I19: -23.43926 | J19: -23.41582 | K19: -28.49068 | L19: -23.47187 | M19: -26.01337 | N19: -308.82519
A20: Insurance | B20: -5.45225 | C20: -5.45225 | D20: -9.18009 | E20: -9.18009 | F20: -9.18009 | G20: -9.68009 | H20: -9.18009 | I20: -9.18009 | J20: -9.18009 | K20: -9.18009 | L20: -9.18009 | M20: -9.18009 | N20: -103.2054
A21: Property Taxes | B21: -31.337 | C21: -31.337 | D21: -31.337 | E21: -31.337 | F21: -31.75919 | G21: -31.42691 | H21: -31.337 | I21: -31.337 | J21: -31.337 | K21: -31.337 | L21: -31.50121 | M21: -31.337 | N21: -376.72031
A22: Leasing & Marketing | B22: -5.23631 | C22: -3.85965 | D22: -0.48817 | E22: -3.61937 | F22: -5.94748 | G22: -11.67756 | H22: -3.71905 | I22: -5.67871 | J22: -5.37941 | K22: -4.88472 | L22: -8.14604 | M22: -6.72848 | N22: -65.36495
A23: Professional fees | B23: 0 | C23: 0 | D23: 0 | E23: 0 | F23: 0 | G23: 0 | H23: 0 | I23: 0 | J23: 0 | K23: 0 | L23: 0 | M23: 0 | N23: 0
A24: Landscaping | B24: -2.55908 | C24: -2.22644 | D24: -2.2 | E24: -2.56728 | F24: -8.37 | G24: -4.16015 | H24: -4.80056 | I24: -2.48649 | J24: -3.05373 | K24: -4.33914 | L24: -2.88779 | M24: -2.93596 | N24: -42.58662
A25: Security & Life Safety | B25: 0.09988 | C25: 0 | D25: 0 | E25: 0 | F25: 0 | G25: 0 | H25: 0 | I25: -4.75184 | J25: -0.34383 | K25: -0.52383 | L25: -0.34383 | M25: -3.00783 | N25: -8.87128
A26: Repairs & Maintenance | B26: -4.38872 | C26: -2.72555 | D26: -4.4206 | E26: -3.21349 | F26: -12.28809 | G26: -5.95662 | H26: -2.05406 | I26: -0.13437 | J26: -3.84569 | K26: -7.00491 | L26: -2.95149 | M26: -3.74404 | N26: -52.72763
A27: Unit T/O Refurbishment | B27: -5.72101 | C27: -2.745 | D27: -3.51143 | E27: -8.26492 | F27: -7.23099 | G27: -7.16533 | H27: -5.50371 | I27: -2.91955 | J27: -5.81329 | K27: -6.57544 | L27: -0.73 | M27: -1.7169 | N27: -57.89757
A28: Utilities | B28: -9.95882 | C28: -4.47982 | D28: -6.75211 | E28: -6.62676 | F28: -10.38538 | G28: -11.54114 | H28: -20.61163 | I28: -10.70401 | J28: -9.31124 | K28: -13.42028 | L28: -11.41003 | M28: -7.96649 | N28: -123.16771
... A32: Total Expense | B32: -113.48879 | C32: -78.61252 | D32: -107.70918 | E32: -106.17531 | F32: -139.10122 | G32: -127.09901 | H32: -120.94004 | I32: -105.19408 | J32: -126.64812 | K32: -122.47535 | L32: -82.29504 | M32: -110.15208 | N32: -1339.8907
B34: Jul 2024 | C34: Aug 2024 | D34: Sep 2024 | E34: Oct 2024 | F34: Nov 2024 | G34: Dec 2024 | H34: Jan 2025 | I34: Feb 2025 | J34: Mar 2025 | K34: Apr 2025 | L34: May 2025 | M34: Jun 2025 | N34: YTD
A35: EBITDA (NOI) | B35: 92.53599 | C35: 143.27704 | D35: 97.53469 | E35: 102.58955 | F35: 61.88913 | G35: 83.0179 | H35: 76.67471 | I35: 102.82599 | J35: 88.64669 | K35: 86.93419 | L35: 122.10661 | M35: 86.41533 | N35: 1144.4478
B36: Yes | C36: Yes | D36: Yes | E36: Yes | F36: Yes | G36: Yes | H36: Yes | I36: Yes | J36: Yes | K36: Yes | L36: Yes | M36: Yes
B37: Jul 2024 | C37: Aug 2024 | D37: Sep 2024 | E37: Oct 2024 | F37: Nov 2024 | G37: Dec 2024 | H37: Jan 2025 | I37: Feb 2025 | J37: Mar 2025 | K37: Apr 2025 | L37: May 2025 | M37: Jun 2025 | N37: YTD
A38: Repl. Reserve Fund | B38: -5.00473 | C38: -2.61006 | D38: -4.6 | E38: 0 | F38: -1.73547 | G38: 65.48008 | H38: -2.32565 | I38: -5.78282 | J38: -11.1821 | K38: -9.52209 | L38: -45.08336 | M38: -44.92517 | N38: -67.29137
A39: State Franchise Fee | B39: 0 | C39: 0 | D39: 0 | E39: 0 | F39: 0 | G39: 0 | H39: 0 | I39: 0 | J39: 0 | K39: 0 | L39: 0 | M39: 0 | N39: 0
A40: Partnership Professional Fees | B40: -1.21 | C40: -1.62809 | D40: -3.96605 | E40: -1.2185 | F40: -1.53198 | G40: -2.02935 | H40: -7.12985 | I40: -13.49 | J40: -20.4864 | K40: -3.95001 | L40: -16.05901 | M40: -1.47501 | N40: -74.17425
A41: Asset Management Fees | B41: -3.39911 | C41: -3.32831 | D41: -3.12958 | E41: -3.23487 | F41: -3.04756 | G41: -3.17406 | H41: -3.09461 | I41: -2.85558 | J41: -3.24529 | K41: -3.18311 | L41: -3.14905 | M41: -2.89211 | N41: -37.73324
A42: Debt Service | B42: -163.37724 | C42: -163.31857 | D42: -152.88809 | E42: -158.75899 | F42: -150.2879 | G42: -150.94259 | H42: -149.07327 | I42: -134.73959 | J42: -106.44333 | K42: -96.90521 | L42: -103.36534 | M42: -96.52155 | N42: -1626.6217
A43: Other - Below Line | B43: 0 | C43: 0 | D43: 0 | E43: 0 | F43: 0 | G43: 0 | H43: 0 | I43: 0 | J43: 0 | K43: 0 | L43: 0 | M43: 0 | N43: 0
A44: Total Below Line | B44: -172.99108 | C44: -170.88503 | D44: -164.58372 | E44: -163.21236 | F44: -156.60291 | G44: -90.66592 | H44: -161.62338 | I44: -156.86799 | J44: -141.35712 | K44: -113.56042 | L44: -167.65676 | M44: -145.81384 | N44: -1805.8205
A45: Renovations | B45: 0 | C45: 0 | D45: 0 | E45: 0 | F45: 0 | G45: 0 | H45: 0 | I45: 0 | J45: 0 | K45: 0 | L45: 0 | M45: 0 | N45: 0
B46: Jul 2024 | C46: Aug 2024 | D46: Sep 2024 | E46: Oct 2024 | F46: Nov 2024 | G46: Dec 2024 | H46: Jan 2025 | I46: Feb 2025 | J46: Mar 2025 | K46: Apr 2025 | L46: May 2025 | M46: Jun 2025 | N46: YTD
A47: Monthly Cash Flow | B47: -80.45509 | C47: -27.60799 | D47: -67.04903 | E47: -60.62281 | F47: -94.71378 | G47: -7.64802 | H47: -84.94867 | I47: -54.042 | J47: -52.71043 | K47: -26.62623 | L47: -45.55015 | M47: -59.39851 | N47: -661.37271
B49: =B1 -> Jul 2024 | C49: =C1 -> Aug 2024 | D49: =D1 -> Sep 2024 | E49: =E1 -> Oct 2024 | F49: =F1 -> Nov 2024 | G49: =G1 -> Dec 2024 | H49: =H1 -> Jan 2025 | I49: =I1 -> Feb 2025 | ... M49: =M1 -> Jun 2025
A50: Operating Account Balance
A51: Interest Reserve Account
A52: Undeposited Funds
A53: Security Deposits
A54: Total Cash | B54: =IF(B36="","",SUM(B50:B53)) -> 0 | C54: =IF(C36="","",SUM(C50:C53)) -> 0 | D54: =IF(D36="","",SUM(D50:D53)) -> 0 | E54: =IF(E36="","",SUM(E50:E53)) -> 0 | F54: =IF(F36="","",SUM(F50:F53)) -> 0 | G54: =IF(G36="","",SUM(G50:G53)) -> 0 | H54: =IF(H36="","",SUM(H50:H53)) -> 0 | I54: =IF(I36="","",SUM(I50:I53)) -> 0 | ... M54: =IF(M36="","",SUM(M50:M53)) -> 0
A55: Open AR
A56: Escrow - Taxes
A57: Escrow - Insurance
A58: Escrow - Other
A59: Escrow - RR
A60: Open AP
A62: Total Equity
A63: Total Debt

Sheet Altamonte - Variance
A1: Las Palmas (693wymor)
A2: Budget Comparison
A3: Period = Mar 2024
A4: Book = Accrual ; Tree = ysi_is
C5: PTD Actual | D5: PTD Budget | E5: Variance | F5: % Var | G5: YTD Actual | H5: YTD Budget | I5: Variance | J5: % Var | K5: Annual
A7: 4000-0000 | B7: NET INCOME
A9: 4001-0000 | B9: OPERATING INCOME
A11: 4004-0000 | B11: REVENUE
A13: 4010-0000 | B13: MONTHLY RENT
A14: 4010-0010 | B14: Gross Potential Rent | C14: 378750 | D14: 375600 | E14: 3150 | F14: 0.84 | G14: 1133476 | H14: 1126800 | I14: 6676 | J14: 0.59 | K14: 4507200
A15: 4013-0000 | B15: Gain - Loss to Lease | C15: -3703 | D15: 2457.56 | E15: -6160.56 | F15: -250.68 | G15: -8654 | H15: 3529.6 | I15: -12183.6 | J15: -345.18 | K15: 68308.84
A17: 4019-9999 | B17: TOTAL MONTHLY RENT | C17: 375047 | D17: 378057.56 | E17: -3010.56 | F17: -0.8 | G17: 1124822 | H17: 1130329.6 | I17: -5507.6 | J17: -0.49 | K17: 4575508.8
A19: 4020-0000 | B19: RENTAL ADJUSTMENTS
A20: 4021-0000 | B20: Less: Concessions | C20: -10538 | D20: -1125 | E20: -9413 | F20: -836.71 | G20: -43564.24 | H20: -4673.07 | I20: -38891.17 | J20: -832.24 | K20: -19298.03
A21: 4022-0000 | B21: Less: Vacancies | C21: -54168.3 | D21: -41586.33 | E21: -12581.97 | F21: -30.26 | G21: -209656.4 | H21: -131858.97 | I21: -77797.43 | J21: -59 | K21: -414842.21
A22: 4023-0000 | B22: Less: Employee Units | C22: -1999 | D22: -450 | E22: -1549 | F22: -344.22 | G22: -2303.37 | H22: -1350 | I22: -953.37 | J22: -70.62 | K22: -5400
A23: 4025-0000 | B23: Less: Model Unit | C23: -1175 | D23: -1369 | E23: 194 | F23: 14.17 | G23: -4519.52 | H23: -4069 | I23: -450.52 | J23: -11.07 | K23: -16390
A24: 4026-0000 | B24: Less: Non Revenue Generating Units | C24: -1700 | D24: 0 | E24: -1700 | F24: N/A | G24: -5100 | H24: 0 | I24: -5100 | J24: N/A | K24: 0
A25: 4027-0000 | B25: Less: Bad Debt-Write Offs | C25: -14935.52 | D25: -20188.27 | E25: 5252.75 | F25: 26.02 | G25: 18363.49 | H25: -63218.23 | I25: 81581.72 | J25: 129.05 | K25: -189008.51
A27: 4039-9999 | B27: TOTAL RENTAL ADJUSTMENTS | C27: -84515.82 | D27: -64718.6 | E27: -19797.22 | F27: -30.59 | G27: -246780.04 | H27: -205169.27 | I27: -41610.77 | J27: -20.28 | K27: -644938.75
A29: 4200-0000 | B29: OTHER RENTAL INCOME
A30: 4201-0000 | B30: Utilities - RUBS - Water-Sewer | C30: 9136.03 | D30: 8141.64 | E30: 994.39 | F30: 12.21 | G30: 25269.66 | H30: 24424.92 | I30: 844.74 | J30: 3.46 | K30: 97699.68
A31: 4202-0000 | B31: Utilities - RUBS - Electric | C31: 546.84 | D31: 549.23 | E31: -2.39 | F31: -0.44 | G31: 2233.02 | H31: 1647.69 | I31: 585.33 | J31: 35.52 | K31: 6590.76
A32: 4203-0000 | B32: Utilities - RUBS - Trash | C32: 10234.08 | D32: 9600 | E32: 634.08 | F32: 6.6 | G32: 30827.93 | H32: 28800 | I32: 2027.93 | J32: 7.04 | K32: 115200
A33: 4205-0000 | B33: Utilities - RUBS - Pest | C33: 2184.05 | D33: 2225 | E33: -40.95 | F33: -1.84 | G33: 6156.62 | H33: 6625 | I33: -468.38 | J33: -7.07 | K33: 27275
A34: 4206-0000 | B34: Utilities - RUBS - Other | C34: 0 | D34: 0 | E34: 0 | F34: N/A | G34: -99.73 | H34: 0 | I34: -99.73 | J34: N/A | K34: 0
A35: 4210-0000 | B35: Late Fees | C35: 3725 | D35: 4171.88 | E35: -446.88 | F35: -10.71 | G35: 11725 | H35: 12421.88 | I35: -696.88 | J35: -5.61 | K35: 51140.66
A36: 4211-0000 | B36: Interest Income | C36: 768.61 | D36: 0 | E36: 768.61 | F36: N/A | G36: 768.61 | H36: 0 | I36: 768.61 | J36: N/A | K36: 0
A37: 4213-0000 | B37: NSF Fees | C37: 975 | D37: 75 | E37: 900 | F37: 1200 | G37: 2025 | H37: 225 | I37: 1800 | J37: 800 | K37: 900
A38: 4214-0000 | B38: Less: Other Bad Debt | C38: -14206.89 | D38: -4461.89 | E38: -9745 | F38: -218.41 | G38: -18442.28 | H38: -13764.78 | I38: -4677.5 | J38: -33.98 | K38: -55829.49
A39: 4215-0000 | B39: Bad Debt Recovery | C39: 0 | D39: 0 | E39: 0 | F39: N/A | G39: 49.72 | H39: 0 | I39: 49.72 | J39: N/A | K39: 0
A40: 4216-0000 | B40: Miscellaneous | C40: 5 | D40: 0 | E40: 5 | F40: N/A | G40: 5 | H40: 0 | I40: 5 | J40: N/A | K40: 0
A41: 4221-0000 | B41: Move Out Charges | C41: 625 | D41: 500 | E41: 125 | F41: 25 | G41: 865 | H41: 1500 | I41: -635 | J41: -42.33 | K41: 6000
A42: 4223-0000 | B42: Gate and Key Income | C42: 0 | D42: 0 | E42: 0 | F42: N/A | G42: 0 | H42: 25 | I42: -25 | J42: -100 | K42: 75
A43: 4225-0000 | B43: Short Term Premiums | C43: 625.81 | D43: 400 | E43: 225.81 | F43: 56.45 | G43: 2332.83 | H43: 1200 | I43: 1132.83 | J43: 94.4 | K43: 5500
A44: 4226-0000 | B44: Pet Rent | C44: 1475 | D44: 1200 | E44: 275 | F44: 22.92 | G44: 3099.31 | H44: 3560 | I44: -460.69 | J44: -12.94 | K44: 14720
A45: 4227-0000 | B45: Lease Breakage Fee | C45: 10614 | D45: 1427 | E45: 9187 | F45: 643.8 | G45: 24925 | H45: 4281 | I45: 20644 | J45: 482.22 | K45: 17124
A46: 4229-0000 | B46: Application Fees | C46: 4725 | D46: 950 | E46: 3775 | F46: 397.37 | G46: 10050 | H46: 3900 | I46: 6150 | J46: 157.69 | K46: 16000
A47: 4231-0000 | B47: Legal Fees | C47: 433 | D47: 250 | E47: 183 | F47: 73.2 | G47: 1856 | H47: 750 | I47: 1106 | J47: 147.47 | K47: 3000
A48: 4232-0000 | B48: Tenant Charges | C48: 3508 | D48: 0 | E48: 3508 | F48: N/A | G48: 3513 | H48: 0 | I48: 3513 | J48: N/A | K48: 0
A49: 4234-0000 | B49: Unit Transfer Fee | C49: 0 | D49: 0 | E49: 0 | F49: N/A | G49: 0 | H49: 0 | I49: 0 | J49: N/A | K49: 1000
A50: 4235-0000 | B50: Damages - Repairs | C50: 900 | D50: 0 | E50: 900 | F50: N/A | G50: 1910 | H50: 0 | I50: 1910 | J50: N/A | K50: 0
A51: 4236-0000 | B51: Renter's Insurance | C51: 103.35 | D51: 300 | E51: -196.65 | F51: -65.55 | G51: 369.29 | H51: 900 | I51: -530.71 | J51: -58.97 | K51: 3600
A52: 4237-0000 | B52: Amenity Premium | C52: 2177.05 | D52: 2002.5 | E52: 174.55 | F52: 8.72 | G52: 6164.97 | H52: 5962.5 | I52: 202.47 | J52: 3.4 | K52: 24547.5
A53: 4238-0000 | B53: Admin Fees | C53: 10930 | D53: 1820 | E53: 9110 | F53: 500.55 | G53: 23161.5 | H53: 7560 | I53: 15601.5 | J53: 206.37 | K53: 31220
A54: 4239-0000 | B54: Building Protection Fee | C54: 2675.42 | D54: 1335 | E54: 1340.42 | F54: 100.41 | G54: 7747.59 | H54: 3975 | I54: 3772.59 | J54: 94.91 | K54: 16365
A56: 4299-9999 | B56: TOTAL OTHER RENTAL INCOME | C56: 52159.35 | D56: 30485.36 | E56: 21673.99 | F56: 71.1 | G56: 146513.04 | H56: 93993.21 | I56: 52519.83 | J56: 55.88 | K56: 382128.11
A58: 4999-9999 | B58: TOTAL REVENUE | C58: 342690.53 | D58: 343824.32 | E58: -1133.79 | F58: -0.33 | G58: 1024555 | H58: 1019153.5 | I58: 5401.46 | J58: 0.53 | K58: 4312698.2
A60: 6100-0000 | B60: OPERATING EXPENSES
A62: 6100-0001 | B62: PERSONNEL COSTS
A63: 6101-0000 | B63: Manager - Wages | C63: 7846.17 | D63: 7680 | E63: -166.17 | F63: -2.16 | G63: 20245.87 | H63: 17920 | I63: -2325.87 | J63: -12.98 | K63: 69273.6
A64: 6103-0000 | B64: Manager - Bonus | C64: 350 | D64: 218.4 | E64: -131.6 | F64: -60.26 | G64: 1778.44 | H64: 907.2 | I64: -871.24 | J64: -96.04 | K64: 3746.4
A65: 6104-0000 | B65: Manager - Leasing Commission | C65: 900 | D65: 117 | E65: -783 | F65: -669.23 | G65: 5250 | H65: 486 | I65: -4764 | J65: -980.25 | K65: 2007
A66: 6105-0000 | B66: Manager - Payroll taxes | C66: 683.03 | D66: 643.72 | E66: -39.31 | F66: -6.11 | G66: 2319.66 | H66: 1534.42 | I66: -785.24 | J66: -51.18 | K66: 5951.14
A67: 6106-0000 | B67: Asst Manager - Wages | C67: 6095.5 | D67: 4800 | E67: -1295.5 | F67: -26.99 | G67: 7095.5 | H67: 11200 | I67: 4104.5 | J67: 36.65 | K67: 43200
A68: 6107-0000 | B68: Asst Manager - Overtime | C68: 895.5 | D68: 0 | E68: -895.5 | F68: N/A | G68: 1091.25 | H68: 0 | I68: -1091.25 | J68: N/A | K68: 0
A69: 6108-0000 | B69: Asst Manager - Bonus | C69: 350 | D69: 249.6 | E69: -100.4 | F69: -40.22 | G69: 350 | H69: 1036.8 | I69: 686.8 | J69: 66.24 | K69: 4281.6
A70: 6109-0000 | B70: Asst Manager - Leasing Commission | C70: 150 | D70: 78 | E70: -72 | F70: -92.31 | G70: 150 | H70: 324 | I70: 174 | J70: 53.7 | K70: 1338
A71: 6110-0000 | B71: Asst Manager - Payroll taxes | C71: 628.77 | D71: 404 | E71: -224.77 | F71: -55.64 | G71: 731.72 | H71: 979 | I71: 247.28 | J71: 25.26 | K71: 3798
A72: 6111-0000 | B72: Leasing - Wages | C72: 4879 | D72: 5280 | E72: 401 | F72: 7.59 | G72: 6082 | H72: 12320 | I72: 6238 | J72: 50.63 | K72: 47625.6
A73: 6112-0000 | B73: Leasing - Overtime | C73: 724.41 | D73: 0 | E73: -724.41 | F73: N/A | G73: 724.41 | H73: 0 | I73: -724.41 | J73: N/A | K73: 0
A74: 6113-0000 | B74: Leasing - Bonus | C74: 350 | D74: 312 | E74: -38 | F74: -12.18 | G74: 350 | H74: 1296 | I74: 946 | J74: 72.99 | K74: 5352
A75: 6114-0000 | B75: Leasing - Leasing Commission | C75: 1650 | D75: 585 | E75: -1065 | F75: -182.05 | G75: 1650 | H75: 2430 | I75: 780 | J75: 32.1 | K75: 10035
A76: 6115-0000 | B76: Leasing - Payroll taxes | C76: 617.11 | D76: 531 | E76: -86.11 | F76: -16.22 | G76: 688.07 | H76: 1293 | I76: 604.93 | J76: 46.78 | K76: 5032
A77: 6116-0000 | B77: Maintenance - Wages | C77: 11945.91 | D77: 10560 | E77: -1385.91 | F77: -13.12 | G77: 22313.93 | H77: 24640 | I77: 2326.07 | J77: 9.44 | K77: 95145.6
A78: 6117-0000 | B78: Maintenance - Overtime | C78: 770.19 | D78: 571.56 | E78: -198.63 | F78: -34.75 | G78: 1386.99 | H78: 1714.68 | I78: 327.69 | J78: 19.11 | K78: 6858.72
A79: 6118-0000 | B79: Maintenance - Bonus | C79: 0 | D79: 421.2 | E79: 421.2 | F79: 100 | G79: 1583.34 | H79: 1749.6 | I79: 166.26 | J79: 9.5 | K79: 7225.2
A80: 6120-0000 | B80: Maintenance - Payroll taxes | C80: 1048.2 | D80: 982 | E80: -66.2 | F80: -6.74 | G80: 2367.32 | H80: 2389 | I80: 21.68 | J80: 0.91 | K80: 9285
A81: 6158-0000 | B81: Recruitment Expense | C81: -6550 | D81: 0 | E81: 6550 | F81: N/A | G81: 0 | H81: 0 | I81: 0 | J81: N/A | K81: 0
A82: 6159-0000 | B82: Training - Education | C82: 193.24 | D82: 105 | E82: -88.24 | F82: -84.04 | G82: 728.78 | H82: 315 | I82: -413.78 | J82: -131.36 | K82: 1260
A83: 6160-0000 | B83: Uniforms | C83: 0 | D83: 0 | E83: 0 | F83: N/A | G83: 131.53 | H83: 0 | I83: -131.53 | J83: N/A | K83: 0
A84: 6161-0000 | B84: Payroll Processing | C84: 2361.97 | D84: 526.62 | E84: -1835.35 | F84: -348.52 | G84: 3563.51 | H84: 1273.72 | I84: -2289.79 | J84: -179.77 | K84: 4947.4
A85: 6162-0000 | B85: 401k Company Match | C85: 543.03 | D85: 368 | E85: -175.03 | F85: -47.56 | G85: 1169.44 | H85: 858 | I85: -311.44 | J85: -36.3 | K85: 3314
A86: 6164-0000 | B86: Employee Health Insurance | C86: 484.91 | D86: 1300 | E86: 815.09 | F86: 62.7 | G86: 2011.99 | H86: 3900 | I86: 1888.01 | J86: 48.41 | K86: 15600
A87: 6165-0000 | B87: Workers Comp Insurance | C87: 0 | D87: 226 | E87: 226 | F87: 100 | G87: 0 | H87: 547 | I87: 547 | J87: 100 | K87: 2120
A89: 6179-9999 | B89: TOTAL PERSONNEL COSTS | C89: 36916.94 | D89: 35959.1 | E89: -957.84 | F89: -2.66 | G89: 83763.75 | H89: 89113.42 | I89: 5349.67 | J89: 6 | K89: 347396.26
A91: 6200-0000 | B91: CONTRACT EXPENSES
A92: 6203-0000 | B92: Landscaping | C92: 4200 | D92: 4200 | E92: 0 | F92: 0 | G92: 16250 | H92: 12600 | I92: -3650 | J92: -28.97 | K92: 50400
A93: 6204-0000 | B93: Pest Control | C93: 275 | D93: 350 | E93: 75 | F93: 21.43 | G93: 889.42 | H93: 1050 | I93: 160.58 | J93: 15.29 | K93: 4200
A94: 6206-0000 | B94: Swimming Pool | C94: 1200 | D94: 1000 | E94: -200 | F94: -20 | G94: 3600 | H94: 3000 | I94: -600 | J94: -20 | K94: 12000
A95: 6208-0000 | B95: Janitorial | C95: 1820 | D95: 2000 | E95: 180 | F95: 9 | G95: 5460 | H95: 6000 | I95: 540 | J95: 9 | K95: 24000
A96: 6209-0000 | B96: Security-Alarm | C96: 2600 | D96: 2600 | E96: 0 | F96: 0 | G96: 7445.07 | H96: 7800 | I96: 354.93 | J96: 4.55 | K96: 31200
A97: 6210-0000 | B97: Fitness Equipment Maintenance | C97: 200 | D97: 0 | E97: -200 | F97: N/A | G97: 600 | H97: 200 | I97: -400 | J97: -200 | K97: 800
A98: 6211-0000 | B98: Annual Fire System Maintenance-Inspection | C98: 0 | D98: 1000 | E98: 1000 | F98: 100 | G98: 760 | H98: 2000 | I98: 1240 | J98: 62 | K98: 3000
A100: 6219-9999 | B100: TOTAL CONTRACT EXPENSES | C100: 10295 | D100: 11150 | E100: 855 | F100: 7.67 | G100: 35004.49 | H100: 32650 | I100: -2354.49 | J100: -7.21 | K100: 125600
A102: 6300-0000 | B102: REPAIRS AND MAINTENANCE R-M
A103: 6301-0000 | B103: HVAC | C103: 148.9 | D103: 850 | E103: 701.1 | F103: 82.48 | G103: 2233.9 | H103: 2550 | I103: 316.1 | J103: 12.4 | K103: 10200
A104: 6302-0000 | B104: Appliances | C104: 0 | D104: 416.67 | E104: 416.67 | F104: 100 | G104: 0 | H104: 1250.01 | I104: 1250.01 | J104: 100 | K104: 5000.04
A105: 6303-0000 | B105: Maintenance Supplies-Equipment-Tools | C105: 656.04 | D105: 2100 | E105: 1443.96 | F105: 68.76 | G105: 656.04 | H105: 6300 | I105: 5643.96 | J105: 89.59 | K105: 25200
A106: 6304-0000 | B106: Electrical Repairs and Supplies | C106: 558 | D106: 1200 | E106: 642 | F106: 53.5 | G106: 2313.48 | H106: 3600 | I106: 1286.52 | J106: 35.74 | K106: 14400
A107: 6305-0000 | B107: Fences-Gates-Exterior Doors | C107: 0 | D107: 0 | E107: 0 | F107: N/A | G107: 0 | H107: 0 | I107: 0 | J107: N/A | K107: 350
A108: 6306-0000 | B108: Common Area | C108: 192.01 | D108: 0 | E108: -192.01 | F108: N/A | G108: 192.01 | H108: 0 | I108: -192.01 | J108: N/A | K108: 0
A109: 6308-0000 | B109: Locks - Keys | C109: 0 | D109: 0 | E109: 0 | F109: N/A | G109: 1085.72 | H109: 0 | I109: -1085.72 | J109: N/A | K109: 0
A110: 6309-0000 | B110: Maintenance Labor | C110: 405 | D110: 162 | E110: -243 | F110: -150 | G110: 405 | H110: 486 | I110: 81 | J110: 16.67 | K110: 1944
A111: 6311-0000 | B111: Painting Supplies and Materials | C111: 0 | D111: 500 | E111: 500 | F111: 100 | G111: 677.61 | H111: 1500 | I111: 822.39 | J111: 54.83 | K111: 6000
A112: 6312-0000 | B112: Pool Repair - Supplies | C112: 0 | D112: 200 | E112: 200 | F112: 100 | G112: 0 | H112: 600 | I112: 600 | J112: 100 | K112: 2150
A113: 6314-0000 | B113: Plumbing Repair - Supplies | C113: 556.67 | D113: 1666.67 | E113: 1110 | F113: 66.6 | G113: 2796.5 | H113: 5000.01 | I113: 2203.51 | J113: 44.07 | K113: 20000.04
A114: 6315-0000 | B114: Flooring | C114: 0 | D114: 0 | E114: 0 | F114: N/A | G114: 247.92 | H114: 0 | I114: -247.92 | J114: N/A | K114: 0
A115: 6316-0000 | B115: Roof-Gutter Maintenance | C115: 0 | D115: 40 | E115: 40 | F115: 100 | G115: 360 | H115: 120 | I115: -240 | J115: -200 | K115: 480
A116: 6317-0000 | B116: Irrigation | C116: 0 | D116: 52 | E116: 52 | F116: 100 | G116: 0 | H116: 156 | I116: 156 | J116: 100 | K116: 624
...

Sheet Teagen - Input
A2: Income Statement Trailing 12
A3: Teagen
A4: Accrual Basis
A5: Jan 2024 - Dec 2024
A7: Account | B7: Account Name | C7: Jan 2024 | D7: Feb 2024 | E7: Mar 2024 | F7: Apr 2024 | G7: May 2024 | H7: Jun 2024 | I7: Jul 2024 | J7: Aug 2024 | K7: Sep 2024 | L7: Oct 2024 | M7: Nov 2024 | N7: Dec 2024 | O7: Total | Q7: Income Statement: GL Account Type | R7: Income Statement: Property | S7: Income Statement: Property Look-Up Code | T7: Income Statement: Unit Count | U7: Income Statement: Month 1 Change Sign | V7: Income Statement: Month 2 Change Sign | W7: Income Statement: Month 3 Change Sign | X7: Income Statement: Month 4 Change Sign | Y7: Income Statement: Month 5 Change Sign | Z7: Income Statement: Month 6 Change Sign | AA7: Income Statement: Month 7 Change Sign | AB7: Income Statement: Month 8 Change Sign | AC7: Income Statement: Month 9 Change Sign | AD7: Income Statement: Month 10 Change Sign | AE7: Income Statement: Month 11 Change Sign | AF7: Income Statement: Month 12 Change Sign | AG7: Income Statement: Total Change Sign
A8: Income
A9: Rental Income
A10: 5001 | B10: Market Rent | C10: 275633.79 | D10: 275671.73 | E10: 279635.21 | F10: 278835.64 | G10: 275544.36 | H10: 275959.53 | I10: 276405.72 | J10: 274406.38 | K10: 274776.06 | L10: 275160.13 | M10: 267203.42 | N10: 268855.27 | O10: 3298087.2 | Q10: 4 | R10: Teagen | S10: TEA | U10: =IF(5 = Q10, C10 * -1, C10) -> 275633.79 | V10: =IF(5 = Q10, D10 * -1, D10) -> 275671.73 | W10: =IF(5 = Q10, E10 * -1, E10) -> 279635.21 | X10: =IF(5 = Q10, F10 * -1, F10) -> 278835.64 | Y10: =IF(5 = Q10, G10 * -1, G10) -> 275544.36 | Z10: =IF(5 = Q10, H10 * -1, H10) -> 275959.53 | AA10: =IF(5 = Q10, I10 * -1, I10) -> 276405.72 | AB10: =IF(5 = Q10, J10 * -1, J10) -> 274406.38 | AC10: =IF(5 = Q10, K10 * -1, K10) -> 274776.06 | AD10: =IF(5 = Q10, L10 * -1, L10) -> 275160.13 | AE10: =IF(5 = Q10, M10 * -1, M10) -> 267203.42 | AF10: =IF(5 = Q10, N10 * -1, N10) -> 268855.27 | AG10: =IF(5 = Q10, O10 * -1, O10) -> 3298087.2 | AH10: Property Asking Rent
A11: 5002 | B11: Gain/Loss To Lease | C11: -20703.22 | D11: -18666.7 | E11: -21247.26 | F11: -18608.65 | G11: -16892.25 | H11: -17799.09 | I11: -18065.64 | J11: -16178.15 | K11: -14469.73 | L11: -15890.83 | M11: -8271.96 | N11: -9504.2 | O11: -196297.68 | Q11: 4 | R11: Teagen | S11: TEA | U11: =IF(5 = Q11, C11 * -1, C11) -> -20703.22 | V11: =IF(5 = Q11, D11 * -1, D11) -> -18666.7 | W11: =IF(5 = Q11, E11 * -1, E11) -> -21247.26 | X11: =IF(5 = Q11, F11 * -1, F11) -> -18608.65 | Y11: =IF(5 = Q11, G11 * -1, G11) -> -16892.25 | Z11: =IF(5 = Q11, H11 * -1, H11) -> -17799.09 | AA11: =IF(5 = Q11, I11 * -1, I11) -> -18065.64 | AB11: =IF(5 = Q11, J11 * -1, J11) -> -16178.15 | AC11: =IF(5 = Q11, K11 * -1, K11) -> -14469.73 | AD11: =IF(5 = Q11, L11 * -1, L11) -> -15890.83 | AE11: =IF(5 = Q11, M11 * -1, M11) -> -8271.96 | AF11: =IF(5 = Q11, N11 * -1, N11) -> -9504.2 | AG11: =IF(5 = Q11, O11 * -1, O11) -> -196297.68 | AH11: Loss to lease
A12: 5954 | B12: Monthly Yard Revenue | C12: 1574.35 | D12: 1675 | E12: 1617.07 | F12: 1610.69 | G12: 1926.57 | H12: 1904.5 | I12: 2073.58 | J12: 2076.13 | K12: 2181.6 | L12: 2755.32 | M12: 3166.53 | N12: 3339.2 | O12: 25900.54 | Q12: 4 | R12: Teagen | S12: TEA | U12: =IF(5 = Q12, C12 * -1, C12) -> 1574.35 | V12: =IF(5 = Q12, D12 * -1, D12) -> 1675 | W12: =IF(5 = Q12, E12 * -1, E12) -> 1617.07 | X12: =IF(5 = Q12, F12 * -1, F12) -> 1610.69 | Y12: =IF(5 = Q12, G12 * -1, G12) -> 1926.57 | Z12: =IF(5 = Q12, H12 * -1, H12) -> 1904.5 | AA12: =IF(5 = Q12, I12 * -1, I12) -> 2073.58 | AB12: =IF(5 = Q12, J12 * -1, J12) -> 2076.13 | AC12: =IF(5 = Q12, K12 * -1, K12) -> 2181.6 | AD12: =IF(5 = Q12, L12 * -1, L12) -> 2755.32 | AE12: =IF(5 = Q12, M12 * -1, M12) -> 3166.53 | AF12: =IF(5 = Q12, N12 * -1, N12) -> 3339.2 | AG12: =IF(5 = Q12, O12 * -1, O12) -> 25900.54 | AH12: Other
A13: 5006 | B13: Washer/Dryer | C13: -147.13 | D13: 0 | E13: 0 | F13: 0 | G13: 0 | H13: 0 | I13: 0 | J13: 0 | K13: 6.67 | L13: 235.55 | M13: 7818.72 | N13: 7840.82 | O13: 15754.63 | Q13: 4 | R13: Teagen | S13: TEA | U13: =IF(5 = Q13, C13 * -1, C13) -> -147.13 | V13: =IF(5 = Q13, D13 * -1, D13) -> 0 | W13: =IF(5 = Q13, E13 * -1, E13) -> 0 | X13: =IF(5 = Q13, F13 * -1, F13) -> 0 | Y13: =IF(5 = Q13, G13 * -1, G13) -> 0 | Z13: =IF(5 = Q13, H13 * -1, H13) -> 0 | AA13: =IF(5 = Q13, I13 * -1, I13) -> 0 | AB13: =IF(5 = Q13, J13 * -1, J13) -> 0 | AC13: =IF(5 = Q13, K13 * -1, K13) -> 6.67 | AD13: =IF(5 = Q13, L13 * -1, L13) -> 235.55 | AE13: =IF(5 = Q13, M13 * -1, M13) -> 7818.72 | AF13: =IF(5 = Q13, N13 * -1, N13) -> 7840.82 | AG13: =IF(5 = Q13, O13 * -1, O13) -> 15754.63 | AH13: Other
B14: Rental Income | C14: 256357.79 | D14: 258680.03 | E14: 260005.02 | F14: 261837.68 | G14: 260578.68 | H14: 260064.94 | I14: 260413.66 | J14: 260304.36 | K14: 262494.6 | L14: 262260.17 | M14: 269916.71 | N14: 270531.09 | O14: 3143444.7 | Q14: 4 | R14: Teagen | S14: TEA | U14: =IF(5 = Q14, C14 * -1, C14) -> 256357.79 | V14: =IF(5 = Q14, D14 * -1, D14) -> 258680.03 | W14: =IF(5 = Q14, E14 * -1, E14) -> 260005.02 | X14: =IF(5 = Q14, F14 * -1, F14) -> 261837.68 | Y14: =IF(5 = Q14, G14 * -1, G14) -> 260578.68 | Z14: =IF(5 = Q14, H14 * -1, H14) -> 260064.94 | AA14: =IF(5 = Q14, I14 * -1, I14) -> 260413.66 | AB14: =IF(5 = Q14, J14 * -1, J14) -> 260304.36 | AC14: =IF(5 = Q14, K14 * -1, K14) -> 262494.6 | AD14: =IF(5 = Q14, L14 * -1, L14) -> 262260.17 | AE14: =IF(5 = Q14, M14 * -1, M14) -> 269916.71 | AF14: =IF(5 = Q14, N14 * -1, N14) -> 270531.09 | AG14: =IF(5 = Q14, O14 * -1, O14) -> 3143444.7
Q15: 4 | R15: Teagen | S15: TEA | U15: =IF(5 = Q15, C15 * -1, C15) -> 0 | V15: =IF(5 = Q15, D15 * -1, D15) -> 0 | W15: =IF(5 = Q15, E15 * -1, E15) -> 0 | X15: =IF(5 = Q15, F15 * -1, F15) -> 0 | Y15: =IF(5 = Q15, G15 * -1, G15) -> 0 | Z15: =IF(5 = Q15, H15 * -1, H15) -> 0 | AA15: =IF(5 = Q15, I15 * -1, I15) -> 0 | AB15: =IF(5 = Q15, J15 * -1, J15) -> 0 | AC15: =IF(5 = Q15, K15 * -1, K15) -> 0 | AD15: =IF(5 = Q15, L15 * -1, L15) -> 0 | AE15: =IF(5 = Q15, M15 * -1, M15) -> 0 | AF15: =IF(5 = Q15, N15 * -1, N15) -> 0 | AG15: =IF(5 = Q15, O15 * -1, O15) -> 0
A16: Vacancy, Losses & Concessions | Q16: 4 | R16: Teagen | S16: TEA | U16: =IF(5 = Q16, C16 * -1, C16) -> 0 | V16: =IF(5 = Q16, D16 * -1, D16) -> 0 | W16: =IF(5 = Q16, E16 * -1, E16) -> 0 | X16: =IF(5 = Q16, F16 * -1, F16) -> 0 | Y16: =IF(5 = Q16, G16 * -1, G16) -> 0 | Z16: =IF(5 = Q16, H16 * -1, H16) -> 0 | AA16: =IF(5 = Q16, I16 * -1, I16) -> 0 | AB16: =IF(5 = Q16, J16 * -1, J16) -> 0 | AC16: =IF(5 = Q16, K16 * -1, K16) -> 0 | AD16: =IF(5 = Q16, L16 * -1, L16) -> 0 | AE16: =IF(5 = Q16, M16 * -1, M16) -> 0 | AF16: =IF(5 = Q16, N16 * -1, N16) -> 0 | AG16: =IF(5 = Q16, O16 * -1, O16) -> 0
A17: 5102 | B17: Delinquent Rent/Bad Debt | C17: -4074.38 | D17: -9022.6 | E17: -3280.08 | F17: -3161.13 | G17: -11395.38 | H17: -11435.88 | I17: -8348.67 | J17: -15964.4 | K17: -11211.49 | L17: -8522.61 | M17: -11145.94 | N17: -5962.15 | O17: -103524.71 | Q17: 4 | R17: Teagen | S17: TEA | U17: =IF(5 = Q17, C17 * -1, C17) -> -4074.38 | V17: =IF(5 = Q17, D17 * -1, D17) -> -9022.6 | W17: =IF(5 = Q17, E17 * -1, E17) -> -3280.08 | X17: =IF(5 = Q17, F17 * -1, F17) -> -3161.13 | Y17: =IF(5 = Q17, G17 * -1, G17) -> -11395.38 | Z17: =IF(5 = Q17, H17 * -1, H17) -> -11435.88 | AA17: =IF(5 = Q17, I17 * -1, I17) -> -8348.67 | AB17: =IF(5 = Q17, J17 * -1, J17) -> -15964.4 | AC17: =IF(5 = Q17, K17 * -1, K17) -> -11211.49 | AD17: =IF(5 = Q17, L17 * -1, L17) -> -8522.61 | AE17: =IF(5 = Q17, M17 * -1, M17) -> -11145.94 | AF17: =IF(5 = Q17, N17 * -1, N17) -> -5962.15 | AG17: =IF(5 = Q17, O17 * -1, O17) -> -103524.71 | AH17: Delinquency
A18: 5950 | B18: Bad Debt Recovery | C18: 0 | D18: 0 | E18: 0 | F18: 0 | G18: 0 | H18: 801.97 | I18: 5260.42 | J18: 0 | K18: 11656.91 | L18: 4897.48 | M18: 3507.37 | N18: 18318.31 | O18: 44442.46 | Q18: 4 | R18: Teagen | S18: TEA | U18: =IF(5 = Q18, C18 * -1, C18) -> 0 | V18: =IF(5 = Q18, D18 * -1, D18) -> 0 | W18: =IF(5 = Q18, E18 * -1, E18) -> 0 | X18: =IF(5 = Q18, F18 * -1, F18) -> 0 | Y18: =IF(5 = Q18, G18 * -1, G18) -> 0 | Z18: =IF(5 = Q18, H18 * -1, H18) -> 801.97 | AA18: =IF(5 = Q18, I18 * -1, I18) -> 5260.42 | AB18: =IF(5 = Q18, J18 * -1, J18) -> 0 | AC18: =IF(5 = Q18, K18 * -1, K18) -> 11656.91 | AD18: =IF(5 = Q18, L18 * -1, L18) -> 4897.48 | AE18: =IF(5 = Q18, M18 * -1, M18) -> 3507.37 | AF18: =IF(5 = Q18, N18 * -1, N18) -> 18318.31 | AG18: =IF(5 = Q18, O18 * -1, O18) -> 44442.46 | AH18: Other
A19: 5103 | B19: Rental Concessions | C19: -2938 | D19: -1675.88 | E19: -2874.47 | F19: -7759.25 | G19: -3024.95 | H19: -9486.11 | I19: -9028.06 | J19: -11806.63 | K19: -12838.82 | L19: -6397.75 | M19: -10670.5 | N19: -5635.6 | O19: -84136.02 | Q19: 4 | R19: Teagen | S19: TEA | U19: =IF(5 = Q19, C19 * -1, C19) -> -2938 | V19: =IF(5 = Q19, D19 * -1, D19) -> -1675.88 | W19: =IF(5 = Q19, E19 * -1, E19) -> -2874.47 | X19: =IF(5 = Q19, F19 * -1, F19) -> -7759.25 | Y19: =IF(5 = Q19, G19 * -1, G19) -> -3024.95 | Z19: =IF(5 = Q19, H19 * -1, H19) -> -9486.11 | AA19: =IF(5 = Q19, I19 * -1, I19) -> -9028.06 | AB19: =IF(5 = Q19, J19 * -1, J19) -> -11806.63 | AC19: =IF(5 = Q19, K19 * -1, K19) -> -12838.82 | AD19: =IF(5 = Q19, L19 * -1, L19) -> -6397.75 | AE19: =IF(5 = Q19, M19 * -1, M19) -> -10670.5 | AF19: =IF(5 = Q19, N19 * -1, N19) -> -5635.6 | AG19: =IF(5 = Q19, O19 * -1, O19) -> -84136.02 | AH19: Concessions
A20: 5104 | B20: Vacancy Loss | C20: -16258.8 | D20: -15479.74 | E20: -15972.75 | F20: -22854.02 | G20: -21026.49 | H20: -21367.33 | I20: -15568.18 | J20: -18879.51 | K20: -22091.78 | L20: -19608.59 | M20: -14273.23 | N20: -15773.34 | O20: -219153.76 | Q20: 4 | R20: =R19 -> Teagen | S20: =S19 -> TEA | T20: =T19 -> 0 | U20: =SUM(U10:U19) -> 505703.2 | V20: =SUM(V10:V19) -> 506661.58 | W20: =SUM(W10:W19) -> 513855.49 | X20: =SUM(X10:X19) -> 512754.98 | Y20: =SUM(Y10:Y19) -> 506737.03 | Z20: =SUM(Z10:Z19) -> 500009.86 | AA20: =SUM(AA10:AA19) -> 508711.01 | AB20: =SUM(AB10:AB19) -> 492837.69 | ... AG20: =SUM(AG10:AG19) -> 6143671.2 | AH20: Vacancy
A21: 5107 | B21: Employee Rent Discount | C21: -841.5 | D21: -961.74 | E21: -514.2 | F21: -787.5 | G21: -1179.86 | H21: -1179.86 | I21: -1179.86 | J21: -1179.86 | K21: -1179.86 | L21: -1179.86 | M21: -1179.86 | N21: -907.77 | O21: -12271.73 | AH21: Other
A22: 5110 | B22: Preferred Employer Rent Discount | C22: 0 | D22: 0 | E22: 0 | F22: 0 | G22: 0 | H22: 0 | I22: 0 | J22: 0 | K22: 0 | L22: 0 | M22: 0 | N22: -82.89 | O22: -82.89 | AH22: Vacancy
A23: 5109 | B23: Model Vacancy Loss | C23: -1065 | D23: -1065 | E23: -1065 | F23: -1065 | G23: -1065 | H23: -1065 | I23: -1065 | J23: -1065 | K23: -1065 | L23: -839 | M23: -839 | N23: -839 | O23: -12102 | Q23: 4 | R23: Teagen | S23: TEA | U23: =IF(5 = Q23, C23 * -1, C23) -> -1065 | V23: =IF(5 = Q23, D23 * -1, D23) -> -1065 | W23: =IF(5 = Q23, E23 * -1, E23) -> -1065 | X23: =IF(5 = Q23, F23 * -1, F23) -> -1065 | Y23: =IF(5 = Q23, G23 * -1, G23) -> -1065 | Z23: =IF(5 = Q23, H23 * -1, H23) -> -1065 | AA23: =IF(5 = Q23, I23 * -1, I23) -> -1065 | AB23: =IF(5 = Q23, J23 * -1, J23) -> -1065 | AC23: =IF(5 = Q23, K23 * -1, K23) -> -1065 | AD23: =IF(5 = Q23, L23 * -1, L23) -> -839 | AE23: =IF(5 = Q23, M23 * -1, M23) -> -839 | AF23: =IF(5 = Q23, N23 * -1, N23) -> -839 | AG23: =IF(5 = Q23, O23 * -1, O23) -> -12102 | AH23: Non Revenue Units
B24: Vacancy, Losses & Concessions | C24: -25177.68 | D24: -28204.96 | E24: -23706.5 | F24: -35626.9 | G24: -37691.68 | H24: -43732.21 | I24: -29929.35 | J24: -48895.4 | K24: -36730.04 | L24: -31650.33 | M24: -34601.16 | N24: -10882.44 | O24: -386828.65 | Q24: 4 | R24: Teagen | S24: TEA | U24: =IF(5 = Q24, C24 * -1, C24) -> -25177.68 | V24: =IF(5 = Q24, D24 * -1, D24) -> -28204.96 | W24: =IF(5 = Q24, E24 * -1, E24) -> -23706.5 | X24: =IF(5 = Q24, F24 * -1, F24) -> -35626.9 | Y24: =IF(5 = Q24, G24 * -1, G24) -> -37691.68 | Z24: =IF(5 = Q24, H24 * -1, H24) -> -43732.21 | AA24: =IF(5 = Q24, I24 * -1, I24) -> -29929.35 | AB24: =IF(5 = Q24, J24 * -1, J24) -> -48895.4 | AC24: =IF(5 = Q24, K24 * -1, K24) -> -36730.04 | AD24: =IF(5 = Q24, L24 * -1, L24) -> -31650.33 | AE24: =IF(5 = Q24, M24 * -1, M24) -> -34601.16 | AF24: =IF(5 = Q24, N24 * -1, N24) -> -10882.44 | AG24: =IF(5 = Q24, O24 * -1, O24) -> -386828.65
Q25: 4 | R25: Teagen | S25: TEA | U25: =IF(5 = Q25, C25 * -1, C25) -> 0 | V25: =IF(5 = Q25, D25 * -1, D25) -> 0 | W25: =IF(5 = Q25, E25 * -1, E25) -> 0 | X25: =IF(5 = Q25, F25 * -1, F25) -> 0 | Y25: =IF(5 = Q25, G25 * -1, G25) -> 0 | Z25: =IF(5 = Q25, H25 * -1, H25) -> 0 | AA25: =IF(5 = Q25, I25 * -1, I25) -> 0 | AB25: =IF(5 = Q25, J25 * -1, J25) -> 0 | AC25: =IF(5 = Q25, K25 * -1, K25) -> 0 | AD25: =IF(5 = Q25, L25 * -1, L25) -> 0 | AE25: =IF(5 = Q25, M25 * -1, M25) -> 0 | AF25: =IF(5 = Q25, N25 * -1, N25) -> 0 | AG25: =IF(5 = Q25, O25 * -1, O25) -> 0
B26: Net Rental Income | C26: 231180.11 | D26: 230475.07 | E26: 236298.52 | F26: 226210.78 | G26: 222887 | H26: 216332.73 | I26: 230484.31 | J26: 211408.96 | K26: 225764.56 | L26: 230609.84 | M26: 235315.55 | N26: 259648.65 | O26: 2756616.1 | Q26: 4 | R26: Teagen | S26: TEA | U26: =IF(5 = Q26, C26 * -1, C26) -> 231180.11 | V26: =IF(5 = Q26, D26 * -1, D26) -> 230475.07 | W26: =IF(5 = Q26, E26 * -1, E26) -> 236298.52 | X26: =IF(5 = Q26, F26 * -1, F26) -> 226210.78 | Y26: =IF(5 = Q26, G26 * -1, G26) -> 222887 | Z26: =IF(5 = Q26, H26 * -1, H26) -> 216332.73 | AA26: =IF(5 = Q26, I26 * -1, I26) -> 230484.31 | AB26: =IF(5 = Q26, J26 * -1, J26) -> 211408.96 | AC26: =IF(5 = Q26, K26 * -1, K26) -> 225764.56 | AD26: =IF(5 = Q26, L26 * -1, L26) -> 230609.84 | AE26: =IF(5 = Q26, M26 * -1, M26) -> 235315.55 | AF26: =IF(5 = Q26, N26 * -1, N26) -> 259648.65 | AG26: =IF(5 = Q26, O26 * -1, O26) -> 2756616.1
Q27: 4 | R27: Teagen | S27: TEA | U27: =IF(5 = Q27, C27 * -1, C27) -> 0 | V27: =IF(5 = Q27, D27 * -1, D27) -> 0 | W27: =IF(5 = Q27, E27 * -1, E27) -> 0 | X27: =IF(5 = Q27, F27 * -1, F27) -> 0 | Y27: =IF(5 = Q27, G27 * -1, G27) -> 0 | Z27: =IF(5 = Q27, H27 * -1, H27) -> 0 | AA27: =IF(5 = Q27, I27 * -1, I27) -> 0 | AB27: =IF(5 = Q27, J27 * -1, J27) -> 0 | AC27: =IF(5 = Q27, K27 * -1, K27) -> 0 | AD27: =IF(5 = Q27, L27 * -1, L27) -> 0 | AE27: =IF(5 = Q27, M27 * -1, M27) -> 0 | AF27: =IF(5 = Q27, N27 * -1, N27) -> 0 | AG27: =IF(5 = Q27, O27 * -1, O27) -> 0
A28: Other Income | Q28: 4 | R28: Teagen | S28: TEA | U28: =IF(5 = Q28, C28 * -1, C28) -> 0 | V28: =IF(5 = Q28, D28 * -1, D28) -> 0 | W28: =IF(5 = Q28, E28 * -1, E28) -> 0 | X28: =IF(5 = Q28, F28 * -1, F28) -> 0 | Y28: =IF(5 = Q28, G28 * -1, G28) -> 0 | Z28: =IF(5 = Q28, H28 * -1, H28) -> 0 | AA28: =IF(5 = Q28, I28 * -1, I28) -> 0 | AB28: =IF(5 = Q28, J28 * -1, J28) -> 0 | AC28: =IF(5 = Q28, K28 * -1, K28) -> 0 | AD28: =IF(5 = Q28, L28 * -1, L28) -> 0 | AE28: =IF(5 = Q28, M28 * -1, M28) -> 0 | AF28: =IF(5 = Q28, N28 * -1, N28) -> 0 | AG28: =IF(5 = Q28, O28 * -1, O28) -> 0
A29: 5007 | B29: Other Income - Monthly Pet Rent | C29: 1435.58 | D29: 1672.67 | E29: 1583.91 | F29: 1475.17 | G29: 1491.55 | H29: 1374.68 | I29: 1532.01 | J29: 1448.71 | K29: 1413 | L29: 1361.6 | M29: 1338 | N29: 1351.16 | O29: 17478.04 | Q29: 4 | R29: Teagen | S29: TEA | U29: =IF(5 = Q29, C29 * -1, C29) -> 1435.58 | V29: =IF(5 = Q29, D29 * -1, D29) -> 1672.67 | W29: =IF(5 = Q29, E29 * -1, E29) -> 1583.91 | X29: =IF(5 = Q29, F29 * -1, F29) -> 1475.17 | Y29: =IF(5 = Q29, G29 * -1, G29) -> 1491.55 | Z29: =IF(5 = Q29, H29 * -1, H29) -> 1374.68 | AA29: =IF(5 = Q29, I29 * -1, I29) -> 1532.01 | AB29: =IF(5 = Q29, J29 * -1, J29) -> 1448.71 | AC29: =IF(5 = Q29, K29 * -1, K29) -> 1413 | AD29: =IF(5 = Q29, L29 * -1, L29) -> 1361.6 | AE29: =IF(5 = Q29, M29 * -1, M29) -> 1338 | AF29: =IF(5 = Q29, N29 * -1, N29) -> 1351.16 | AG29: =IF(5 = Q29, O29 * -1, O29) -> 17478.04 | AH29: Other
A30: 5013 | B30: Other Income - Washer/Dryer Rental | C30: 5834.5 | D30: 6419.63 | E30: 6549.65 | F30: 6153.55 | G30: 6702.92 | H30: 6884.73 | I30: 7125.52 | J30: 7459.37 | K30: 7014.61 | L30: 7267.37 | M30: 0 | N30: 0 | O30: 67411.85 | Q30: 4 | R30: Teagen | S30: TEA | U30: =IF(5 = Q30, C30 * -1, C30) -> 5834.5 | V30: =IF(5 = Q30, D30 * -1, D30) -> 6419.63 | W30: =IF(5 = Q30, E30 * -1, E30) -> 6549.65 | X30: =IF(5 = Q30, F30 * -1, F30) -> 6153.55 | Y30: =IF(5 = Q30, G30 * -1, G30) -> 6702.92 | Z30: =IF(5 = Q30, H30 * -1, H30) -> 6884.73 | AA30: =IF(5 = Q30, I30 * -1, I30) -> 7125.52 | AB30: =IF(5 = Q30, J30 * -1, J30) -> 7459.37 | AC30: =IF(5 = Q30, K30 * -1, K30) -> 7014.61 | AD30: =IF(5 = Q30, L30 * -1, L30) -> 7267.37 | AE30: =IF(5 = Q30, M30 * -1, M30) -> 0 | AF30: =IF(5 = Q30, N30 * -1, N30) -> 0 | AG30: =IF(5 = Q30, O30 * -1, O30) -> 67411.85 | AH30: Other
A31: 5202 | B31: Other Income - Cable TV Income | C31: 0 | D31: 1778.02 | E31: 0 | F31: 0 | G31: 1815.18 | H31: 0 | I31: 0 | J31: 1619.51 | K31: 0 | L31: 0 | M31: 1709.16 | N31: 0 | O31: 6921.87 | Q31: 4 | R31: Teagen | S31: TEA | U31: =IF(5 = Q31, C31 * -1, C31) -> 0 | V31: =IF(5 = Q31, D31 * -1, D31) -> 1778.02 | W31: =IF(5 = Q31, E31 * -1, E31) -> 0 | X31: =IF(5 = Q31, F31 * -1, F31) -> 0 | Y31: =IF(5 = Q31, G31 * -1, G31) -> 1815.18 | Z31: =IF(5 = Q31, H31 * -1, H31) -> 0 | AA31: =IF(5 = Q31, I31 * -1, I31) -> 0 | AB31: =IF(5 = Q31, J31 * -1, J31) -> 1619.51 | AC31: =IF(5 = Q31, K31 * -1, K31) -> 0 | AD31: =IF(5 = Q31, L31 * -1, L31) -> 0 | AE31: =IF(5 = Q31, M31 * -1, M31) -> 1709.16 | AF31: =IF(5 = Q31, N31 * -1, N31) -> 0 | AG31: =IF(5 = Q31, O31 * -1, O31) -> 6921.87 | AH31: Other
A32: 5204 | B32: Other Income - Loss Damage Waiver | C32: 4271.18 | D32: 4264.78 | E32: 4273.45 | F32: 4210.35 | G32: 4258.97 | H32: 4290.01 | I32: 4428.15 | J32: 4392.24 | K32: 4380.39 | L32: 4484.2 | M32: 4591.86 | N32: 4618.45 | O32: 52464.03 | Q32: 4 | R32: Teagen | S32: TEA | U32: =IF(5 = Q32, C32 * -1, C32) -> 4271.18 | V32: =IF(5 = Q32, D32 * -1, D32) -> 4264.78 | W32: =IF(5 = Q32, E32 * -1, E32) -> 4273.45 | X32: =IF(5 = Q32, F32 * -1, F32) -> 4210.35 | Y32: =IF(5 = Q32, G32 * -1, G32) -> 4258.97 | Z32: =IF(5 = Q32, H32 * -1, H32) -> 4290.01 | AA32: =IF(5 = Q32, I32 * -1, I32) -> 4428.15 | AB32: =IF(5 = Q32, J32 * -1, J32) -> 4392.24 | AC32: =IF(5 = Q32, K32 * -1, K32) -> 4380.39 | AD32: =IF(5 = Q32, L32 * -1, L32) -> 4484.2 | AE32: =IF(5 = Q32, M32 * -1, M32) -> 4591.86 | AF32: =IF(5 = Q32, N32 * -1, N32) -> 4618.45 | AG32: =IF(5 = Q32, O32 * -1, O32) -> 52464.03 | AH32: Other
A33: 5205 | B33: Other Income - Conditional Fees | C33: 0 | D33: 0 | E33: 0 | F33: 0 | G33: 0 | H33: 0 | I33: 0 | J33: 0 | K33: 2000 | L33: 3000 | M33: 2000 | N33: 0 | O33: 7000 | Q33: 4 | R33: Teagen | S33: TEA | U33: =IF(5 = Q33, C33 * -1, C33) -> 0 | V33: =IF(5 = Q33, D33 * -1, D33) -> 0 | W33: =IF(5 = Q33, E33 * -1, E33) -> 0 | X33: =IF(5 = Q33, F33 * -1, F33) -> 0 | Y33: =IF(5 = Q33, G33 * -1, G33) -> 0 | Z33: =IF(5 = Q33, H33 * -1, H33) -> 0 | AA33: =IF(5 = Q33, I33 * -1, I33) -> 0 | AB33: =IF(5 = Q33, J33 * -1, J33) -> 0 | AC33: =IF(5 = Q33, K33 * -1, K33) -> 2000 | AD33: =IF(5 = Q33, L33 * -1, L33) -> 3000 | AE33: =IF(5 = Q33, M33 * -1, M33) -> 2000 | AF33: =IF(5 = Q33, N33 * -1, N33) -> 0 | AG33: =IF(5 = Q33, O33 * -1, O33) -> 7000 | AH33: Other
A34: 5211 | B34: Other Income - Water/Sewer Reimbursements | C34: 14756.57 | D34: 20075.59 | E34: 17871.27 | F34: 14651.06 | G34: 22486.9 | H34: 19185.04 | I34: 20364.79 | J34: 19386.27 | K34: 13688.34 | L34: 18777.85 | M34: 15811.63 | N34: 16539.64 | O34: 213594.95 | Q34: 4 | R34: Teagen | S34: TEA | U34: =IF(5 = Q34, C34 * -1, C34) -> 14756.57 | V34: =IF(5 = Q34, D34 * -1, D34) -> 20075.59 | W34: =IF(5 = Q34, E34 * -1, E34) -> 17871.27 | X34: =IF(5 = Q34, F34 * -1, F34) -> 14651.06 | Y34: =IF(5 = Q34, G34 * -1, G34) -> 22486.9 | Z34: =IF(5 = Q34, H34 * -1, H34) -> 19185.04 | AA34: =IF(5 = Q34, I34 * -1, I34) -> 20364.79 | AB34: =IF(5 = Q34, J34 * -1, J34) -> 19386.27 | AC34: =IF(5 = Q34, K34 * -1, K34) -> 13688.34 | AD34: =IF(5 = Q34, L34 * -1, L34) -> 18777.85 | AE34: =IF(5 = Q34, M34 * -1, M34) -> 15811.63 | AF34: =IF(5 = Q34, N34 * -1, N34) -> 16539.64 | AG34: =IF(5 = Q34, O34 * -1, O34) -> 213594.95 | AH34: Other
A35: 5212 | B35: Other Income - Trash Reimbursements | C35: 10823.08 | D35: 10749.88 | E35: 10756.78 | F35: 10593.18 | G35: 10633.19 | H35: 10610.51 | I35: 10877.2 | J35: 10688.89 | K35: 10659.37 | L35: 10815.55 | M35: 10962.75 | N35: 11066.79 | O35: 129237.17 | Q35: 4 | R35: Teagen | S35: TEA | U35: =IF(5 = Q35, C35 * -1, C35) -> 10823.08 | V35: =IF(5 = Q35, D35 * -1, D35) -> 10749.88 | W35: =IF(5 = Q35, E35 * -1, E35) -> 10756.78 | X35: =IF(5 = Q35, F35 * -1, F35) -> 10593.18 | Y35: =IF(5 = Q35, G35 * -1, G35) -> 10633.19 | Z35: =IF(5 = Q35, H35 * -1, H35) -> 10610.51 | AA35: =IF(5 = Q35, I35 * -1, I35) -> 10877.2 | AB35: =IF(5 = Q35, J35 * -1, J35) -> 10688.89 | AC35: =IF(5 = Q35, K35 * -1, K35) -> 10659.37 | AD35: =IF(5 = Q35, L35 * -1, L35) -> 10815.55 | AE35: =IF(5 = Q35, M35 * -1, M35) -> 10962.75 | AF35: =IF(5 = Q35, N35 * -1, N35) -> 11066.79 | AG35: =IF(5 = Q35, O35 * -1, O35) -> 129237.17 | AH35: Other
A36: 5220 | B36: Other Income - Pest Control Reimbursement | C36: 2276.63 | D36: 2269.5 | E36: 2265.95 | F36: 2221.31 | G36: 2241.37 | H36: 2236.77 | I36: 2291.61 | J36: 2258.58 | K36: 2235.97 | L36: 2203.93 | M36: 2116.57 | N36: 1986.52 | O36: 26604.71 | Q36: 4 | R36: =R35 -> Teagen | S36: =S35 -> TEA | T36: =T35 -> 0 | U36: =SUM(U23:U35) -> 242058.34 | V36: =SUM(V23:V35) -> 246165.68 | W36: =SUM(W23:W35) -> 252562.08 | X36: =SUM(X23:X35) -> 226602.19 | Y36: =SUM(Y23:Y35) -> 231519.03 | Z36: =SUM(Z23:Z35) -> 213880.49 | AA36: =SUM(AA23:AA35) -> 243817.63 | AB36: =SUM(AB23:AB35) -> 206443.55 | ... AG36: =SUM(AG23:AG35) -> 2851793.3 | AH36: Other
A37: 5804 | B37: Other Income - Amenity Fee | C37: 2890.72 | D37: 2887.61 | E37: 2881.98 | F37: 2867.49 | G37: 2962.51 | H37: 3020.08 | I37: 3159.36 | J37: 3170.01 | K37: 3172.01 | L37: 3144.56 | M37: 3042.66 | N37: 2839.16 | O37: 36038.15 | AH37: Other
A38: 5805 | B38: Other Income - Late Charges | C38: 4050 | D38: 3950 | E38: 3200 | F38: 4200 | G38: 3250 | H38: 3650 | I38: 4600 | J38: 3700 | K38: 4700 | L38: 3100 | M38: 2650 | N38: 4150 | O38: 45200 | Q38: 4 | R38: =R35 -> Teagen | S38: =S35 -> TEA | T38: =T35 -> 0 | U38: =SUM(U10:U19)+SUM(U23:U35) -> 747761.54 | V38: =SUM(V10:V19)+SUM(V23:V35) -> 752827.26 | W38: =SUM(W10:W19)+SUM(W23:W35) -> 766417.57 | X38: =SUM(X10:X19)+SUM(X23:X35) -> 739357.17 | Y38: =SUM(Y10:Y19)+SUM(Y23:Y35) -> 738256.06 | Z38: =SUM(Z10:Z19)+SUM(Z23:Z35) -> 713890.35 | AA38: =SUM(AA10:AA19)+SUM(AA23:AA35) -> 752528.64 | AB38: =SUM(AB10:AB19)+SUM(AB23:AB35) -> 699281.24 | ... AG38: =SUM(AG10:AG19)+SUM(AG23:AG35) -> 8995464.5 | AH38: Other
A39: 5860 | B39: Other Income - Parcel Services Income | C39: 2565.41 | D39: 2562.71 | E39: 2573.96 | F39: 2544.38 | G39: 2601.93 | H39: 2628.41 | I39: 2725.48 | J39: 2714.26 | K39: 2711.96 | L39: 2695.5 | M39: 2603.6 | N39: 2452.29 | O39: 31379.89 | AH39: Other
A40: 5861 | B40: Other Income - Lease Lock | C40: 4746.1 | D40: 5212.33 | E40: 5675.69 | F40: 6153.54 | G40: 6680.23 | H40: 7024.97 | I40: 7530.88 | J40: 7487.81 | K40: 7565.76 | L40: 7894.82 | M40: 8093.41 | N40: 8169.25 | O40: 82234.79 | AH40: Other
A41: 5890 | B41: Other Income - Miscellaneous Income | C41: 112.12 | D41: 50 | E41: 275 | F41: 860 | G41: 415 | H41: 536.85 | I41: 358.15 | J41: 465.6 | K41: 768.75 | L41: 1059 | M41: 1604.1 | N41: 1510.05 | O41: 8014.62 | Q41: 4 | R41: Teagen | S41: TEA | U41: =IF(5 = Q41, C41 * -1, C41) -> 112.12 | V41: =IF(5 = Q41, D41 * -1, D41) -> 50 | W41: =IF(5 = Q41, E41 * -1, E41) -> 275 | X41: =IF(5 = Q41, F41 * -1, F41) -> 860 | Y41: =IF(5 = Q41, G41 * -1, G41) -> 415 | Z41: =IF(5 = Q41, H41 * -1, H41) -> 536.85 | AA41: =IF(5 = Q41, I41 * -1, I41) -> 358.15 | AB41: =IF(5 = Q41, J41 * -1, J41) -> 465.6 | AC41: =IF(5 = Q41, K41 * -1, K41) -> 768.75 | AD41: =IF(5 = Q41, L41 * -1, L41) -> 1059 | AE41: =IF(5 = Q41, M41 * -1, M41) -> 1604.1 | AF41: =IF(5 = Q41, N41 * -1, N41) -> 1510.05 | AG41: =IF(5 = Q41, O41 * -1, O41) -> 8014.62 | AH41: Other
A42: 5891 | B42: Other Income - NSF Charges | C42: 917.31 | D42: 582.69 | E42: 450 | F42: 375 | G42: 75 | H42: 150 | I42: 225 | J42: 150 | K42: 225 | L42: 225 | M42: 75 | N42: 150 | O42: 3600 | Q42: 4 | R42: Teagen | S42: TEA | U42: =IF(5 = Q42, C42 * -1, C42) -> 917.31 | V42: =IF(5 = Q42, D42 * -1, D42) -> 582.69 | W42: =IF(5 = Q42, E42 * -1, E42) -> 450 | X42: =IF(5 = Q42, F42 * -1, F42) -> 375 | Y42: =IF(5 = Q42, G42 * -1, G42) -> 75 | Z42: =IF(5 = Q42, H42 * -1, H42) -> 150 | AA42: =IF(5 = Q42, I42 * -1, I42) -> 225 | AB42: =IF(5 = Q42, J42 * -1, J42) -> 150 | AC42: =IF(5 = Q42, K42 * -1, K42) -> 225 | AD42: =IF(5 = Q42, L42 * -1, L42) -> 225 | AE42: =IF(5 = Q42, M42 * -1, M42) -> 75 | AF42: =IF(5 = Q42, N42 * -1, N42) -> 150 | AG42: =IF(5 = Q42, O42 * -1, O42) -> 3600 | AH42: Other
A43: 5892 | B43: Other Income - Non-Refundable Pet Fee | C43: 779.4 | D43: 2100 | E43: 600 | F43: 1200 | G43: 1200 | H43: 2400 | I43: 400 | J43: 1200 | K43: 800 | L43: 800 | M43: 0 | N43: 1600 | O43: 13079.4 | Q43: 4 | R43: Teagen | S43: TEA | U43: =IF(5 = Q43, C43 * -1, C43) -> 779.4 | V43: =IF(5 = Q43, D43 * -1, D43) -> 2100 | W43: =IF(5 = Q43, E43 * -1, E43) -> 600 | X43: =IF(5 = Q43, F43 * -1, F43) -> 1200 | Y43: =IF(5 = Q43, G43 * -1, G43) -> 1200 | Z43: =IF(5 = Q43, H43 * -1, H43) -> 2400 | AA43: =IF(5 = Q43, I43 * -1, I43) -> 400 | AB43: =IF(5 = Q43, J43 * -1, J43) -> 1200 | AC43: =IF(5 = Q43, K43 * -1, K43) -> 800 | AD43: =IF(5 = Q43, L43 * -1, L43) -> 800 | AE43: =IF(5 = Q43, M43 * -1, M43) -> 0 | AF43: =IF(5 = Q43, N43 * -1, N43) -> 1600 | AG43: =IF(5 = Q43, O43 * -1, O43) -> 13079.4 | AH43: Other
A44: 5893 | B44: Other Income - Damages | C44: 5234.87 | D44: 1361 | E44: 1855.16 | F44: 803.06 | G44: 3075.88 | H44: 2159.95 | I44: 2710.58 | J44: 535 | K44: 5383.8 | L44: 2505.37 | M44: 853.13 | N44: 5115.06 | O44: 31592.86 | Q44: 4 | R44: Teagen | S44: TEA | U44: =IF(5 = Q44, C44 * -1, C44) -> 5234.87 | V44: =IF(5 = Q44, D44 * -1, D44) -> 1361 | W44: =IF(5 = Q44, E44 * -1, E44) -> 1855.16 | X44: =IF(5 = Q44, F44 * -1, F44) -> 803.06 | Y44: =IF(5 = Q44, G44 * -1, G44) -> 3075.88 | Z44: =IF(5 = Q44, H44 * -1, H44) -> 2159.95 | AA44: =IF(5 = Q44, I44 * -1, I44) -> 2710.58 | AB44: =IF(5 = Q44, J44 * -1, J44) -> 535 | AC44: =IF(5 = Q44, K44 * -1, K44) -> 5383.8 | AD44: =IF(5 = Q44, L44 * -1, L44) -> 2505.37 | AE44: =IF(5 = Q44, M44 * -1, M44) -> 853.13 | AF44: =IF(5 = Q44, N44 * -1, N44) -> 5115.06 | AG44: =IF(5 = Q44, O44 * -1, O44) -> 31592.86 | AH44: Other
A45: 5894 | B45: Other Income - Transfer Fee | C45: 0 | D45: 0 | E45: 0 | F45: 0 | G45: 0 | H45: 0 | I45: 0 | J45: 0 | K45: 0 | L45: 1000 | M45: 0 | N45: 500 | O45: 1500 | Q45: 4 | R45: Teagen | S45: TEA | U45: =IF(5 = Q45, C45 * -1, C45) -> 0 | V45: =IF(5 = Q45, D45 * -1, D45) -> 0 | W45: =IF(5 = Q45, E45 * -1, E45) -> 0 | X45: =IF(5 = Q45, F45 * -1, F45) -> 0 | Y45: =IF(5 = Q45, G45 * -1, G45) -> 0 | Z45: =IF(5 = Q45, H45 * -1, H45) -> 0 | AA45: =IF(5 = Q45, I45 * -1, I45) -> 0 | AB45: =IF(5 = Q45, J45 * -1, J45) -> 0 | AC45: =IF(5 = Q45, K45 * -1, K45) -> 0 | AD45: =IF(5 = Q45, L45 * -1, L45) -> 1000 | AE45: =IF(5 = Q45, M45 * -1, M45) -> 0 | AF45: =IF(5 = Q45, N45 * -1, N45) -> 500 | AG45: =IF(5 = Q45, O45 * -1, O45) -> 1500 | AH45: Other
A46: 5896 | B46: Other Income - Application Fee | C46: 1175 | D46: 500 | E46: 975 | F46: 1425 | G46: 2000 | H46: 2100 | I46: 3200 | J46: 2375 | K46: 2525 | L46: 1550 | M46: 1225 | N46: 1975 | O46: 21025 | Q46: 4 | R46: Teagen | S46: TEA | U46: =IF(5 = Q46, C46 * -1, C46) -> 1175 | V46: =IF(5 = Q46, D46 * -1, D46) -> 500 | W46: =IF(5 = Q46, E46 * -1, E46) -> 975 | X46: =IF(5 = Q46, F46 * -1, F46) -> 1425 | Y46: =IF(5 = Q46, G46 * -1, G46) -> 2000 | Z46: =IF(5 = Q46, H46 * -1, H46) -> 2100 | AA46: =IF(5 = Q46, I46 * -1, I46) -> 3200 | AB46: =IF(5 = Q46, J46 * -1, J46) -> 2375 | AC46: =IF(5 = Q46, K46 * -1, K46) -> 2525 | AD46: =IF(5 = Q46, L46 * -1, L46) -> 1550 | AE46: =IF(5 = Q46, M46 * -1, M46) -> 1225 | AF46: =IF(5 = Q46, N46 * -1, N46) -> 1975 | AG46: =IF(5 = Q46, O46 * -1, O46) -> 21025 | AH46: Other
A47: 5897 | B47: Other Income - Non-Refundable Gate/Pool/Fitness Fee | C47: 800 | D47: 400 | E47: 600 | F47: 700 | G47: 1050 | H47: 800 | I47: 1000 | J47: 450 | K47: 1000 | L47: 750 | M47: 550 | N47: 700 | O47: 8800 | Q47: 4 | R47: Teagen | S47: TEA | U47: =IF(5 = Q47, C47 * -1, C47) -> 800 | V47: =IF(5 = Q47, D47 * -1, D47) -> 400 | W47: =IF(5 = Q47, E47 * -1, E47) -> 600 | X47: =IF(5 = Q47, F47 * -1, F47) -> 700 | Y47: =IF(5 = Q47, G47 * -1, G47) -> 1050 | Z47: =IF(5 = Q47, H47 * -1, H47) -> 800 | AA47: =IF(5 = Q47, I47 * -1, I47) -> 1000 | AB47: =IF(5 = Q47, J47 * -1, J47) -> 450 | AC47: =IF(5 = Q47, K47 * -1, K47) -> 1000 | AD47: =IF(5 = Q47, L47 * -1, L47) -> 750 | AE47: =IF(5 = Q47, M47 * -1, M47) -> 550 | AF47: =IF(5 = Q47, N47 * -1, N47) -> 700 | AG47: =IF(5 = Q47, O47 * -1, O47) -> 8800 | AH47: Other
A48: 5898 | B48: Other Income - Cancellation Fee | C48: 2839.95 | D48: 0 | E48: 1098.93 | F48: 2829 | G48: 1344.02 | H48: 1774.87 | I48: 5187.01 | J48: 1174 | K48: 5680.71 | L48: 278.6 | M48: 1256.55 | N48: 755.98 | O48: 24219.62 | Q48: 4 | R48: Teagen | S48: TEA | U48: =IF(5 = Q48, C48 * -1, C48) -> 2839.95 | V48: =IF(5 = Q48, D48 * -1, D48) -> 0 | W48: =IF(5 = Q48, E48 * -1, E48) -> 1098.93 | X48: =IF(5 = Q48, F48 * -1, F48) -> 2829 | Y48: =IF(5 = Q48, G48 * -1, G48) -> 1344.02 | Z48: =IF(5 = Q48, H48 * -1, H48) -> 1774.87 | AA48: =IF(5 = Q48, I48 * -1, I48) -> 5187.01 | AB48: =IF(5 = Q48, J48 * -1, J48) -> 1174 | AC48: =IF(5 = Q48, K48 * -1, K48) -> 5680.71 | AD48: =IF(5 = Q48, L48 * -1, L48) -> 278.6 | AE48: =IF(5 = Q48, M48 * -1, M48) -> 1256.55 | AF48: =IF(5 = Q48, N48 * -1, N48) -> 755.98 | AG48: =IF(5 = Q48, O48 * -1, O48) -> 24219.62 | AH48: Other
A49: 5899 | B49: Other Income - Non-Refundable Admin Fee | C49: 2950 | D49: 400 | E49: 2000 | F49: 2800 | G49: 4200 | H49: 3400 | I49: 4200 | J49: 1950 | K49: 4600 | L49: 3075 | M49: 2200 | N49: 2475 | O49: 34250 | Q49: 4 | R49: Teagen | S49: TEA | U49: =IF(5 = Q49, C49 * -1, C49) -> 2950 | V49: =IF(5 = Q49, D49 * -1, D49) -> 400 | W49: =IF(5 = Q49, E49 * -1, E49) -> 2000 | X49: =IF(5 = Q49, F49 * -1, F49) -> 2800 | Y49: =IF(5 = Q49, G49 * -1, G49) -> 4200 | Z49: =IF(5 = Q49, H49 * -1, H49) -> 3400 | AA49: =IF(5 = Q49, I49 * -1, I49) -> 4200 | AB49: =IF(5 = Q49, J49 * -1, J49) -> 1950 | AC49: =IF(5 = Q49, K49 * -1, K49) -> 4600 | AD49: =IF(5 = Q49, L49 * -1, L49) -> 3075 | AE49: =IF(5 = Q49, M49 * -1, M49) -> 2200 | AF49: =IF(5 = Q49, N49 * -1, N49) -> 2475 | AG49: =IF(5 = Q49, O49 * -1, O49) -> 34250 | AH49: Other
B50: Other Income | C50: 68458.42 | D50: 67236.41 | E50: 65486.73 | F50: 66062.09 | G50: 78484.65 | H50: 74226.87 | I50: 81915.74 | J50: 72625.25 | K50: 80524.67 | L50: 75988.35 | M50: 62683.42 | N50: 67954.35 | O50: 861646.95 | Q50: 4 | R50: Teagen | S50: TEA | U50: =IF(5 = Q50, C50 * -1, C50) -> 68458.42 | V50: =IF(5 = Q50, D50 * -1, D50) -> 67236.41 | W50: =IF(5 = Q50, E50 * -1, E50) -> 65486.73 | X50: =IF(5 = Q50, F50 * -1, F50) -> 66062.09 | Y50: =IF(5 = Q50, G50 * -1, G50) -> 78484.65 | Z50: =IF(5 = Q50, H50 * -1, H50) -> 74226.87 | AA50: =IF(5 = Q50, I50 * -1, I50) -> 81915.74 | AB50: =IF(5 = Q50, J50 * -1, J50) -> 72625.25 | AC50: =IF(5 = Q50, K50 * -1, K50) -> 80524.67 | AD50: =IF(5 = Q50, L50 * -1, L50) -> 75988.35 | AE50: =IF(5 = Q50, M50 * -1, M50) -> 62683.42 | AF50: =IF(5 = Q50, N50 * -1, N50) -> 67954.35 | AG50: =IF(5 = Q50, O50 * -1, O50) -> 861646.95
Q51: 4 | R51: Teagen | S51: TEA | U51: =IF(5 = Q51, C51 * -1, C51) -> 0 | V51: =IF(5 = Q51, D51 * -1, D51) -> 0 | W51: =IF(5 = Q51, E51 * -1, E51) -> 0 | X51: =IF(5 = Q51, F51 * -1, F51) -> 0 | Y51: =IF(5 = Q51, G51 * -1, G51) -> 0 | Z51: =IF(5 = Q51, H51 * -1, H51) -> 0 | AA51: =IF(5 = Q51, I51 * -1, I51) -> 0 | AB51: =IF(5 = Q51, J51 * -1, J51) -> 0 | AC51: =IF(5 = Q51, K51 * -1, K51) -> 0 | AD51: =IF(5 = Q51, L51 * -1, L51) -> 0 | AE51: =IF(5 = Q51, M51 * -1, M51) -> 0 | AF51: =IF(5 = Q51, N51 * -1, N51) -> 0 | AG51: =IF(5 = Q51, O51 * -1, O51) -> 0
B52: Income | C52: 299638.53 | D52: 297711.48 | E52: 301785.25 | F52: 292272.87 | G52: 301371.65 | H52: 290559.6 | I52: 312400.05 | J52: 284034.21 | K52: 306289.23 | L52: 306598.19 | M52: 297998.97 | N52: 327603 | O52: 3618263 | Q52: 4 | R52: Teagen | S52: TEA | U52: =IF(5 = Q52, C52 * -1, C52) -> 299638.53 | V52: =IF(5 = Q52, D52 * -1, D52) -> 297711.48 | W52: =IF(5 = Q52, E52 * -1, E52) -> 301785.25 | X52: =IF(5 = Q52, F52 * -1, F52) -> 292272.87 | Y52: =IF(5 = Q52, G52 * -1, G52) -> 301371.65 | Z52: =IF(5 = Q52, H52 * -1, H52) -> 290559.6 | AA52: =IF(5 = Q52, I52 * -1, I52) -> 312400.05 | AB52: =IF(5 = Q52, J52 * -1, J52) -> 284034.21 | AC52: =IF(5 = Q52, K52 * -1, K52) -> 306289.23 | AD52: =IF(5 = Q52, L52 * -1, L52) -> 306598.19 | AE52: =IF(5 = Q52, M52 * -1, M52) -> 297998.97 | AF52: =IF(5 = Q52, N52 * -1, N52) -> 327603 | AG52: =IF(5 = Q52, O52 * -1, O52) -> 3618263
Q53: 4 | R53: Teagen | S53: TEA | U53: =IF(5 = Q53, C53 * -1, C53) -> 0 | V53: =IF(5 = Q53, D53 * -1, D53) -> 0 | W53: =IF(5 = Q53, E53 * -1, E53) -> 0 | X53: =IF(5 = Q53, F53 * -1, F53) -> 0 | Y53: =IF(5 = Q53, G53 * -1, G53) -> 0 | Z53: =IF(5 = Q53, H53 * -1, H53) -> 0 | AA53: =IF(5 = Q53, I53 * -1, I53) -> 0 | AB53: =IF(5 = Q53, J53 * -1, J53) -> 0 | AC53: =IF(5 = Q53, K53 * -1, K53) -> 0 | AD53: =IF(5 = Q53, L53 * -1, L53) -> 0 | AE53: =IF(5 = Q53, M53 * -1, M53) -> 0 | AF53: =IF(5 = Q53, N53 * -1, N53) -> 0 | AG53: =IF(5 = Q53, O53 * -1, O53) -> 0
A54: Operating Expenses | Q54: 4 | R54: Teagen | S54: TEA | U54: =IF(5 = Q54, C54 * -1, C54) -> 0 | V54: =IF(5 = Q54, D54 * -1, D54) -> 0 | W54: =IF(5 = Q54, E54 * -1, E54) -> 0 | X54: =IF(5 = Q54, F54 * -1, F54) -> 0 | Y54: =IF(5 = Q54, G54 * -1, G54) -> 0 | Z54: =IF(5 = Q54, H54 * -1, H54) -> 0 | AA54: =IF(5 = Q54, I54 * -1, I54) -> 0 | AB54: =IF(5 = Q54, J54 * -1, J54) -> 0 | AC54: =IF(5 = Q54, K54 * -1, K54) -> 0 | AD54: =IF(5 = Q54, L54 * -1, L54) -> 0 | AE54: =IF(5 = Q54, M54 * -1, M54) -> 0 | AF54: =IF(5 = Q54, N54 * -1, N54) -> 0 | AG54: =IF(5 = Q54, O54 * -1, O54) -> 0
A55: Payroll & Related | Q55: 4 | R55: Teagen | S55: TEA | U55: =IF(5 = Q55, C55 * -1, C55) -> 0 | V55: =IF(5 = Q55, D55 * -1, D55) -> 0 | W55: =IF(5 = Q55, E55 * -1, E55) -> 0 | X55: =IF(5 = Q55, F55 * -1, F55) -> 0 | Y55: =IF(5 = Q55, G55 * -1, G55) -> 0 | Z55: =IF(5 = Q55, H55 * -1, H55) -> 0 | AA55: =IF(5 = Q55, I55 * -1, I55) -> 0 | AB55: =IF(5 = Q55, J55 * -1, J55) -> 0 | AC55: =IF(5 = Q55, K55 * -1, K55) -> 0 | AD55: =IF(5 = Q55, L55 * -1, L55) -> 0 | AE55: =IF(5 = Q55, M55 * -1, M55) -> 0 | AF55: =IF(5 = Q55, N55 * -1, N55) -> 0 | AG55: =IF(5 = Q55, O55 * -1, O55) -> 0
A56: Payroll | Q56: 4 | R56: Teagen | S56: TEA | U56: =IF(5 = Q56, C56 * -1, C56) -> 0 | V56: =IF(5 = Q56, D56 * -1, D56) -> 0 | W56: =IF(5 = Q56, E56 * -1, E56) -> 0 | X56: =IF(5 = Q56, F56 * -1, F56) -> 0 | Y56: =IF(5 = Q56, G56 * -1, G56) -> 0 | Z56: =IF(5 = Q56, H56 * -1, H56) -> 0 | AA56: =IF(5 = Q56, I56 * -1, I56) -> 0 | AB56: =IF(5 = Q56, J56 * -1, J56) -> 0 | AC56: =IF(5 = Q56, K56 * -1, K56) -> 0 | AD56: =IF(5 = Q56, L56 * -1, L56) -> 0 | AE56: =IF(5 = Q56, M56 * -1, M56) -> 0 | AF56: =IF(5 = Q56, N56 * -1, N56) -> 0 | AG56: =IF(5 = Q56, O56 * -1, O56) -> 0
A57: 7008 | B57: Payroll - Manager | C57: 5384.6 | D57: 5384.61 | E57: 8076.9 | F57: 5384.6 | G57: 5384.6 | H57: 5384.6 | I57: 5384.6 | J57: 8076.91 | K57: 5769.23 | L57: 5769.24 | M57: 5769.23 | N57: 5769.23 | O57: 71538.35 | Q57: 4 | R57: Teagen | S57: TEA | U57: =IF(5 = Q57, C57 * -1, C57) -> 5384.6 | V57: =IF(5 = Q57, D57 * -1, D57) -> 5384.61 | W57: =IF(5 = Q57, E57 * -1, E57) -> 8076.9 | X57: =IF(5 = Q57, F57 * -1, F57) -> 5384.6 | Y57: =IF(5 = Q57, G57 * -1, G57) -> 5384.6 | Z57: =IF(5 = Q57, H57 * -1, H57) -> 5384.6 | AA57: =IF(5 = Q57, I57 * -1, I57) -> 5384.6 | AB57: =IF(5 = Q57, J57 * -1, J57) -> 8076.91 | AC57: =IF(5 = Q57, K57 * -1, K57) -> 5769.23 | AD57: =IF(5 = Q57, L57 * -1, L57) -> 5769.24 | AE57: =IF(5 = Q57, M57 * -1, M57) -> 5769.23 | AF57: =IF(5 = Q57, N57 * -1, N57) -> 5769.23 | AG57: =IF(5 = Q57, O57 * -1, O57) -> 71538.35 | AH57: Payroll
A58: 7012 | B58: Payroll - Assistant Manager | C58: 3067.21 | D58: 3078 | E58: 614.46 | F58: 2621.62 | G58: 2934.55 | H58: 2980.34 | I58: 3054.82 | J58: 4604.34 | K58: 2975.31 | L58: 2951.46 | M58: 2996.3 | N58: 2736.95 | O58: 34615.36 | Q58: 4 | R58: Teagen | S58: TEA | U58: =IF(5 = Q58, C58 * -1, C58) -> 3067.21 | V58: =IF(5 = Q58, D58 * -1, D58) -> 3078 | W58: =IF(5 = Q58, E58 * -1, E58) -> 614.46 | X58: =IF(5 = Q58, F58 * -1, F58) -> 2621.62 | Y58: =IF(5 = Q58, G58 * -1, G58) -> 2934.55 | Z58: =IF(5 = Q58, H58 * -1, H58) -> 2980.34 | AA58: =IF(5 = Q58, I58 * -1, I58) -> 3054.82 | AB58: =IF(5 = Q58, J58 * -1, J58) -> 4604.34 | AC58: =IF(5 = Q58, K58 * -1, K58) -> 2975.31 | AD58: =IF(5 = Q58, L58 * -1, L58) -> 2951.46 | AE58: =IF(5 = Q58, M58 * -1, M58) -> 2996.3 | AF58: =IF(5 = Q58, N58 * -1, N58) -> 2736.95 | AG58: =IF(5 = Q58, O58 * -1, O58) -> 34615.36 | AH58: Payroll
A59: 7013 | B59: Payroll - Leasing Agent | C59: 2902.61 | D59: 2942.33 | E59: 4441.48 | F59: 2845.96 | G59: 2876.81 | H59: 2890.43 | I59: 2880.51 | J59: 3781.45 | K59: 2809.55 | L59: 2872.53 | M59: 3087.38 | N59: 3095.37 | O59: 37426.41 | Q59: 4 | R59: Teagen | S59: TEA | U59: =IF(5 = Q59, C59 * -1, C59) -> 2902.61 | V59: =IF(5 = Q59, D59 * -1, D59) -> 2942.33 | W59: =IF(5 = Q59, E59 * -1, E59) -> 4441.48 | X59: =IF(5 = Q59, F59 * -1, F59) -> 2845.96 | Y59: =IF(5 = Q59, G59 * -1, G59) -> 2876.81 | Z59: =IF(5 = Q59, H59 * -1, H59) -> 2890.43 | AA59: =IF(5 = Q59, I59 * -1, I59) -> 2880.51 | AB59: =IF(5 = Q59, J59 * -1, J59) -> 3781.45 | AC59: =IF(5 = Q59, K59 * -1, K59) -> 2809.55 | AD59: =IF(5 = Q59, L59 * -1, L59) -> 2872.53 | AE59: =IF(5 = Q59, M59 * -1, M59) -> 3087.38 | AF59: =IF(5 = Q59, N59 * -1, N59) -> 3095.37 | AG59: =IF(5 = Q59, O59 * -1, O59) -> 37426.41 | AH59: Payroll
A60: 7016 | B60: Payroll - Maintenance Foreman | C60: 5018.46 | D60: 5083.82 | E60: 7608.21 | F60: 5089.8 | G60: 5151.85 | H60: 5238.46 | I60: 5296.41 | J60: 7556.7 | K60: 5027.23 | L60: 4935.44 | M60: 5003.7 | N60: 5084.27 | O60: 66094.35 | Q60: 4 | R60: Teagen | S60: TEA | U60: =IF(5 = Q60, C60 * -1, C60) -> 5018.46 | V60: =IF(5 = Q60, D60 * -1, D60) -> 5083.82 | W60: =IF(5 = Q60, E60 * -1, E60) -> 7608.21 | X60: =IF(5 = Q60, F60 * -1, F60) -> 5089.8 | Y60: =IF(5 = Q60, G60 * -1, G60) -> 5151.85 | Z60: =IF(5 = Q60, H60 * -1, H60) -> 5238.46 | AA60: =IF(5 = Q60, I60 * -1, I60) -> 5296.41 | AB60: =IF(5 = Q60, J60 * -1, J60) -> 7556.7 | AC60: =IF(5 = Q60, K60 * -1, K60) -> 5027.23 | AD60: =IF(5 = Q60, L60 * -1, L60) -> 4935.44 | AE60: =IF(5 = Q60, M60 * -1, M60) -> 5003.7 | AF60: =IF(5 = Q60, N60 * -1, N60) -> 5084.27 | AG60: =IF(5 = Q60, O60 * -1, O60) -> 66094.35 | AH60: Payroll
A61: 7020 | B61: Payroll - Maintenance Labor | C61: 7696.75 | D61: 6909.09 | E61: 9585.03 | F61: 6563.34 | G61: 6708.19 | H61: 6925.57 | I61: 6815.18 | J61: 10137.73 | K61: 6939.25 | L61: 6783.64 | M61: 6689.98 | N61: 6825.86 | O61: 88579.61 | Q61: 4 | R61: Teagen | S61: TEA | U61: =IF(5 = Q61, C61 * -1, C61) -> 7696.75 | V61: =IF(5 = Q61, D61 * -1, D61) -> 6909.09 | W61: =IF(5 = Q61, E61 * -1, E61) -> 9585.03 | X61: =IF(5 = Q61, F61 * -1, F61) -> 6563.34 | Y61: =IF(5 = Q61, G61 * -1, G61) -> 6708.19 | Z61: =IF(5 = Q61, H61 * -1, H61) -> 6925.57 | AA61: =IF(5 = Q61, I61 * -1, I61) -> 6815.18 | AB61: =IF(5 = Q61, J61 * -1, J61) -> 10137.73 | AC61: =IF(5 = Q61, K61 * -1, K61) -> 6939.25 | AD61: =IF(5 = Q61, L61 * -1, L61) -> 6783.64 | AE61: =IF(5 = Q61, M61 * -1, M61) -> 6689.98 | AF61: =IF(5 = Q61, N61 * -1, N61) -> 6825.86 | AG61: =IF(5 = Q61, O61 * -1, O61) -> 88579.61 | AH61: Payroll
A62: 7028 | B62: Payroll - Porter | C62: 0 | D62: 3427.88 | E62: 4495.78 | F62: 3101.59 | G62: 2912.19 | H62: 3111.09 | I62: 2953.54 | J62: 4310.95 | K62: 2896.57 | L62: 2813.15 | M62: 2799.25 | N62: 2775.83 | O62: 35597.82 | Q62: 4 | R62: Teagen | S62: TEA | U62: =IF(5 = Q62, C62 * -1, C62) -> 0 | V62: =IF(5 = Q62, D62 * -1, D62) -> 3427.88 | W62: =IF(5 = Q62, E62 * -1, E62) -> 4495.78 | X62: =IF(5 = Q62, F62 * -1, F62) -> 3101.59 | Y62: =IF(5 = Q62, G62 * -1, G62) -> 2912.19 | Z62: =IF(5 = Q62, H62 * -1, H62) -> 3111.09 | AA62: =IF(5 = Q62, I62 * -1, I62) -> 2953.54 | AB62: =IF(5 = Q62, J62 * -1, J62) -> 4310.95 | AC62: =IF(5 = Q62, K62 * -1, K62) -> 2896.57 | AD62: =IF(5 = Q62, L62 * -1, L62) -> 2813.15 | AE62: =IF(5 = Q62, M62 * -1, M62) -> 2799.25 | AF62: =IF(5 = Q62, N62 * -1, N62) -> 2775.83 | AG62: =IF(5 = Q62, O62 * -1, O62) -> 35597.82 | AH62: Payroll
A63: 7036 | B63: Payroll - Maid | C63: 2420.21 | D63: 2427.38 | E63: 3558.86 | F63: 2382.46 | G63: 2357.6 | H63: 2395.88 | I63: 2375.68 | J63: 3633.6 | K63: 2581.1 | L63: 2577.01 | M63: 2553.94 | N63: 2538.48 | O63: 31802.2 | Q63: 4 | R63: Teagen | S63: TEA | U63: =IF(5 = Q63, C63 * -1, C63) -> 2420.21 | V63: =IF(5 = Q63, D63 * -1, D63) -> 2427.38 | W63: =IF(5 = Q63, E63 * -1, E63) -> 3558.86 | X63: =IF(5 = Q63, F63 * -1, F63) -> 2382.46 | Y63: =IF(5 = Q63, G63 * -1, G63) -> 2357.6 | Z63: =IF(5 = Q63, H63 * -1, H63) -> 2395.88 | AA63: =IF(5 = Q63, I63 * -1, I63) -> 2375.68 | AB63: =IF(5 = Q63, J63 * -1, J63) -> 3633.6 | AC63: =IF(5 = Q63, K63 * -1, K63) -> 2581.1 | AD63: =IF(5 = Q63, L63 * -1, L63) -> 2577.01 | AE63: =IF(5 = Q63, M63 * -1, M63) -> 2553.94 | AF63: =IF(5 = Q63, N63 * -1, N63) -> 2538.48 | AG63: =IF(5 = Q63, O63 * -1, O63) -> 31802.2 | AH63: Payroll
B64: Payroll | C64: 26489.84 | D64: 29253.11 | E64: 38380.72 | F64: 27989.37 | G64: 28325.79 | H64: 28926.37 | I64: 28760.74 | J64: 42101.68 | K64: 28998.24 | L64: 28702.47 | M64: 28899.78 | N64: 28825.99 | O64: 365654.1 | Q64: 4 | R64: Teagen | S64: TEA | U64: =IF(5 = Q64, C64 * -1, C64) -> 26489.84 | V64: =IF(5 = Q64, D64 * -1, D64) -> 29253.11 | W64: =IF(5 = Q64, E64 * -1, E64) -> 38380.72 | X64: =IF(5 = Q64, F64 * -1, F64) -> 27989.37 | Y64: =IF(5 = Q64, G64 * -1, G64) -> 28325.79 | Z64: =IF(5 = Q64, H64 * -1, H64) -> 28926.37 | AA64: =IF(5 = Q64, I64 * -1, I64) -> 28760.74 | AB64: =IF(5 = Q64, J64 * -1, J64) -> 42101.68 | AC64: =IF(5 = Q64, K64 * -1, K64) -> 28998.24 | AD64: =IF(5 = Q64, L64 * -1, L64) -> 28702.47 | AE64: =IF(5 = Q64, M64 * -1, M64) -> 28899.78 | AF64: =IF(5 = Q64, N64 * -1, N64) -> 28825.99 | AG64: =IF(5 = Q64, O64 * -1, O64) -> 365654.1
Q65: 4 | R65: Teagen | S65: TEA | U65: =IF(5 = Q65, C65 * -1, C65) -> 0 | V65: =IF(5 = Q65, D65 * -1, D65) -> 0 | W65: =IF(5 = Q65, E65 * -1, E65) -> 0 | X65: =IF(5 = Q65, F65 * -1, F65) -> 0 | Y65: =IF(5 = Q65, G65 * -1, G65) -> 0 | Z65: =IF(5 = Q65, H65 * -1, H65) -> 0 | AA65: =IF(5 = Q65, I65 * -1, I65) -> 0 | AB65: =IF(5 = Q65, J65 * -1, J65) -> 0 | AC65: =IF(5 = Q65, K65 * -1, K65) -> 0 | AD65: =IF(5 = Q65, L65 * -1, L65) -> 0 | AE65: =IF(5 = Q65, M65 * -1, M65) -> 0 | AF65: =IF(5 = Q65, N65 * -1, N65) -> 0 | AG65: =IF(5 = Q65, O65 * -1, O65) -> 0
A66: Payroll Related | Q66: 4 | R66: Teagen | S66: TEA | U66: =IF(5 = Q66, C66 * -1, C66) -> 0 | V66: =IF(5 = Q66, D66 * -1, D66) -> 0 | W66: =IF(5 = Q66, E66 * -1, E66) -> 0 | X66: =IF(5 = Q66, F66 * -1, F66) -> 0 | Y66: =IF(5 = Q66, G66 * -1, G66) -> 0 | Z66: =IF(5 = Q66, H66 * -1, H66) -> 0 | AA66: =IF(5 = Q66, I66 * -1, I66) -> 0 | AB66: =IF(5 = Q66, J66 * -1, J66) -> 0 | AC66: =IF(5 = Q66, K66 * -1, K66) -> 0 | AD66: =IF(5 = Q66, L66 * -1, L66) -> 0 | AE66: =IF(5 = Q66, M66 * -1, M66) -> 0 | AF66: =IF(5 = Q66, N66 * -1, N66) -> 0 | AG66: =IF(5 = Q66, O66 * -1, O66) -> 0
A67: 7101 | B67: Payroll Related - Payroll Taxes | C67: 2870.33 | D67: 3103.85 | E67: 3605.6 | F67: 2791.1 | G67: 2735.81 | H67: 2694.33 | I67: 2678.69 | J67: 3702.74 | K67: 2440.92 | L67: 2586.61 | M67: 2908.08 | N67: 2457.08 | O67: 34575.14 | Q67: 4 | R67: Teagen | S67: TEA | U67: =IF(5 = Q67, C67 * -1, C67) -> 2870.33 | V67: =IF(5 = Q67, D67 * -1, D67) -> 3103.85 | W67: =IF(5 = Q67, E67 * -1, E67) -> 3605.6 | X67: =IF(5 = Q67, F67 * -1, F67) -> 2791.1 | Y67: =IF(5 = Q67, G67 * -1, G67) -> 2735.81 | Z67: =IF(5 = Q67, H67 * -1, H67) -> 2694.33 | AA67: =IF(5 = Q67, I67 * -1, I67) -> 2678.69 | AB67: =IF(5 = Q67, J67 * -1, J67) -> 3702.74 | AC67: =IF(5 = Q67, K67 * -1, K67) -> 2440.92 | AD67: =IF(5 = Q67, L67 * -1, L67) -> 2586.61 | AE67: =IF(5 = Q67, M67 * -1, M67) -> 2908.08 | AF67: =IF(5 = Q67, N67 * -1, N67) -> 2457.08 | AG67: =IF(5 = Q67, O67 * -1, O67) -> 34575.14 | AH67: Payroll
A68: 7104 | B68: Payroll Related - Health Insurance | C68: 4354.6 | D68: 4355.95 | E68: 3655.77 | F68: 2615.82 | G68: 3859.26 | H68: 6145.28 | I68: 3872.67 | J68: 3872.67 | K68: 3872.67 | L68: 3942.17 | M68: 3921.06 | N68: 3723.15 | O68: 48191.07 | Q68: 4 | R68: Teagen | S68: TEA | U68: =IF(5 = Q68, C68 * -1, C68) -> 4354.6 | V68: =IF(5 = Q68, D68 * -1, D68) -> 4355.95 | W68: =IF(5 = Q68, E68 * -1, E68) -> 3655.77 | X68: =IF(5 = Q68, F68 * -1, F68) -> 2615.82 | Y68: =IF(5 = Q68, G68 * -1, G68) -> 3859.26 | Z68: =IF(5 = Q68, H68 * -1, H68) -> 6145.28 | AA68: =IF(5 = Q68, I68 * -1, I68) -> 3872.67 | AB68: =IF(5 = Q68, J68 * -1, J68) -> 3872.67 | AC68: =IF(5 = Q68, K68 * -1, K68) -> 3872.67 | AD68: =IF(5 = Q68, L68 * -1, L68) -> 3942.17 | AE68: =IF(5 = Q68, M68 * -1, M68) -> 3921.06 | AF68: =IF(5 = Q68, N68 * -1, N68) -> 3723.15 | AG68: =IF(5 = Q68, O68 * -1, O68) -> 48191.07 | AH68: Payroll
A69: 7108 | B69: Payroll Related - Other Benefits | C69: 4664.71 | D69: 5045.82 | E69: 2755.23 | F69: 4090.88 | G69: 4405.17 | H69: 3745.4 | I69: 4165.92 | J69: 6698.6 | K69: 3934.63 | L69: 7054.84 | M69: 10764.26 | N69: 4728.95 | O69: 62054.41 | Q69: 4 | R69: Teagen | S69: TEA | U69: =IF(5 = Q69, C69 * -1, C69) -> 4664.71 | V69: =IF(5 = Q69, D69 * -1, D69) -> 5045.82 | W69: =IF(5 = Q69, E69 * -1, E69) -> 2755.23 | X69: =IF(5 = Q69, F69 * -1, F69) -> 4090.88 | Y69: =IF(5 = Q69, G69 * -1, G69) -> 4405.17 | Z69: =IF(5 = Q69, H69 * -1, H69) -> 3745.4 | AA69: =IF(5 = Q69, I69 * -1, I69) -> 4165.92 | AB69: =IF(5 = Q69, J69 * -1, J69) -> 6698.6 | AC69: =IF(5 = Q69, K69 * -1, K69) -> 3934.63 | AD69: =IF(5 = Q69, L69 * -1, L69) -> 7054.84 | AE69: =IF(5 = Q69, M69 * -1, M69) -> 10764.26 | AF69: =IF(5 = Q69, N69 * -1, N69) -> 4728.95 | AG69: =IF(5 = Q69, O69 * -1, O69) -> 62054.41 | AH69: Payroll
A70: 7112 | B70: Payroll Related - Workers Compensation | C70: 643.82 | D70: 699.54 | E70: 2258.73 | F70: 907.05 | G70: 669.84 | H70: 675.64 | I70: 673.77 | J70: 675.96 | K70: 999.69 | L70: 676.6 | M70: 715.64 | N70: 798.29 | O70: 10394.57 | Q70: 4 | R70: Teagen | S70: TEA | U70: =IF(5 = Q70, C70 * -1, C70) -> 643.82 | V70: =IF(5 = Q70, D70 * -1, D70) -> 699.54 | W70: =IF(5 = Q70, E70 * -1, E70) -> 2258.73 | X70: =IF(5 = Q70, F70 * -1, F70) -> 907.05 | Y70: =IF(5 = Q70, G70 * -1, G70) -> 669.84 | Z70: =IF(5 = Q70, H70 * -1, H70) -> 675.64 | AA70: =IF(5 = Q70, I70 * -1, I70) -> 673.77 | AB70: =IF(5 = Q70, J70 * -1, J70) -> 675.96 | AC70: =IF(5 = Q70, K70 * -1, K70) -> 999.69 | AD70: =IF(5 = Q70, L70 * -1, L70) -> 676.6 | AE70: =IF(5 = Q70, M70 * -1, M70) -> 715.64 | AF70: =IF(5 = Q70, N70 * -1, N70) -> 798.29 | AG70: =IF(5 = Q70, O70 * -1, O70) -> 10394.57 | AH70: Payroll
A71: 7113 | B71: Payroll Related - Training & Education | C71: 168.48 | D71: 168.48 | E71: 168.48 | F71: 304.7 | G71: 286.69 | H71: 175.03 | I71: 175.03 | J71: 183.4 | K71: 206.32 | L71: 178.77 | M71: 178.77 | N71: 178.77 | O71: 2372.92 | Q71: 4 | R71: Teagen | S71: TEA | U71: =IF(5 = Q71, C71 * -1, C71) -> 168.48 | V71: =IF(5 = Q71, D71 * -1, D71) -> 168.48 | W71: =IF(5 = Q71, E71 * -1, E71) -> 168.48 | X71: =IF(5 = Q71, F71 * -1, F71) -> 304.7 | Y71: =IF(5 = Q71, G71 * -1, G71) -> 286.69 | Z71: =IF(5 = Q71, H71 * -1, H71) -> 175.03 | AA71: =IF(5 = Q71, I71 * -1, I71) -> 175.03 | AB71: =IF(5 = Q71, J71 * -1, J71) -> 183.4 | AC71: =IF(5 = Q71, K71 * -1, K71) -> 206.32 | AD71: =IF(5 = Q71, L71 * -1, L71) -> 178.77 | AE71: =IF(5 = Q71, M71 * -1, M71) -> 178.77 | AF71: =IF(5 = Q71, N71 * -1, N71) -> 178.77 | AG71: =IF(5 = Q71, O71 * -1, O71) -> 2372.92 | AH71: Payroll
B72: Payroll Related | C72: 12701.94 | D72: 13373.64 | E72: 12443.81 | F72: 10709.55 | G72: 11956.77 | H72: 13435.68 | I72: 11566.08 | J72: 15133.37 | K72: 11454.23 | L72: 14438.99 | M72: 18487.81 | N72: 11886.24 | O72: 157588.11 | Q72: 4 | R72: Teagen | S72: TEA | U72: =IF(5 = Q72, C72 * -1, C72) -> 12701.94 | V72: =IF(5 = Q72, D72 * -1, D72) -> 13373.64 | W72: =IF(5 = Q72, E72 * -1, E72) -> 12443.81 | X72: =IF(5 = Q72, F72 * -1, F72) -> 10709.55 | Y72: =IF(5 = Q72, G72 * -1, G72) -> 11956.77 | Z72: =IF(5 = Q72, H72 * -1, H72) -> 13435.68 | AA72: =IF(5 = Q72, I72 * -1, I72) -> 11566.08 | AB72: =IF(5 = Q72, J72 * -1, J72) -> 15133.37 | AC72: =IF(5 = Q72, K72 * -1, K72) -> 11454.23 | AD72: =IF(5 = Q72, L72 * -1, L72) -> 14438.99 | AE72: =IF(5 = Q72, M72 * -1, M72) -> 18487.81 | AF72: =IF(5 = Q72, N72 * -1, N72) -> 11886.24 | AG72: =IF(5 = Q72, O72 * -1, O72) -> 157588.11
Q73: 4 | R73: Teagen | S73: TEA | U73: =IF(5 = Q73, C73 * -1, C73) -> 0 | V73: =IF(5 = Q73, D73 * -1, D73) -> 0 | W73: =IF(5 = Q73, E73 * -1, E73) -> 0 | X73: =IF(5 = Q73, F73 * -1, F73) -> 0 | Y73: =IF(5 = Q73, G73 * -1, G73) -> 0 | Z73: =IF(5 = Q73, H73 * -1, H73) -> 0 | AA73: =IF(5 = Q73, I73 * -1, I73) -> 0 | AB73: =IF(5 = Q73, J73 * -1, J73) -> 0 | AC73: =IF(5 = Q73, K73 * -1, K73) -> 0 | AD73: =IF(5 = Q73, L73 * -1, L73) -> 0 | AE73: =IF(5 = Q73, M73 * -1, M73) -> 0 | AF73: =IF(5 = Q73, N73 * -1, N73) -> 0 | AG73: =IF(5 = Q73, O73 * -1, O73) -> 0
B74: Payroll & Related | C74: 39191.78 | D74: 42626.75 | E74: 50824.53 | F74: 38698.92 | G74: 40282.56 | H74: 42362.05 | I74: 40326.82 | J74: 57235.05 | K74: 40452.47 | L74: 43141.46 | M74: 47387.59 | N74: 40712.23 | O74: 523242.21 | Q74: 4 | R74: Teagen | S74: TEA | U74: =IF(5 = Q74, C74 * -1, C74) -> 39191.78 | V74: =IF(5 = Q74, D74 * -1, D74) -> 42626.75 | W74: =IF(5 = Q74, E74 * -1, E74) -> 50824.53 | X74: =IF(5 = Q74, F74 * -1, F74) -> 38698.92 | Y74: =IF(5 = Q74, G74 * -1, G74) -> 40282.56 | Z74: =IF(5 = Q74, H74 * -1, H74) -> 42362.05 | AA74: =IF(5 = Q74, I74 * -1, I74) -> 40326.82 | AB74: =IF(5 = Q74, J74 * -1, J74) -> 57235.05 | AC74: =IF(5 = Q74, K74 * -1, K74) -> 40452.47 | AD74: =IF(5 = Q74, L74 * -1, L74) -> 43141.46 | AE74: =IF(5 = Q74, M74 * -1, M74) -> 47387.59 | AF74: =IF(5 = Q74, N74 * -1, N74) -> 40712.23 | AG74: =IF(5 = Q74, O74 * -1, O74) -> 523242.21
Q75: 4 | R75: Teagen | S75: TEA | U75: =IF(5 = Q75, C75 * -1, C75) -> 0 | V75: =IF(5 = Q75, D75 * -1, D75) -> 0 | W75: =IF(5 = Q75, E75 * -1, E75) -> 0 | X75: =IF(5 = Q75, F75 * -1, F75) -> 0 | Y75: =IF(5 = Q75, G75 * -1, G75) -> 0 | Z75: =IF(5 = Q75, H75 * -1, H75) -> 0 | AA75: =IF(5 = Q75, I75 * -1, I75) -> 0 | AB75: =IF(5 = Q75, J75 * -1, J75) -> 0 | AC75: =IF(5 = Q75, K75 * -1, K75) -> 0 | AD75: =IF(5 = Q75, L75 * -1, L75) -> 0 | AE75: =IF(5 = Q75, M75 * -1, M75) -> 0 | AF75: =IF(5 = Q75, N75 * -1, N75) -> 0 | AG75: =IF(5 = Q75, O75 * -1, O75) -> 0
A76: Contractual Services | Q76: 4 | R76: Teagen | S76: TEA | U76: =IF(5 = Q76, C76 * -1, C76) -> 0 | V76: =IF(5 = Q76, D76 * -1, D76) -> 0 | W76: =IF(5 = Q76, E76 * -1, E76) -> 0 | X76: =IF(5 = Q76, F76 * -1, F76) -> 0 | Y76: =IF(5 = Q76, G76 * -1, G76) -> 0 | Z76: =IF(5 = Q76, H76 * -1, H76) -> 0 | AA76: =IF(5 = Q76, I76 * -1, I76) -> 0 | AB76: =IF(5 = Q76, J76 * -1, J76) -> 0 | AC76: =IF(5 = Q76, K76 * -1, K76) -> 0 | AD76: =IF(5 = Q76, L76 * -1, L76) -> 0 | AE76: =IF(5 = Q76, M76 * -1, M76) -> 0 | AF76: =IF(5 = Q76, N76 * -1, N76) -> 0 | AG76: =IF(5 = Q76, O76 * -1, O76) -> 0
A77: 7247 | B77: Contractual Services - Key Trak System | C77: 64.95 | D77: 64.95 | E77: 64.95 | F77: 64.95 | G77: 64.95 | H77: 64.95 | I77: 64.95 | J77: 65 | K77: 64.9 | L77: 64.95 | M77: 64.95 | N77: 64.95 | O77: 779.4 | Q77: 4 | R77: Teagen | S77: TEA | U77: =IF(5 = Q77, C77 * -1, C77) -> 64.95 | V77: =IF(5 = Q77, D77 * -1, D77) -> 64.95 | W77: =IF(5 = Q77, E77 * -1, E77) -> 64.95 | X77: =IF(5 = Q77, F77 * -1, F77) -> 64.95 | Y77: =IF(5 = Q77, G77 * -1, G77) -> 64.95 | Z77: =IF(5 = Q77, H77 * -1, H77) -> 64.95 | AA77: =IF(5 = Q77, I77 * -1, I77) -> 64.95 | AB77: =IF(5 = Q77, J77 * -1, J77) -> 65 | AC77: =IF(5 = Q77, K77 * -1, K77) -> 64.9 | AD77: =IF(5 = Q77, L77 * -1, L77) -> 64.95 | AE77: =IF(5 = Q77, M77 * -1, M77) -> 64.95 | AF77: =IF(5 = Q77, N77 * -1, N77) -> 64.95 | AG77: =IF(5 = Q77, O77 * -1, O77) -> 779.4 | AH77: Repairs & Maintenance
A78: 7251 | B78: Contractual Services - Grounds Contract | C78: 2300 | D78: 2300 | E78: 2300 | F78: 2300 | G78: 2300 | H78: 2300 | I78: 2300 | J78: 2300 | K78: 2300 | L78: 2300 | M78: 2300 | N78: 2300 | O78: 27600 | Q78: 4 | R78: Teagen | S78: TEA | U78: =IF(5 = Q78, C78 * -1, C78) -> 2300 | V78: =IF(5 = Q78, D78 * -1, D78) -> 2300 | W78: =IF(5 = Q78, E78 * -1, E78) -> 2300 | X78: =IF(5 = Q78, F78 * -1, F78) -> 2300 | Y78: =IF(5 = Q78, G78 * -1, G78) -> 2300 | Z78: =IF(5 = Q78, H78 * -1, H78) -> 2300 | AA78: =IF(5 = Q78, I78 * -1, I78) -> 2300 | AB78: =IF(5 = Q78, J78 * -1, J78) -> 2300 | AC78: =IF(5 = Q78, K78 * -1, K78) -> 2300 | AD78: =IF(5 = Q78, L78 * -1, L78) -> 2300 | AE78: =IF(5 = Q78, M78 * -1, M78) -> 2300 | AF78: =IF(5 = Q78, N78 * -1, N78) -> 2300 | AG78: =IF(5 = Q78, O78 * -1, O78) -> 27600 | AH78: Repairs & Maintenance
A79: 7253 | B79: Contractual Services - Electronic Monitoring | C79: 309.91 | D79: 319.11 | E79: 334.88 | F79: 334.88 | G79: 837.42 | H79: 391.84 | I79: 313.36 | J79: 320 | K79: 150.2 | L79: 1502.45 | M79: 173.01 | N79: 636.75 | O79: 5623.81 | Q79: 4 | R79: Teagen | S79: TEA | U79: =IF(5 = Q79, C79 * -1, C79) -> 309.91 | V79: =IF(5 = Q79, D79 * -1, D79) -> 319.11 | W79: =IF(5 = Q79, E79 * -1, E79) -> 334.88 | X79: =IF(5 = Q79, F79 * -1, F79) -> 334.88 | Y79: =IF(5 = Q79, G79 * -1, G79) -> 837.42 | Z79: =IF(5 = Q79, H79 * -1, H79) -> 391.84 | AA79: =IF(5 = Q79, I79 * -1, I79) -> 313.36 | AB79: =IF(5 = Q79, J79 * -1, J79) -> 320 | AC79: =IF(5 = Q79, K79 * -1, K79) -> 150.2 | AD79: =IF(5 = Q79, L79 * -1, L79) -> 1502.45 | AE79: =IF(5 = Q79, M79 * -1, M79) -> 173.01 | AF79: =IF(5 = Q79, N79 * -1, N79) -> 636.75 | AG79: =IF(5 = Q79, O79 * -1, O79) -> 5623.81 | AH79: Repairs & Maintenance
A80: 7255 | B80: Contractual Services - Patrol Service | C80: 1264 | D80: 1680 | E80: 1345 | F80: 1345 | G80: 1345 | H80: 1345 | I80: 1345 | J80: 1345 | K80: 1345 | L80: 0 | M80: 1340 | N80: 1345 | O80: 15044 | Q80: 4 | R80: Teagen | S80: TEA | U80: =IF(5 = Q80, C80 * -1, C80) -> 1264 | V80: =IF(5 = Q80, D80 * -1, D80) -> 1680 | W80: =IF(5 = Q80, E80 * -1, E80) -> 1345 | X80: =IF(5 = Q80, F80 * -1, F80) -> 1345 | Y80: =IF(5 = Q80, G80 * -1, G80) -> 1345 | Z80: =IF(5 = Q80, H80 * -1, H80) -> 1345 | AA80: =IF(5 = Q80, I80 * -1, I80) -> 1345 | AB80: =IF(5 = Q80, J80 * -1, J80) -> 1345 | AC80: =IF(5 = Q80, K80 * -1, K80) -> 1345 | AD80: =IF(5 = Q80, L80 * -1, L80) -> 0 | AE80: =IF(5 = Q80, M80 * -1, M80) -> 1340 | AF80: =IF(5 = Q80, N80 * -1, N80) -> 1345 | AG80: =IF(5 = Q80, O80 * -1, O80) -> 15044 | AH80: Repairs & Maintenance
A81: 7256 | B81: Contractual Services - Fire Alarm Monitoring | C81: 392 | D81: 0 | E81: 0 | F81: 392 | G81: 0 | H81: 556.2 | I81: 0 | J81: 0 | K81: 0 | L81: 0 | M81: 412 | N81: 0 | O81: 1752.2 | Q81: 4 | R81: Teagen | S81: TEA | U81: =IF(5 = Q81, C81 * -1, C81) -> 392 | V81: =IF(5 = Q81, D81 * -1, D81) -> 0 | W81: =IF(5 = Q81, E81 * -1, E81) -> 0 | X81: =IF(5 = Q81, F81 * -1, F81) -> 392 | Y81: =IF(5 = Q81, G81 * -1, G81) -> 0 | Z81: =IF(5 = Q81, H81 * -1, H81) -> 556.2 | AA81: =IF(5 = Q81, I81 * -1, I81) -> 0 | AB81: =IF(5 = Q81, J81 * -1, J81) -> 0 | AC81: =IF(5 = Q81, K81 * -1, K81) -> 0 | AD81: =IF(5 = Q81, L81 * -1, L81) -> 0 | AE81: =IF(5 = Q81, M81 * -1, M81) -> 412 | AF81: =IF(5 = Q81, N81 * -1, N81) -> 0 | AG81: =IF(5 = Q81, O81 * -1, O81) -> 1752.2 | AH81: Repairs & Maintenance
B82: Contractual Services | C82: 4330.86 | D82: 4364.06 | E82: 4044.83 | F82: 4436.83 | G82: 4547.37 | H82: 4657.99 | I82: 4023.31 | J82: 4030 | K82: 3860.1 | L82: 3867.4 | M82: 4289.96 | N82: 4346.7 | O82: 50799.41 | Q82: 4 | R82: Teagen | S82: TEA | U82: =IF(5 = Q82, C82 * -1, C82) -> 4330.86 | V82: =IF(5 = Q82, D82 * -1, D82) -> 4364.06 | W82: =IF(5 = Q82, E82 * -1, E82) -> 4044.83 | X82: =IF(5 = Q82, F82 * -1, F82) -> 4436.83 | Y82: =IF(5 = Q82, G82 * -1, G82) -> 4547.37 | Z82: =IF(5 = Q82, H82 * -1, H82) -> 4657.99 | AA82: =IF(5 = Q82, I82 * -1, I82) -> 4023.31 | AB82: =IF(5 = Q82, J82 * -1, J82) -> 4030 | AC82: =IF(5 = Q82, K82 * -1, K82) -> 3860.1 | AD82: =IF(5 = Q82, L82 * -1, L82) -> 3867.4 | AE82: =IF(5 = Q82, M82 * -1, M82) -> 4289.96 | AF82: =IF(5 = Q82, N82 * -1, N82) -> 4346.7 | AG82: =IF(5 = Q82, O82 * -1, O82) -> 50799.41
Q83: 4 | R83: Teagen | S83: TEA | U83: =IF(5 = Q83, C83 * -1, C83) -> 0 | V83: =IF(5 = Q83, D83 * -1, D83) -> 0 | W83: =IF(5 = Q83, E83 * -1, E83) -> 0 | X83: =IF(5 = Q83, F83 * -1, F83) -> 0 | Y83: =IF(5 = Q83, G83 * -1, G83) -> 0 | Z83: =IF(5 = Q83, H83 * -1, H83) -> 0 | AA83: =IF(5 = Q83, I83 * -1, I83) -> 0 | AB83: =IF(5 = Q83, J83 * -1, J83) -> 0 | AC83: =IF(5 = Q83, K83 * -1, K83) -> 0 | AD83: =IF(5 = Q83, L83 * -1, L83) -> 0 | AE83: =IF(5 = Q83, M83 * -1, M83) -> 0 | AF83: =IF(5 = Q83, N83 * -1, N83) -> 0 | AG83: =IF(5 = Q83, O83 * -1, O83) -> 0
A84: Utilities | Q84: 4 | R84: Teagen | S84: TEA | U84: =IF(5 = Q84, C84 * -1, C84) -> 0 | V84: =IF(5 = Q84, D84 * -1, D84) -> 0 | W84: =IF(5 = Q84, E84 * -1, E84) -> 0 | X84: =IF(5 = Q84, F84 * -1, F84) -> 0 | Y84: =IF(5 = Q84, G84 * -1, G84) -> 0 | Z84: =IF(5 = Q84, H84 * -1, H84) -> 0 | AA84: =IF(5 = Q84, I84 * -1, I84) -> 0 | AB84: =IF(5 = Q84, J84 * -1, J84) -> 0 | AC84: =IF(5 = Q84, K84 * -1, K84) -> 0 | AD84: =IF(5 = Q84, L84 * -1, L84) -> 0 | AE84: =IF(5 = Q84, M84 * -1, M84) -> 0 | AF84: =IF(5 = Q84, N84 * -1, N84) -> 0 | AG84: =IF(5 = Q84, O84 * -1, O84) -> 0
A85: 7308 | B85: Utilities - Common Area | C85: 2361.45 | D85: 2117.65 | E85: 2202.88 | F85: 2022.15 | G85: 2156.84 | H85: 1910.53 | I85: 2070.72 | J85: 2829.6 | K85: 3300.06 | L85: 4504.08 | M85: 2486.9 | N85: 3705.27 | O85: 31668.13 | Q85: 4 | R85: Teagen | S85: TEA | U85: =IF(5 = Q85, C85 * -1, C85) -> 2361.45 | V85: =IF(5 = Q85, D85 * -1, D85) -> 2117.65 | W85: =IF(5 = Q85, E85 * -1, E85) -> 2202.88 | X85: =IF(5 = Q85, F85 * -1, F85) -> 2022.15 | Y85: =IF(5 = Q85, G85 * -1, G85) -> 2156.84 | Z85: =IF(5 = Q85, H85 * -1, H85) -> 1910.53 | AA85: =IF(5 = Q85, I85 * -1, I85) -> 2070.72 | AB85: =IF(5 = Q85, J85 * -1, J85) -> 2829.6 | AC85: =IF(5 = Q85, K85 * -1, K85) -> 3300.06 | AD85: =IF(5 = Q85, L85 * -1, L85) -> 4504.08 | AE85: =IF(5 = Q85, M85 * -1, M85) -> 2486.9 | AF85: =IF(5 = Q85, N85 * -1, N85) -> 3705.27 | AG85: =IF(5 = Q85, O85 * -1, O85) -> 31668.13 | AH85: Utilities
A86: 7309 | B86: Utilities - Vacants | C86: 48.26 | D86: 2141.77 | E86: 120.23 | F86: 291.38 | G86: -305.26 | H86: 209.27 | I86: -1221.12 | J86: 776.2 | K86: -1206.74 | L86: -612.57 | M86: -504.81 | N86: -1031.13 | O86: -1294.52 | Q86: 4 | R86: Teagen | S86: TEA | U86: =IF(5 = Q86, C86 * -1, C86) -> 48.26 | V86: =IF(5 = Q86, D86 * -1, D86) -> 2141.77 | W86: =IF(5 = Q86, E86 * -1, E86) -> 120.23 | X86: =IF(5 = Q86, F86 * -1, F86) -> 291.38 | Y86: =IF(5 = Q86, G86 * -1, G86) -> -305.26 | Z86: =IF(5 = Q86, H86 * -1, H86) -> 209.27 | AA86: =IF(5 = Q86, I86 * -1, I86) -> -1221.12 | AB86: =IF(5 = Q86, J86 * -1, J86) -> 776.2 | AC86: =IF(5 = Q86, K86 * -1, K86) -> -1206.74 | AD86: =IF(5 = Q86, L86 * -1, L86) -> -612.57 | AE86: =IF(5 = Q86, M86 * -1, M86) -> -504.81 | AF86: =IF(5 = Q86, N86 * -1, N86) -> -1031.13 | AG86: =IF(5 = Q86, O86 * -1, O86) -> -1294.52 | AH86: Utilities
A87: 7312 | B87: Utilities - Gas | C87: 452.32 | D87: 521.93 | E87: 386.92 | F87: 315.52 | G87: 183.5 | H87: 160.2 | I87: 159.13 | J87: 147.17 | K87: 8.67 | L87: -500 | M87: 350.29 | N87: 302.9 | O87: 2488.55 | Q87: 4 | R87: Teagen | S87: TEA | U87: =IF(5 = Q87, C87 * -1, C87) -> 452.32 | V87: =IF(5 = Q87, D87 * -1, D87) -> 521.93 | W87: =IF(5 = Q87, E87 * -1, E87) -> 386.92 | X87: =IF(5 = Q87, F87 * -1, F87) -> 315.52 | Y87: =IF(5 = Q87, G87 * -1, G87) -> 183.5 | Z87: =IF(5 = Q87, H87 * -1, H87) -> 160.2 | AA87: =IF(5 = Q87, I87 * -1, I87) -> 159.13 | AB87: =IF(5 = Q87, J87 * -1, J87) -> 147.17 | AC87: =IF(5 = Q87, K87 * -1, K87) -> 8.67 | AD87: =IF(5 = Q87, L87 * -1, L87) -> -500 | AE87: =IF(5 = Q87, M87 * -1, M87) -> 350.29 | AF87: =IF(5 = Q87, N87 * -1, N87) -> 302.9 | AG87: =IF(5 = Q87, O87 * -1, O87) -> 2488.55 | AH87: Utilities
A88: 7315 | B88: Utilities - Water | C88: 7301.5 | D88: 18969.7 | E88: 14850.88 | F88: 23657.78 | G88: 20647.28 | H88: 21736.28 | I88: 22033.28 | J88: 14645.4 | K88: 16950.03 | L88: 17830.34 | M88: 17354 | N88: 21822.94 | O88: 217799.41 | Q88: 4 | R88: Teagen | S88: TEA | U88: =IF(5 = Q88, C88 * -1, C88) -> 7301.5 | V88: =IF(5 = Q88, D88 * -1, D88) -> 18969.7 | W88: =IF(5 = Q88, E88 * -1, E88) -> 14850.88 | X88: =IF(5 = Q88, F88 * -1, F88) -> 23657.78 | Y88: =IF(5 = Q88, G88 * -1, G88) -> 20647.28 | Z88: =IF(5 = Q88, H88 * -1, H88) -> 21736.28 | AA88: =IF(5 = Q88, I88 * -1, I88) -> 22033.28 | AB88: =IF(5 = Q88, J88 * -1, J88) -> 14645.4 | AC88: =IF(5 = Q88, K88 * -1, K88) -> 16950.03 | AD88: =IF(5 = Q88, L88 * -1, L88) -> 17830.34 | AE88: =IF(5 = Q88, M88 * -1, M88) -> 17354 | AF88: =IF(5 = Q88, N88 * -1, N88) -> 21822.94 | AG88: =IF(5 = Q88, O88 * -1, O88) -> 217799.41 | AH88: Utilities
A89: 7320 | B89: Utilities - Trash Removal | C89: 2554.72 | D89: 2939.72 | E89: 3243.45 | F89: 3243.45 | G89: 3243.45 | H89: 2858.45 | I89: 3628.45 | J89: 3243.45 | K89: 2858.45 | L89: 3439.45 | M89: 3243.45 | N89: 3393.45 | O89: 37889.94 | Q89: 4 | R89: Teagen | S89: TEA | U89: =IF(5 = Q89, C89 * -1, C89) -> 2554.72 | V89: =IF(5 = Q89, D89 * -1, D89) -> 2939.72 | W89: =IF(5 = Q89, E89 * -1, E89) -> 3243.45 | X89: =IF(5 = Q89, F89 * -1, F89) -> 3243.45 | Y89: =IF(5 = Q89, G89 * -1, G89) -> 3243.45 | Z89: =IF(5 = Q89, H89 * -1, H89) -> 2858.45 | AA89: =IF(5 = Q89, I89 * -1, I89) -> 3628.45 | AB89: =IF(5 = Q89, J89 * -1, J89) -> 3243.45 | AC89: =IF(5 = Q89, K89 * -1, K89) -> 2858.45 | AD89: =IF(5 = Q89, L89 * -1, L89) -> 3439.45 | AE89: =IF(5 = Q89, M89 * -1, M89) -> 3243.45 | AF89: =IF(5 = Q89, N89 * -1, N89) -> 3393.45 | AG89: =IF(5 = Q89, O89 * -1, O89) -> 37889.94 | AH89: Trash Removal
A90: 7322 | B90: Utilities - Valet Trash Service | C90: 2958.6 | D90: 2958.6 | E90: 2958.6 | F90: 2958.6 | G90: 2958.6 | H90: 2958.6 | I90: 2958.6 | J90: 2958.6 | K90: 2958.6 | L90: 2958.6 | M90: 2958.6 | N90: 2958.6 | O90: 35503.2 | Q90: 4 | R90: Teagen | S90: TEA | U90: =IF(5 = Q90, C90 * -1, C90) -> 2958.6 | V90: =IF(5 = Q90, D90 * -1, D90) -> 2958.6 | W90: =IF(5 = Q90, E90 * -1, E90) -> 2958.6 | X90: =IF(5 = Q90, F90 * -1, F90) -> 2958.6 | Y90: =IF(5 = Q90, G90 * -1, G90) -> 2958.6 | Z90: =IF(5 = Q90, H90 * -1, H90) -> 2958.6 | AA90: =IF(5 = Q90, I90 * -1, I90) -> 2958.6 | AB90: =IF(5 = Q90, J90 * -1, J90) -> 2958.6 | AC90: =IF(5 = Q90, K90 * -1, K90) -> 2958.6 | AD90: =IF(5 = Q90, L90 * -1, L90) -> 2958.6 | AE90: =IF(5 = Q90, M90 * -1, M90) -> 2958.6 | AF90: =IF(5 = Q90, N90 * -1, N90) -> 2958.6 | AG90: =IF(5 = Q90, O90 * -1, O90) -> 35503.2 | AH90: Trash Removal
A91: 7335 | B91: Utilities - Utility Billing Service | C91: 1510 | D91: 1475 | E91: 1465 | F91: 1470 | G91: 1425 | H91: 1430 | I91: 1450 | J91: 2018.02 | K91: 1475 | L91: 1410 | M91: 1430 | N91: 1460 | O91: 18018.02 | Q91: 4 | R91: Teagen | S91: TEA | U91: =IF(5 = Q91, C91 * -1, C91) -> 1510 | V91: =IF(5 = Q91, D91 * -1, D91) -> 1475 | W91: =IF(5 = Q91, E91 * -1, E91) -> 1465 | X91: =IF(5 = Q91, F91 * -1, F91) -> 1470 | Y91: =IF(5 = Q91, G91 * -1, G91) -> 1425 | Z91: =IF(5 = Q91, H91 * -1, H91) -> 1430 | AA91: =IF(5 = Q91, I91 * -1, I91) -> 1450 | AB91: =IF(5 = Q91, J91 * -1, J91) -> 2018.02 | AC91: =IF(5 = Q91, K91 * -1, K91) -> 1475 | AD91: =IF(5 = Q91, L91 * -1, L91) -> 1410 | AE91: =IF(5 = Q91, M91 * -1, M91) -> 1430 | AF91: =IF(5 = Q91, N91 * -1, N91) -> 1460 | AG91: =IF(5 = Q91, O91 * -1, O91) -> 18018.02 | AH91: Utilities
B92: Utilities | C92: 17186.85 | D92: 31124.37 | E92: 25227.96 | F92: 33958.88 | G92: 30309.41 | H92: 31263.33 | I92: 31079.06 | J92: 26618.44 | K92: 26344.07 | L92: 29029.9 | M92: 27318.43 | N92: 32612.03 | O92: 342072.73 | Q92: 4 | R92: Teagen | S92: TEA | U92: =IF(5 = Q92, C92 * -1, C92) -> 17186.85 | V92: =IF(5 = Q92, D92 * -1, D92) -> 31124.37 | W92: =IF(5 = Q92, E92 * -1, E92) -> 25227.96 | X92: =IF(5 = Q92, F92 * -1, F92) -> 33958.88 | Y92: =IF(5 = Q92, G92 * -1, G92) -> 30309.41 | Z92: =IF(5 = Q92, H92 * -1, H92) -> 31263.33 | AA92: =IF(5 = Q92, I92 * -1, I92) -> 31079.06 | AB92: =IF(5 = Q92, J92 * -1, J92) -> 26618.44 | AC92: =IF(5 = Q92, K92 * -1, K92) -> 26344.07 | AD92: =IF(5 = Q92, L92 * -1, L92) -> 29029.9 | AE92: =IF(5 = Q92, M92 * -1, M92) -> 27318.43 | AF92: =IF(5 = Q92, N92 * -1, N92) -> 32612.03 | AG92: =IF(5 = Q92, O92 * -1, O92) -> 342072.73
Q93: 4 | R93: Teagen | S93: TEA | U93: =IF(5 = Q93, C93 * -1, C93) -> 0 | V93: =IF(5 = Q93, D93 * -1, D93) -> 0 | W93: =IF(5 = Q93, E93 * -1, E93) -> 0 | X93: =IF(5 = Q93, F93 * -1, F93) -> 0 | Y93: =IF(5 = Q93, G93 * -1, G93) -> 0 | Z93: =IF(5 = Q93, H93 * -1, H93) -> 0 | AA93: =IF(5 = Q93, I93 * -1, I93) -> 0 | AB93: =IF(5 = Q93, J93 * -1, J93) -> 0 | AC93: =IF(5 = Q93, K93 * -1, K93) -> 0 | AD93: =IF(5 = Q93, L93 * -1, L93) -> 0 | AE93: =IF(5 = Q93, M93 * -1, M93) -> 0 | AF93: =IF(5 = Q93, N93 * -1, N93) -> 0 | AG93: =IF(5 = Q93, O93 * -1, O93) -> 0
A94: Redecorating | Q94: 4 | R94: Teagen | S94: TEA | U94: =IF(5 = Q94, C94 * -1, C94) -> 0 | V94: =IF(5 = Q94, D94 * -1, D94) -> 0 | W94: =IF(5 = Q94, E94 * -1, E94) -> 0 | X94: =IF(5 = Q94, F94 * -1, F94) -> 0 | Y94: =IF(5 = Q94, G94 * -1, G94) -> 0 | Z94: =IF(5 = Q94, H94 * -1, H94) -> 0 | AA94: =IF(5 = Q94, I94 * -1, I94) -> 0 | AB94: =IF(5 = Q94, J94 * -1, J94) -> 0 | AC94: =IF(5 = Q94, K94 * -1, K94) -> 0 | AD94: =IF(5 = Q94, L94 * -1, L94) -> 0 | AE94: =IF(5 = Q94, M94 * -1, M94) -> 0 | AF94: =IF(5 = Q94, N94 * -1, N94) -> 0 | AG94: =IF(5 = Q94, O94 * -1, O94) -> 0
A95: 7443 | B95: Redecorating - General Cleaning | C95: 1124.06 | D95: 1661.61 | E95: 715.36 | F95: 132.25 | G95: 265.41 | H95: 134 | I95: 448.36 | J95: 540.76 | K95: 333.72 | L95: 506.46 | M95: 328.36 | N95: 731.9 | O95: 6922.25 | Q95: 4 | R95: Teagen | S95: TEA | U95: =IF(5 = Q95, C95 * -1, C95) -> 1124.06 | V95: =IF(5 = Q95, D95 * -1, D95) -> 1661.61 | W95: =IF(5 = Q95, E95 * -1, E95) -> 715.36 | X95: =IF(5 = Q95, F95 * -1, F95) -> 132.25 | Y95: =IF(5 = Q95, G95 * -1, G95) -> 265.41 | Z95: =IF(5 = Q95, H95 * -1, H95) -> 134 | AA95: =IF(5 = Q95, I95 * -1, I95) -> 448.36 | AB95: =IF(5 = Q95, J95 * -1, J95) -> 540.76 | AC95: =IF(5 = Q95, K95 * -1, K95) -> 333.72 | AD95: =IF(5 = Q95, L95 * -1, L95) -> 506.46 | AE95: =IF(5 = Q95, M95 * -1, M95) -> 328.36 | AF95: =IF(5 = Q95, N95 * -1, N95) -> 731.9 | AG95: =IF(5 = Q95, O95 * -1, O95) -> 6922.25 | AH95: Repairs & Maintenance
A96: 7444 | B96: Redecorating - Painting | C96: 7442.5 | D96: 2096.47 | E96: 6222.4 | F96: 4109.63 | G96: 2737.92 | H96: 762.92 | I96: 1047.21 | J96: 3413.97 | K96: -1796.45 | L96: 806.31 | M96: 317.89 | N96: 1616.91 | O96: 28777.68 | Q96: 4 | R96: Teagen | S96: TEA | U96: =IF(5 = Q96, C96 * -1, C96) -> 7442.5 | V96: =IF(5 = Q96, D96 * -1, D96) -> 2096.47 | W96: =IF(5 = Q96, E96 * -1, E96) -> 6222.4 | X96: =IF(5 = Q96, F96 * -1, F96) -> 4109.63 | Y96: =IF(5 = Q96, G96 * -1, G96) -> 2737.92 | Z96: =IF(5 = Q96, H96 * -1, H96) -> 762.92 | AA96: =IF(5 = Q96, I96 * -1, I96) -> 1047.21 | AB96: =IF(5 = Q96, J96 * -1, J96) -> 3413.97 | AC96: =IF(5 = Q96, K96 * -1, K96) -> -1796.45 | AD96: =IF(5 = Q96, L96 * -1, L96) -> 806.31 | AE96: =IF(5 = Q96, M96 * -1, M96) -> 317.89 | AF96: =IF(5 = Q96, N96 * -1, N96) -> 1616.91 | AG96: =IF(5 = Q96, O96 * -1, O96) -> 28777.68 | AH96: Repairs & Maintenance
A97: 7450 | B97: Redecorating - Carpet Cleaning Occupied | C97: 1086.15 | D97: 3634.42 | E97: 1416.89 | F97: 2278.68 | G97: 1193.35 | H97: 1583.39 | I97: 2249.47 | J97: 1150 | K97: 1913.49 | L97: 2676.13 | M97: 532.85 | N97: 310 | O97: 20024.82 | Q97: 4 | R97: Teagen | S97: TEA | U97: =IF(5 = Q97, C97 * -1, C97) -> 1086.15 | V97: =IF(5 = Q97, D97 * -1, D97) -> 3634.42 | W97: =IF(5 = Q97, E97 * -1, E97) -> 1416.89 | X97: =IF(5 = Q97, F97 * -1, F97) -> 2278.68 | Y97: =IF(5 = Q97, G97 * -1, G97) -> 1193.35 | Z97: =IF(5 = Q97, H97 * -1, H97) -> 1583.39 | AA97: =IF(5 = Q97, I97 * -1, I97) -> 2249.47 | AB97: =IF(5 = Q97, J97 * -1, J97) -> 1150 | AC97: =IF(5 = Q97, K97 * -1, K97) -> 1913.49 | AD97: =IF(5 = Q97, L97 * -1, L97) -> 2676.13 | AE97: =IF(5 = Q97, M97 * -1, M97) -> 532.85 | AF97: =IF(5 = Q97, N97 * -1, N97) -> 310 | AG97: =IF(5 = Q97, O97 * -1, O97) -> 20024.82 | AH97: Repairs & Maintenance
A98: 7451 | B98: Redecorating - Carpet Cleaning Vacant | C98: 685 | D98: 370 | E98: 815 | F98: 1121.5 | G98: 1474.06 | H98: 1208.29 | I98: 1140 | J98: 1210 | K98: 820 | L98: 721.76 | M98: 460 | N98: 325 | O98: 10350.61 | Q98: 4 | R98: Teagen | S98: TEA | U98: =IF(5 = Q98, C98 * -1, C98) -> 685 | V98: =IF(5 = Q98, D98 * -1, D98) -> 370 | W98: =IF(5 = Q98, E98 * -1, E98) -> 815 | X98: =IF(5 = Q98, F98 * -1, F98) -> 1121.5 | Y98: =IF(5 = Q98, G98 * -1, G98) -> 1474.06 | Z98: =IF(5 = Q98, H98 * -1, H98) -> 1208.29 | AA98: =IF(5 = Q98, I98 * -1, I98) -> 1140 | AB98: =IF(5 = Q98, J98 * -1, J98) -> 1210 | AC98: =IF(5 = Q98, K98 * -1, K98) -> 820 | AD98: =IF(5 = Q98, L98 * -1, L98) -> 721.76 | AE98: =IF(5 = Q98, M98 * -1, M98) -> 460 | AF98: =IF(5 = Q98, N98 * -1, N98) -> 325 | AG98: =IF(5 = Q98, O98 * -1, O98) -> 10350.61 | AH98: Repairs & Maintenance
A99: 7452 | B99: Redecorating - General Cleaning Common | C99: 0 | D99: 0 | E99: 0 | F99: 0 | G99: 0 | H99: 0 | I99: 25.14 | J99: 0 | K99: 0 | L99: 148.81 | M99: 0 | N99: 179.18 | O99: 353.13 | Q99: 4 | R99: Teagen | S99: TEA | U99: =IF(5 = Q99, C99 * -1, C99) -> 0 | V99: =IF(5 = Q99, D99 * -1, D99) -> 0 | W99: =IF(5 = Q99, E99 * -1, E99) -> 0 | X99: =IF(5 = Q99, F99 * -1, F99) -> 0 | Y99: =IF(5 = Q99, G99 * -1, G99) -> 0 | Z99: =IF(5 = Q99, H99 * -1, H99) -> 0 | AA99: =IF(5 = Q99, I99 * -1, I99) -> 25.14 | AB99: =IF(5 = Q99, J99 * -1, J99) -> 0 | AC99: =IF(5 = Q99, K99 * -1, K99) -> 0 | AD99: =IF(5 = Q99, L99 * -1, L99) -> 148.81 | AE99: =IF(5 = Q99, M99 * -1, M99) -> 0 | AF99: =IF(5 = Q99, N99 * -1, N99) -> 179.18 | AG99: =IF(5 = Q99, O99 * -1, O99) -> 353.13 | AH99: Repairs & Maintenance
A100: 7453 | B100: Redecorating - General Cleaning Vacant | C100: 0 | D100: 0 | E100: 460 | F100: 670 | G100: 1160 | H100: 980 | I100: 1810 | J100: 740 | K100: 1610 | L100: 240 | M100: 630 | N100: 2112.05 | O100: 10412.05 | Q100: 4 | R100: Teagen | S100: TEA | U100: =IF(5 = Q100, C100 * -1, C100) -> 0 | V100: =IF(5 = Q100, D100 * -1, D100) -> 0 | W100: =IF(5 = Q100, E100 * -1, E100) -> 460 | X100: =IF(5 = Q100, F100 * -1, F100) -> 670 | Y100: =IF(5 = Q100, G100 * -1, G100) -> 1160 | Z100: =IF(5 = Q100, H100 * -1, H100) -> 980 | AA100: =IF(5 = Q100, I100 * -1, I100) -> 1810 | AB100: =IF(5 = Q100, J100 * -1, J100) -> 740 | AC100: =IF(5 = Q100, K100 * -1, K100) -> 1610 | AD100: =IF(5 = Q100, L100 * -1, L100) -> 240 | AE100: =IF(5 = Q100, M100 * -1, M100) -> 630 | AF100: =IF(5 = Q100, N100 * -1, N100) -> 2112.05 | AG100: =IF(5 = Q100, O100 * -1, O100) -> 10412.05 | AH100: Repairs & Maintenance
A101: 7454 | B101: Redecorating - Sheetrock | C101: 1020 | D101: 760 | E101: 850 | F101: 540 | G101: 2455 | H101: -690 | I101: 1920 | J101: 1250 | K101: 1345 | L101: -250 | M101: 675 | N101: 1200 | O101: 11075 | Q101: 4 | R101: Teagen | S101: TEA | U101: =IF(5 = Q101, C101 * -1, C101) -> 1020 | V101: =IF(5 = Q101, D101 * -1, D101) -> 760 | W101: =IF(5 = Q101, E101 * -1, E101) -> 850 | X101: =IF(5 = Q101, F101 * -1, F101) -> 540 | Y101: =IF(5 = Q101, G101 * -1, G101) -> 2455 | Z101: =IF(5 = Q101, H101 * -1, H101) -> -690 | AA101: =IF(5 = Q101, I101 * -1, I101) -> 1920 | AB101: =IF(5 = Q101, J101 * -1, J101) -> 1250 | AC101: =IF(5 = Q101, K101 * -1, K101) -> 1345 | AD101: =IF(5 = Q101, L101 * -1, L101) -> -250 | AE101: =IF(5 = Q101, M101 * -1, M101) -> 675 | AF101: =IF(5 = Q101, N101 * -1, N101) -> 1200 | AG101: =IF(5 = Q101, O101 * -1, O101) -> 11075 | AH101: Repairs & Maintenance
B102: Redecorating | C102: 11357.71 | D102: 8522.5 | E102: 10479.65 | F102: 8852.06 | G102: 9285.74 | H102: 3978.6 | I102: 8640.18 | J102: 8304.73 | K102: 4225.76 | L102: 4849.47 | M102: 2944.1 | N102: 6475.04 | O102: 87915.54 | Q102: 4 | R102: Teagen | S102: TEA | U102: =IF(5 = Q102, C102 * -1, C102) -> 11357.71 | V102: =IF(5 = Q102, D102 * -1, D102) -> 8522.5 | W102: =IF(5 = Q102, E102 * -1, E102) -> 10479.65 | X102: =IF(5 = Q102, F102 * -1, F102) -> 8852.06 | Y102: =IF(5 = Q102, G102 * -1, G102) -> 9285.74 | Z102: =IF(5 = Q102, H102 * -1, H102) -> 3978.6 | AA102: =IF(5 = Q102, I102 * -1, I102) -> 8640.18 | AB102: =IF(5 = Q102, J102 * -1, J102) -> 8304.73 | AC102: =IF(5 = Q102, K102 * -1, K102) -> 4225.76 | AD102: =IF(5 = Q102, L102 * -1, L102) -> 4849.47 | AE102: =IF(5 = Q102, M102 * -1, M102) -> 2944.1 | AF102: =IF(5 = Q102, N102 * -1, N102) -> 6475.04 | AG102: =IF(5 = Q102, O102 * -1, O102) -> 87915.54
...

Sheet Teagen - Variance
A2: P/L Report
A3: Teagen
A4: Jun 2024
A5: Accrual Basis
C7: Jun 2024 | H7: YTD ( Jan 2024 - Jun 2024 )
A8: Account | B8: Account Name | C8: Actual | D8: Budget | E8: $ Variance | F8: % Variance | G8: Variance Notes | H8: Actual | I8: Budget | J8: $ Variance | K8: % Variance | M8: Income Statement Budget Vs Actual: Per Sq.Ft. | N8: Income Statement Budget Vs Actual: Per Unit | O8: Income Statement Budget Vs Actual: May 2023 | P8: Income Statement Budget Vs Actual: Actual | Q8: Income Statement Budget Vs Actual: Budget | R8: Income Statement Budget Vs Actual: Per Sq.Ft. | S8: Income Statement Budget Vs Actual: YTD ( 2023 ) | T8: Income Statement Budget Vs Actual: % of Income | U8: Income Statement Budget Vs Actual: % of Income | V8: Income Statement Budget Vs Actual: Prior Year End | W8: Income Statement Budget Vs Actual: Annual Budget | X8: Income Statement Budget Vs Actual: Per Sq.Ft. (Annualized) | Y8: Income Statement Budget Vs Actual: GL Account Type Id | Z8: Income Statement Budget Vs Actual: % of Income | AA8: Income Statement Budget Vs Actual: % of Income | AB8: Income Statement Budget Vs Actual: % of Income | AC8: Income Statement Budget Vs Actual: % of Income | AD8: Income Statement Budget Vs Actual: Prior Mtd Actual Changed Sign | AE8: Income Statement Budget Vs Actual: Mtd Actual Changed Sign | AF8: Income Statement Budget Vs Actual: Mtd Budget Changed Sign | AG8: Income Statement Budget Vs Actual: Mtd Variance Temp | AH8: Income Statement Budget Vs Actual: Prior Ytd Actual Changed Sign | AI8: Income Statement Budget Vs Actual: Prior Year Actual Changed Sign | AJ8: Income Statement Budget Vs Actual: Ytd Actual Changed Sign | AK8: Income Statement Budget Vs Actual: Ytd Budget Changed Sign | AL8: Income Statement Budget Vs Actual: Annual Budget Changed Sign | AM8: Income Statement Budget Vs Actual: Ytd Variance Temp | AN8: Income Statement Budget Vs Actual: Income Expense Converter | AO8: Income Statement Budget Vs Actual: Variance Converter
A9: Income
A10: Rental Income
A11: 5001 | B11: Market Rent | C11: 275959.53 | D11: 283033.12 | E11: -7073.59 | F11: -0.024992093 | G11: This reflects the difference between market rent and effective rent. The number changes based on rent offers and occupancy goals. Pricing is reviewed weekly. | H11: 1661280.3 | I11: 1672131.4 | J11: -10851.18 | K11: -0.00648943 | O11: 265528.07 | S11: 1350334.2 | T11: 1492779.8 | U11: 1453480.7 | V11: 3218646.9 | W11: 3406969.3 | Y11: 4 | Z11: 301371.65 | AA11: 297526.14 | AD11: 265528.07 | AE11: 275544.36 | AF11: 281293.01 | AG11: -5748.65 | AH11: 1350334.2 | AI11: 3218646.9 | AJ11: 1385320.7 | AK11: 1389098.3 | AL11: 3406969.3 | AM11: -3777.59 | AN11: 1 | AO11: 1
A12: 5002 | B12: Gain/Loss To Lease | C12: -17799.09 | D12: -15912.15 | E12: -1886.94 | F12: -0.11858485 | G12: This reflects the difference between market rent and actual rent per unit. | H12: -113917.17 | I12: -101049.45 | J12: -12867.72 | K12: -0.12734082 | O12: -14229.48 | S12: -111704.61 | T12: 1492779.8 | U12: 1453480.7 | V12: -193326.84 | W12: -188549.27 | Y12: 4 | Z12: 301371.65 | AA12: 297526.14 | AD12: -14229.48 | AE12: -16892.25 | AF12: -16286.54 | AG12: -605.71 | AH12: -111704.61 | AI12: -193326.84 | AJ12: -96118.08 | AK12: -85137.3 | AL12: -188549.27 | AM12: -10980.78 | AN12: 1 | AO12: 1
A13: 5954 | B13: Monthly Yard Revenue | C13: 1904.5 | D13: 0 | E13: 1904.5 | F13: 1 | G13: This reflects fifteen residents paying $125 for a pet yard, one paying $65 and five paying $60 per month. | H13: 10308.18 | I13: 0 | J13: 10308.18 | K13: 1 | O13: 556.93 | S13: 1726.34 | T13: 1492779.8 | U13: 1453480.7 | V13: 9166.08 | W13: 0 | Y13: 4 | Z13: 301371.65 | AA13: 297526.14 | AD13: 556.93 | AE13: 1926.57 | AF13: 0 | AG13: 1926.57 | AH13: 1726.34 | AI13: 9166.08 | AJ13: 8403.68 | AK13: 0 | AL13: 0 | AM13: 8403.68 | AN13: 1 | AO13: 1
A14: 5006 | B14: Washer/Dryer | C14: 0 | D14: 0 | E14: 0 | F14: 0 | H14: -147.13 | I14: 0 | J14: -147.13 | K14: -1 | O14: 0 | S14: 0 | T14: 1492779.8 | U14: 1453480.7 | V14: 147.13 | W14: 0 | Y14: 4 | Z14: 301371.65 | AA14: 297526.14 | AD14: 0 | AE14: 0 | AF14: 0 | AG14: 0 | AH14: 0 | AI14: 147.13 | AJ14: -147.13 | AK14: 0 | AL14: 0 | AM14: -147.13 | AN14: 1 | AO14: 1
B15: Rental Income | C15: 260064.94 | D15: 267120.97 | E15: -7056.03 | F15: -0.026415111 | H15: 1557524.1 | I15: 1571082 | J15: -13557.85 | K15: -0.008629626 | O15: 251855.52 | S15: 1240356 | V15: 3034633.3 | W15: 3218420 | Y15: 4 | AD15: 251855.52 | AE15: 260578.68 | AF15: 265006.47 | AG15: -4427.79 | AH15: 1240356 | AI15: 3034633.3 | AJ15: 1297459.2 | AK15: 1303961 | AL15: 3218420 | AM15: -6501.82
A16: Vacancy, Losses & Concessions
A17: 5102 | B17: Delinquent Rent/Bad Debt | C17: -11435.88 | D17: -5500 | E17: -5935.88 | F17: -1.0792509 | H17: -42369.45 | I17: -37500 | J17: -4869.45 | K17: -0.129852 | O17: -2677.99 | S17: -23218.86 | T17: 1492779.8 | U17: 1453480.7 | V17: -75952.42 | W17: -66000 | Y17: 4 | Z17: 301371.65 | AA17: 297526.14 | AD17: -2677.99 | AE17: -11395.38 | AF17: -5500 | AG17: -5895.38 | AH17: -23218.86 | AI17: -75952.42 | AJ17: -30933.57 | AK17: -32000 | AL17: -66000 | AM17: 1066.43 | AN17: 1 | AO17: 1
A18: 5950 | B18: Bad Debt Recovery | C18: 801.97 | D18: 0 | E18: 801.97 | F18: 1 | H18: 801.97 | I18: 0 | J18: 801.97 | K18: 1 | O18: 0 | S18: -7849.43 | T18: 1492779.8 | U18: 1453480.7 | V18: -58789.51 | W18: -12000 | Y18: 4 | Z18: 301371.65 | AA18: 297526.14 | AD18: 0 | AE18: -3024.95 | AF18: -1000 | AG18: -2024.95 | AH18: -7849.43 | AI18: -58789.51 | AJ18: -18272.55 | AK18: -5000 | AL18: -12000 | AM18: -13272.55 | AN18: 1 | AO18: 1
A19: 5103 | B19: Rental Concessions | C19: -9486.11 | D19: -1000 | E19: -8486.11 | F19: -8.48611 | G19: This reflects seven veteran/military discounts, eighteen $500.00 Move-In Specials and one $250.00 Move-In Special. | H19: -27758.66 | I19: -6000 | J19: -21758.66 | K19: -3.6264433 | O19: -19336.73 | S19: -119429.33 | T19: 1492779.8 | U19: 1453480.7 | V19: -281245.32 | W19: -166253.48 | Y19: 4 | Z19: 301371.65 | AA19: 297526.14 | AD19: -19336.73 | AE19: -21026.49 | AF19: -13802.15 | AG19: -7224.34 | AH19: -119429.33 | AI19: -281245.32 | AJ19: -91591.8 | AK19: -68667.42 | AL19: -166253.48 | AM19: -22924.38 | AN19: 1 | AO19: 1
A20: 5104 | B20: Vacancy Loss | C20: -21367.33 | D20: -13836.66 | E20: -7530.67 | F20: -0.5442549 | G20: This reflects the vacancy loss for the month vs. budgeted. The average occupancy for the month was 90.25% vs. 95% | H20: -112959.13 | I20: -82504.08 | J20: -30455.05 | K20: -0.36913387 | O20: -1168.45 | S20: -5304.64 | T20: 1492779.8 | U20: 1453480.7 | V20: -11113.2 | W20: -21000 | Y20: 4 | Z20: 301371.65 | AA20: 297526.14 | AD20: -1168.45 | AE20: -1179.86 | AF20: -1750 | AG20: 570.14 | AH20: -5304.64 | AI20: -11113.2 | AJ20: -4284.8 | AK20: -8750 | AL20: -21000 | AM20: 4465.2 | AN20: 1 | AO20: 1
A21: 5107 | B21: Employee Rent Discount | C21: -1179.86 | D21: -1750 | E21: 570.14 | F21: 0.32579429 | G21: This reflects four employees who live on site and receiving the monthly employee discount. | H21: -5464.66 | I21: -10500 | J21: 5035.34 | K21: 0.47955619 | O21: -972 | S21: -4894 | T21: 1492779.8 | U21: 1453480.7 | V21: -11740 | W21: -12355.36 | Y21: 4 | Z21: 301371.65 | AA21: 297526.14 | AD21: -972 | AE21: -1065 | AF21: -1025.73 | AG21: -39.27 | AH21: -4894 | AI21: -11740 | AJ21: -5325 | AK21: -5103.12 | AL21: -12355.36 | AM21: -221.88 | AN21: 1 | AO21: 1
A22: 5109 | B22: Model Vacancy Loss | C22: -1065 | D22: -1028.29 | E22: -36.71 | F22: -0.035700046 | G22: This reflects one one bedroom one bathroom model apartment home. | H22: -6390 | I22: -6131.41 | J22: -258.59 | K22: -0.042174638 | O22: -24155.17 | S22: -160696.26 | V22: -438840.45 | W22: -277608.84 | Y22: 4 | AD22: -24155.17 | AE22: -37691.68 | AF22: -23077.88 | AG22: -14613.8 | AH22: -160696.26 | AI22: -438840.45 | AJ22: -150407.72 | AK22: -119520.54 | AL22: -277608.84 | AM22: -30887.18
B23: Vacancy, Losses & Concessions | C23: -43732.21 | D23: -23114.95 | E23: -20617.26 | F23: -0.89194482 | H23: -194139.93 | I23: -142635.49 | J23: -51504.44 | K23: -0.36109134 | O23: 227700.35 | S23: 1079659.7 | V23: 2595792.8 | W23: 2940811.2 | Y23: 4 | AD23: 227700.35 | AE23: 222887 | AF23: 241928.59 | AG23: -19041.59 | AH23: 1079659.7 | AI23: 2595792.8 | AJ23: 1147051.5 | AK23: 1184440.5 | AL23: 2940811.2 | AM23: -37389
B24: Net Rental Income | C24: 216332.73 | D24: 244006.02 | E24: -27673.29 | F24: -0.11341232 | H24: 1363384.2 | I24: 1428446.5 | J24: -65062.29 | K24: -0.045547586
A25: Other Income | O25: 908.88 | S25: 4391.07 | T25: 1492779.8 | U25: 1453480.7 | V25: 11227.82 | W25: 10950 | Y25: 4 | Z25: 301371.65 | AA25: 297526.14 | AD25: 908.88 | AE25: 1491.55 | AF25: 875 | AG25: 616.55 | AH25: 4391.07 | AI25: 11227.82 | AJ25: 7658.88 | AK25: 4125 | AL25: 10950 | AM25: 3533.88 | AN25: 1 | AO25: 1
A26: 5007 | B26: Other Income - Monthly Pet Rent | C26: 1374.68 | D26: 900 | E26: 474.68 | F26: 0.52742222 | G26: This reflects income collected for pet rent for the month. The property is charging $30 per pet for pet rent. | H26: 9033.56 | I26: 5025 | J26: 4008.56 | K26: 0.79772338 | O26: 3379.69 | S26: 13857.14 | T26: 1492779.8 | U26: 1453480.7 | V26: 44299.16 | W26: 48480 | Y26: 4 | Z26: 301371.65 | AA26: 297526.14 | AD26: 3379.69 | AE26: 6702.92 | AF26: 3890 | AG26: 2812.92 | AH26: 13857.14 | AI26: 44299.16 | AJ26: 31660.25 | AK26: 18450 | AL26: 48480 | AM26: 13210.25 | AN26: 1 | AO26: 1
A27: 5013 | B27: Other Income - Washer/Dryer Rental | C27: 6884.73 | D27: 3990 | E27: 2894.73 | F27: 0.72549624 | G27: This reflects income collected for washer/dryer connection rent for the month. The property is charging $20.00 per unit for connections and $50 per rental set. As of June 1, 2024 rental sets are priced at $75.00. | H27: 38544.98 | I27: 22440 | J27: 16104.98 | K27: 0.71769073 | O27: 1601.15 | S27: 3221.86 | T27: 1492779.8 | U27: 1453480.7 | V27: 6588.96 | W27: 6600 | Y27: 4 | Z27: 301371.65 | AA27: 297526.14 | AD27: 1601.15 | AE27: 1815.18 | AF27: 0 | AG27: 1815.18 | AH27: 3221.86 | AI27: 6588.96 | AJ27: 3593.2 | AK27: 1650 | AL27: 6600 | AM27: 1943.2 | AN27: 1 | AO27: 1
A28: 5202 | B28: Other Income - Cable TV Income | C28: 0 | D28: 1650 | E28: -1650 | F28: -1 | H28: 3593.2 | I28: 3300 | J28: 293.2 | K28: 0.088848485 | O28: 2851.87 | S28: 11183.21 | T28: 1492779.8 | U28: 1453480.7 | V28: 37343.3 | W28: 53352 | Y28: 4 | Z28: 301371.65 | AA28: 297526.14 | AD28: 2851.87 | AE28: 4258.97 | AF28: 4446 | AG28: -187.03 | AH28: 11183.21 | AI28: 37343.3 | AJ28: 21278.73 | AK28: 22230 | AL28: 53352 | AM28: -951.27 | AN28: 1 | AO28: 1
A29: 5204 | B29: Other Income - Loss Damage Waiver | C29: 4290.01 | D29: 4446 | E29: -155.99 | F29: -0.03508547 | G29: This reflects income collected for RLL for insurance income for the month. The property is charging $16 per unit with new move-ins and renewing residents. | H29: 25568.74 | I29: 26676 | J29: -1107.26 | K29: -0.041507722 | O29: 16181.08 | S29: 68246.35 | T29: 1492779.8 | U29: 1453480.7 | V29: 172145.26 | W29: 164825 | Y29: 4 | Z29: 301371.65 | AA29: 297526.14 | AD29: 16181.08 | AE29: 22486.9 | AF29: 13675 | AG29: 8811.9 | AH29: 68246.35 | AI29: 172145.26 | AJ29: 89841.39 | AK29: 67850 | AL29: 164825 | AM29: 21991.39 | AN29: 1 | AO29: 1
A30: 5211 | B30: Other Income - Water/Sewer Reimbursements | C30: 19185.04 | D30: 14000 | E30: 5185.04 | F30: 0.37036 | G30: This reflects reimbursements billed for the month. Residents are currently billed through Entrata Utilities at the 95% bill-back rate. | H30: 109026.43 | I30: 81850 | J30: 27176.43 | K30: 0.33202724 | O30: 7195.99 | S30: 28019.59 | T30: 1492779.8 | U30: 1453480.7 | V30: 97861.98 | W30: 124488 | Y30: 4 | Z30: 301371.65 | AA30: 297526.14 | AD30: 7195.99 | AE30: 10633.19 | AF30: 10374 | AG30: 259.19 | AH30: 28019.59 | AI30: 97861.98 | AJ30: 53556.11 | AK30: 51870 | AL30: 124488 | AM30: 1686.11 | AN30: 1 | AO30: 1
A31: 5212 | B31: Other Income - Trash Reimbursements | C31: 10610.51 | D31: 10374 | E31: 236.51 | F31: 0.022798342 | G31: This reflects residents being billed $35 for valet trash. | H31: 64166.62 | I31: 62244 | J31: 1922.62 | K31: 0.030888439 | O31: 2028.99 | S31: 6508.2 | T31: 1492779.8 | U31: 1453480.7 | V31: 21022.28 | W31: 28454.4 | Y31: 4 | Z31: 301371.65 | AA31: 297526.14 | AD31: 2028.99 | AE31: 2241.37 | AF31: 2371.2 | AG31: -129.83 | AH31: 6508.2 | AI31: 21022.28 | AJ31: 11274.76 | AK31: 11856 | AL31: 28454.4 | AM31: -581.24 | AN31: 1 | AO31: 1
A32: 5220 | B32: Other Income - Pest Control Reimbursement | C32: 2236.77 | D32: 2371.2 | E32: -134.43 | F32: -0.056692814 | G32: This reflects income for the pest control fee charge at $9 per month for new residents and all renewals. | H32: 13511.53 | I32: 14227.2 | J32: -715.67 | K32: -0.050302941 | O32: 1941.24 | S32: 7540.32 | T32: 1492779.8 | U32: 1453480.7 | V32: 25398.14 | W32: 35568 | Y32: 4 | Z32: 301371.65 | AA32: 297526.14 | AD32: 1941.24 | AE32: 2962.51 | AF32: 2964 | AG32: -1.49 | AH32: 7540.32 | AI32: 25398.14 | AJ32: 14490.31 | AK32: 14820 | AL32: 35568 | AM32: -329.69 | AN32: 1 | AO32: 1
A33: 5804 | B33: Other Income - Amenity Fee | C33: 3020.08 | D33: 2964 | E33: 56.08 | F33: 0.018920378 | G33: This reflects income for the Amenity fee charge back at $12 per month for new residents and all renewals | H33: 17510.39 | I33: 17784 | J33: -273.61 | K33: -0.015385178 | O33: 2500 | S33: 11050 | T33: 1492779.8 | U33: 1453480.7 | V33: 32450 | W33: 33000 | Y33: 4 | Z33: 301371.65 | AA33: 297526.14 | AD33: 2500 | AE33: 3250 | AF33: 2750 | AG33: 500 | AH33: 11050 | AI33: 32450 | AJ33: 18650 | AK33: 13750 | AL33: 33000 | AM33: 4900 | AN33: 1 | AO33: 1
A34: 5805 | B34: Other Income - Late Charges | C34: 3650 | D34: 2750 | E34: 900 | F34: 0.32727273 | G34: This reflects late fees for the month based on the lease which is $50 on the 6th of the month. | H34: 22300 | I34: 16500 | J34: 5800 | K34: 0.35151515 | O34: 0 | S34: 0 | T34: 1492779.8 | U34: 1453480.7 | V34: 477.67 | W34: 2400 | Y34: 4 | Z34: 301371.65 | AA34: 297526.14 | AD34: 0 | AE34: 0 | AF34: 600 | AG34: -600 | AH34: 0 | AI34: 477.67 | AJ34: 0 | AK34: 1200 | AL34: 2400 | AM34: -1200 | AN34: 1 | AO34: 1
A35: 5810 | B35: Other Income - Laundry Income | C35: 0 | D35: 0 | E35: 0 | F35: 0 | H35: 0 | I35: 1200 | J35: -1200 | K35: -1 | O35: 1726.11 | S35: 6780.25 | T35: 1492779.8 | U35: 1453480.7 | V35: 22449.33 | W35: 32011.2 | Y35: 4 | Z35: 301371.65 | AA35: 297526.14 | AD35: 1726.11 | AE35: 2601.93 | AF35: 2667.6 | AG35: -65.67 | AH35: 6780.25 | AI35: 22449.33 | AJ35: 12848.39 | AK35: 13338 | AL35: 32011.2 | AM35: -489.61 | AN35: 1 | AO35: 1
A36: 5860 | B36: Other Income - Parcel Services Income | C36: 2628.41 | D36: 2667.6 | E36: -39.19 | F36: -0.014691108 | H36: 15476.8 | I36: 16005.6 | J36: -528.8 | K36: -0.033038437 | O36: 681.55 | S36: 1061.16 | T36: 1492779.8 | U36: 1453480.7 | V36: 19808.67 | W36: 44382 | Y36: 4 | Z36: 301371.65 | AA36: 297526.14 | AD36: 681.55 | AE36: 6680.23 | AF36: 3436 | AG36: 3244.23 | AH36: 1061.16 | AI36: 19808.67 | AJ36: 28467.89 | AK36: 15430 | AL36: 44382 | AM36: 13037.89 | AN36: 1 | AO36: 1
A37: 5861 | B37: Other Income - Lease Lock | C37: 7024.97 | D37: 3611 | E37: 3413.97 | F37: 0.94543617 | H37: 35492.86 | I37: 19041 | J37: 16451.86 | K37: 0.8640229 | O37: 0 | S37: 1930 | T37: 1492779.8 | U37: 1453480.7 | V37: 3105.01 | W37: 3490.5 | Y37: 4 | Z37: 301371.65 | AA37: 297526.14 | AD37: 0 | AE37: 415 | AF37: 223.75 | AG37: 191.25 | AH37: 1930 | AI37: 3105.01 | AJ37: 1712.12 | AK37: 671.25 | AL37: 3490.5 | AM37: 1040.87 | AN37: 1 | AO37: 1
A38: 5890 | B38: Other Income - Miscellaneous Income | C38: 536.85 | D38: 268.5 | E38: 268.35 | F38: 0.99944134 | G38: This reflects charges for three residents signed up for Rent Plus at $8.95 per resident and the pest control/bed bug charge back for apartment 244. | H38: 2248.97 | I38: 939.75 | J38: 1309.22 | K38: 1.3931578 | O38: 375 | S38: 1365 | T38: 1492779.8 | U38: 1453480.7 | V38: 4290 | W38: 2100 | Y38: 4 | Z38: 301371.65 | AA38: 297526.14 | AD38: 375 | AE38: 75 | AF38: 225 | AG38: -150 | AH38: 1365 | AI38: 4290 | AJ38: 2400 | AK38: 900 | AL38: 2100 | AM38: 1500 | AN38: 1 | AO38: 1
A39: 5891 | B39: Other Income - NSF Charges | C39: 150 | D39: 225 | E39: -75 | F39: -0.33333333 | G39: This reflects the posting of two NSF fees at $75 each. | H39: 2550 | I39: 1125 | J39: 1425 | K39: 1.2666667 | O39: 1310 | S39: 2170 | T39: 1492779.8 | U39: 1453480.7 | V39: 7907.63 | W39: 3200 | Y39: 4 | Z39: 301371.65 | AA39: 297526.14 | AD39: 1310 | AE39: 1200 | AF39: 400 | AG39: 800 | AH39: 2170 | AI39: 7907.63 | AJ39: 5879.4 | AK39: 1200 | AL39: 3200 | AM39: 4679.4 | AN39: 1 | AO39: 1
A40: 5892 | B40: Other Income - Non-Refundable Pet Fee | C40: 2400 | D40: 400 | E40: 2000 | F40: 5 | G40: This reflects six pet fee charges at $400.00. | H40: 8279.4 | I40: 1600 | J40: 6679.4 | K40: 4.174625 | O40: 1188.37 | S40: 6924.12 | T40: 1492779.8 | U40: 1453480.7 | V40: 15786.43 | W40: 15000 | Y40: 4 | Z40: 301371.65 | AA40: 297526.14 | AD40: 1188.37 | AE40: 3075.88 | AF40: 1250 | AG40: 1825.88 | AH40: 6924.12 | AI40: 15786.43 | AJ40: 12329.97 | AK40: 6250 | AL40: 15000 | AM40: 6079.97 | AN40: 1 | AO40: 1
A41: 5893 | B41: Other Income - Damages | C41: 2159.95 | D41: 1250 | E41: 909.95 | F41: 0.72796 | G41: This reflects collected move-out damages. | H41: 14489.92 | I41: 7500 | J41: 6989.92 | K41: 0.93198933 | O41: 1450 | S41: 6950 | T41: 1492779.8 | U41: 1453480.7 | V41: 16020 | W41: 16750 | Y41: 4 | Z41: 301371.65 | AA41: 297526.14 | AD41: 1450 | AE41: 2000 | AF41: 1450 | AG41: 550 | AH41: 6950 | AI41: 16020 | AJ41: 6075 | AK41: 6950 | AL41: 16750 | AM41: -875 | AN41: 1 | AO41: 1
A42: 5896 | B42: Other Income - Application Fee | C42: 2100 | D42: 1500 | E42: 600 | F42: 0.4 | G42: This reflects twenty-eight paid application fees at $75.00. | H42: 8175 | I42: 8450 | J42: -275 | K42: -0.032544379 | O42: 550 | S42: 3300 | T42: 1492779.8 | U42: 1453480.7 | V42: 8050 | W42: 6000 | Y42: 4 | Z42: 301371.65 | AA42: 297526.14 | AD42: 550 | AE42: 1050 | AF42: 500 | AG42: 550 | AH42: 3300 | AI42: 8050 | AJ42: 3550 | AK42: 2500 | AL42: 6000 | AM42: 1050 | AN42: 1 | AO42: 1
A43: 5897 | B43: Other Income - Non-Refundable Gate/Pool/Fitness Fee | C43: 800 | D43: 500 | E43: 300 | F43: 0.6 | G43: This reflects sixteen gate fab fees collected at $50.00 each. | H43: 4350 | I43: 3000 | J43: 1350 | K43: 0.45 | O43: 250.64 | S43: 3381.17 | T43: 1492779.8 | U43: 1453480.7 | V43: 14632.81 | W43: 12000 | Y43: 4 | Z43: 301371.65 | AA43: 297526.14 | AD43: 250.64 | AE43: 1344.02 | AF43: 1000 | AG43: 344.02 | AH43: 3381.17 | AI43: 14632.81 | AJ43: 8111.9 | AK43: 5000 | AL43: 12000 | AM43: 3111.9 | AN43: 1 | AO43: 1
A44: 5898 | B44: Other Income - Cancellation Fee | C44: 1774.87 | D44: 1000 | E44: 774.87 | F44: 0.77487 | G44: This reflects one paid cancellation fee. | H44: 9886.77 | I44: 6000 | J44: 3886.77 | K44: 0.647795 | O44: 1875 | S44: 10802 | T44: 1492779.8 | U44: 1453480.7 | V44: 26127 | W44: 40000 | Y44: 4 | Z44: 301371.65 | AA44: 297526.14 | AD44: 1875 | AE44: 4200 | AF44: 2500 | AG44: 1700 | AH44: 10802 | AI44: 26127 | AJ44: 12350 | AK44: 9000 | AL44: 40000 | AM44: 3350 | AN44: 1 | AO44: 1
A45: 5899 | B45: Other Income - Non-Refundable Redecorating Fee | C45: 3400 | D45: 2500 | E45: 900 | F45: 0.36 | G45: This reflects the increase of administration fees from $125.00 to $200.00. | H45: 15750 | I45: 11500 | J45: 4250 | K45: 0.36956522 | O45: 47995.56 | S45: 198681.44 | V45: 586991.45 | W45: 683051.1 | Y45: 4 | AD45: 47995.56 | AE45: 78484.65 | AF45: 55597.55 | AG45: 22887.1 | AH45: 198681.44 | AI45: 586991.45 | AJ45: 345728.3 | AK45: 269040.25 | AL45: 683051.1 | AM45: 76688.05
B46: Other Income | C46: 74226.87 | D46: 57367.3 | E46: 16859.57 | F46: 0.29388816 | H46: 419955.17 | I46: 326407.55 | J46: 93547.62 | K46: 0.2865976 | O46: 275695.91 | S46: 1278341.2 | V46: 3182784.3 | W46: 3623862.3 | Y46: 4 | AD46: 275695.91 | AE46: 301371.65 | AF46: 297526.14 | AG46: 3845.51 | AH46: 1278341.2 | AI46: 3182784.3 | AJ46: 1492779.8 | AK46: 1453480.7 | AL46: 3623862.3 | AM46: 39299.05
B47: Income | C47: 290559.6 | D47: 301373.32 | E47: -10813.72 | F47: -0.035881477 | H47: 1783339.4 | I47: 1754854.1 | J47: 28485.33 | K47: 0.016232307
A48: Operating Expenses
A49: Payroll & Related
A50: Payroll | O50: 5000 | S50: 27250 | T50: 1492779.8 | U50: 1453480.7 | V50: 62980.77 | W50: 63440 | Y50: 5 | Z50: 301371.65 | AA50: 297526.14 | AD50: -5000 | AE50: -5384.6 | AF50: -4685 | AG50: -699.6 | AH50: -27250 | AI50: -62980.77 | AJ50: -29615.31 | AK50: -25767 | AL50: -63440 | AM50: -3848.31 | AN50: -1 | AO50: 1
A51: 7008 | B51: Payroll - Manager | C51: 5384.6 | D51: 4685 | E51: -699.6 | F51: -0.14932764 | G51: Reflects one Property Manager for the site. | H51: 34999.91 | I51: 30452 | J51: -4547.91 | K51: -0.14934684 | O51: 3078.56 | S51: 15201.57 | T51: 1492779.8 | U51: 1453480.7 | V51: 35771.55 | W51: 37416 | Y51: 5 | Z51: 301371.65 | AA51: 297526.14 | AD51: -3078.56 | AE51: -2934.55 | AF51: -2861 | AG51: -73.55 | AH51: -15201.57 | AI51: -35771.55 | AJ51: -12315.84 | AK51: -15685 | AL51: -37416 | AM51: 3369.16 | AN51: -1 | AO51: 1
A52: 7012 | B52: Payroll - Assistant Manager | C52: 2980.34 | D52: 2861 | E52: -119.34 | F52: -0.041712688 | G52: Reflects one Assistant Manager for the property. | H52: 15296.18 | I52: 18546 | J52: 3249.82 | K52: 0.17523024 | O52: 1977.6 | S52: 10216.68 | T52: 1492779.8 | U52: 1453480.7 | V52: 27203.59 | W52: 35271 | Y52: 5 | Z52: 301371.65 | AA52: 297526.14 | AD52: -1977.6 | AE52: -2876.81 | AF52: -2648 | AG52: -228.81 | AH52: -10216.68 | AI52: -27203.59 | AJ52: -16009.19 | AK52: -14540 | AL52: -35271 | AM52: -1469.19 | AN52: -1 | AO52: 1
A53: 7013 | B53: Payroll - Leasing Agent | C53: 2890.43 | D53: 2648 | E53: -242.43 | F53: -0.091552115 | G53: Reflects one Leasing Professional for the site. | H53: 18899.62 | I53: 17188 | J53: -1711.62 | K53: -0.099582267 | O53: 4924.9 | S53: 26029.97 | T53: 1492779.8 | U53: 1453480.7 | V53: 64433.4 | W53: 62120 | Y53: 5 | Z53: 301371.65 | AA53: 297526.14 | AD53: -4924.9 | AE53: -5151.85 | AF53: -4710 | AG53: -441.85 | AH53: -26029.97 | AI53: -64433.4 | AJ53: -27952.14 | AK53: -25904 | AL53: -62120 | AM53: -2048.14 | AN53: -1 | AO53: 1
A54: 7016 | B54: Payroll - Maintenance Foreman | C54: 5238.46 | D54: 4710 | E54: -528.46 | F54: -0.11219958 | G54: Reflects one maintenance supervisor for the site. | H54: 33190.6 | I54: 30614 | J54: -2576.6 | K54: -0.084164108 | O54: 8955.15 | S54: 45402.32 | T54: 1492779.8 | U54: 1453480.7 | V54: 90333.37 | W54: 86111 | Y54: 5 | Z54: 301371.65 | AA54: 297526.14 | AD54: -8955.15 | AE54: -6708.19 | AF54: -6533 | AG54: -175.19 | AH54: -45402.32 | AI54: -90333.37 | AJ54: -37462.4 | AK54: -35833 | AL54: -86111 | AM54: -1629.4 | AN54: -1 | AO54: 1
A55: 7020 | B55: Payroll - Maintenance Labor | C55: 6925.57 | D55: 6533 | E55: -392.57 | F55: -0.060090311 | G55: Reflects two maintenance technicians for the site. | H55: 44387.97 | I55: 42366 | J55: -2021.97 | K55: -0.047726243 | O55: 0 | S55: 0 | T55: 1492779.8 | U55: 1453480.7 | V55: 0 | W55: 39084 | Y55: 5 | Z55: 301371.65 | AA55: 297526.14 | AD55: 0 | AE55: -2912.19 | AF55: -2973 | AG55: 60.81 | AH55: 0 | AI55: 0 | AJ55: -13937.44 | AK55: -16327 | AL55: -39084 | AM55: 2389.56 | AN55: -1 | AO55: 1
A56: 7028 | B56: Payroll - Porter | C56: 3111.09 | D56: 2973 | E56: -138.09 | F56: -0.046448032 | G56: Reflects one make-ready/porter for the site. | H56: 17048.53 | I56: 19300 | J56: 2251.47 | K56: 0.11665648 | O56: 2235.48 | S56: 12707.99 | T56: 1492779.8 | U56: 1453480.7 | V56: 30407.53 | W56: 31052 | Y56: 5 | Z56: 301371.65 | AA56: 297526.14 | AD56: -2235.48 | AE56: -2357.6 | AF56: -2324 | AG56: -33.6 | AH56: -12707.99 | AI56: -30407.53 | AJ56: -13146.51 | AK56: -12756 | AL56: -31052 | AM56: -390.51 | AN56: -1 | AO56: 1
A57: 7036 | B57: Payroll - Maid | C57: 2395.88 | D57: 2324 | E57: -71.88 | F57: -0.030929432 | G57: Reflects one housekeeper for the property. | H57: 15542.39 | I57: 15080 | J57: -462.39 | K57: -0.030662467 | O57: 26171.69 | S57: 136808.53 | V57: 311130.21 | W57: 354494 | Y57: 5 | AD57: -26171.69 | AE57: -28325.79 | AF57: -26734 | AG57: -1591.79 | AH57: -136808.53 | AI57: -311130.21 | AJ57: -150438.83 | AK57: -146812 | AL57: -354494 | AM57: -3626.83
B58: Payroll | C58: 28926.37 | D58: 26734 | E58: -2192.37 | F58: -0.082006808 | H58: 179365.2 | I58: 173546 | J58: -5819.2 | K58: -0.033531168
A59: Payroll Related | O59: 2607.57 | S59: 13937.15 | T59: 1492779.8 | U59: 1453480.7 | V59: 30098.6 | W59: 31101.92 | Y59: 5 | Z59: 301371.65 | AA59: 297526.14 | AD59: -2607.57 | AE59: -2735.81 | AF59: -2379.49 | AG59: -356.32 | AH59: -13937.15 | AI59: -30098.6 | AJ59: -15106.69 | AK59: -12902.85 | AL59: -31101.92 | AM59: -2203.84 | AN59: -1 | AO59: 1
A60: 7101 | B60: Payroll Related - Payroll Taxes | C60: 2694.33 | D60: 2379.49 | E60: -314.84 | F60: -0.13231407 | H60: 17801.02 | I60: 15282.34 | J60: -2518.68 | K60: -0.16480984 | O60: 1243.27 | S60: 3272.1 | T60: 1492779.8 | U60: 1453480.7 | V60: 39082.14 | W60: 21528 | Y60: 5 | Z60: 301371.65 | AA60: 297526.14 | AD60: -1243.27 | AE60: -3859.26 | AF60: -1794 | AG60: -2065.26 | AH60: -3272.1 | AI60: -39082.14 | AJ60: -18841.4 | AK60: -8970 | AL60: -21528 | AM60: -9871.4 | AN60: -1 | AO60: 1
A61: 7104 | B61: Payroll Related - Health Insurance | C61: 6145.28 | D61: 1794 | E61: -4351.28 | F61: -2.4254627 | H61: 24986.68 | I61: 10764 | J61: -14222.68 | K61: -1.3213192 | O61: 4722 | S61: 21297.5 | T61: 1492779.8 | U61: 1453480.7 | V61: 52145.29 | W61: 47110 | Y61: 5 | Z61: 301371.65 | AA61: 297526.14 | AD61: -4722 | AE61: -4405.17 | AF61: -3730 | AG61: -675.17 | AH61: -21297.5 | AI61: -52145.29 | AJ61: -20961.81 | AK61: -18650 | AL61: -47110 | AM61: -2311.81 | AN61: -1 | AO61: 1
A62: 7108 | B62: Payroll Related - Other Benefits | C62: 3745.4 | D62: 3730 | E62: -15.4 | F62: -0.0041286863 | H62: 24707.21 | I62: 22380 | J62: -2327.21 | K62: -0.10398615 | O62: 623.09 | S62: 4475.77 | T62: 1492779.8 | U62: 1453480.7 | V62: 8766.54 | W62: 6347 | Y62: 5 | Z62: 301371.65 | AA62: 297526.14 | AD62: -623.09 | AE62: -669.84 | AF62: -481 | AG62: -188.84 | AH62: -4475.77 | AI62: -8766.54 | AJ62: -5178.98 | AK62: -2638 | AL62: -6347 | AM62: -2540.98 | AN62: -1 | AO62: 1
A63: 7112 | B63: Payroll Related - Workers Compensation | C63: 675.64 | D63: 481 | E63: -194.64 | F63: -0.40465696 | H63: 5854.62 | I63: 3119 | J63: -2735.62 | K63: -0.8770824 | O63: 162.24 | S63: 831.85 | T63: 1492779.8 | U63: 1453480.7 | V63: 1992.49 | W63: 2100 | Y63: 5 | Z63: 301371.65 | AA63: 297526.14 | AD63: -162.24 | AE63: -286.69 | AF63: -175 | AG63: -111.69 | AH63: -831.85 | AI63: -1992.49 | AJ63: -1096.83 | AK63: -875 | AL63: -2100 | AM63: -221.83 | AN63: -1 | AO63: 1
A64: 7113 | B64: Payroll Related - Training & Education | C64: 175.03 | D64: 175 | E64: -0.03 | F64: -0.00017142857 | H64: 1271.86 | I64: 1050 | J64: -221.86 | K64: -0.21129524 | O64: 9358.17 | S64: 43814.37 | V64: 132085.06 | W64: 108186.92 | Y64: 5 | AD64: -9358.17 | AE64: -11956.77 | AF64: -8559.49 | AG64: -3397.28 | AH64: -43814.37 | AI64: -132085.06 | AJ64: -61185.71 | AK64: -44035.85 | AL64: -108186.92 | AM64: -17149.86
B65: Payroll Related | C65: 13435.68 | D65: 8559.49 | E65: -4876.19 | F65: -0.56968231 | H65: 74621.39 | I65: 52595.34 | J65: -22026.05 | K65: -0.4187833 | O65: 35529.86 | S65: 180622.9 | V65: 443215.27 | W65: 462680.92 | Y65: 5 | AD65: -35529.86 | AE65: -40282.56 | AF65: -35293.49 | AG65: -4989.07 | AH65: -180622.9 | AI65: -443215.27 | AJ65: -211624.54 | AK65: -190847.85 | AL65: -462680.92 | AM65: -20776.69
B66: Payroll & Related | C66: 42362.05 | D66: 35293.49 | E66: -7068.56 | F66: -0.20027943 | H66: 253986.59 | I66: 226141.34 | J66: -27845.25 | K66: -0.12313206
A67: Contractual Services | O67: 64.95 | S67: 310.6 | T67: 1492779.8 | U67: 1453480.7 | V67: 765.24 | W67: 780 | Y67: 5 | Z67: 301371.65 | AA67: 297526.14 | AD67: -64.95 | AE67: -64.95 | AF67: -65 | AG67: 0.05 | AH67: -310.6 | AI67: -765.24 | AJ67: -324.75 | AK67: -325 | AL67: -780 | AM67: 0.25 | AN67: -1 | AO67: 1
A68: 7247 | B68: Contractual Services - Key Trak System | C68: 64.95 | D68: 65 | E68: 0.05 | F68: 0.00076923077 | H68: 389.7 | I68: 390 | J68: 0.3 | K68: 0.00076923077 | O68: 2300 | S68: 11500 | T68: 1492779.8 | U68: 1453480.7 | V68: 27600 | W68: 27600 | Y68: 5 | Z68: 301371.65 | AA68: 297526.14 | AD68: -2300 | AE68: -2300 | AF68: -2300 | AG68: 0 | AH68: -11500 | AI68: -27600 | AJ68: -11500 | AK68: -11500 | AL68: -27600 | AM68: 0 | AN68: -1 | AO68: 1
A69: 7251 | B69: Contractual Services - Grounds Contract | C69: 2300 | D69: 2300 | E69: 0 | F69: 0 | H69: 13800 | I69: 13800 | J69: 0 | K69: 0 | O69: 309.91 | S69: 557.35 | T69: 1492779.8 | U69: 1453480.7 | V69: 3234.95 | W69: 2736 | Y69: 5 | Z69: 301371.65 | AA69: 297526.14 | AD69: -309.91 | AE69: -837.42 | AF69: -228 | AG69: -609.42 | AH69: -557.35 | AI69: -3234.95 | AJ69: -2136.2 | AK69: -1140 | AL69: -2736 | AM69: -996.2 | AN69: -1 | AO69: 1
A70: 7253 | B70: Contractual Services - Electronic Monitoring | C70: 391.84 | D70: 228 | E70: -163.84 | F70: -0.71859649 | H70: 2528.04 | I70: 1368 | J70: -1160.04 | K70: -0.84798246 | O70: 1218 | S70: 5968.18 | T70: 1492779.8 | U70: 1453480.7 | V70: 15062.18 | W70: 17280 | Y70: 5 | Z70: 301371.65 | AA70: 297526.14 | AD70: -1218 | AE70: -1345 | AF70: -1440 | AG70: 95 | AH70: -5968.18 | AI70: -15062.18 | AJ70: -6979 | AK70: -7200 | AL70: -17280 | AM70: 221 | AN70: -1 | AO70: 1
A71: 7255 | B71: Contractual Services - Patrol Service | C71: 1345 | D71: 1440 | E71: 95 | F71: 0.065972222 | H71: 8324 | I71: 8640 | J71: 316 | K71: 0.036574074 | O71: 0 | S71: 368.24 | T71: 1492779.8 | U71: 1453480.7 | V71: 1554.62 | W71: 1556 | Y71: 5 | Z71: 301371.65 | AA71: 297526.14 | AD71: 0 | AE71: 0 | AF71: -500 | AG71: 500 | AH71: -368.24 | AI71: -1554.62 | AJ71: -784 | AK71: -500 | AL71: -1556 | AM71: -284 | AN71: -1 | AO71: 1
A72: 7256 | B72: Contractual Services - Fire Alarm Monitoring | C72: 556.2 | D72: 556 | E72: -0.2 | F72: -0.00035971223 | H72: 1340.2 | I72: 1056 | J72: -284.2 | K72: -0.26912879 | O72: 3892.86 | S72: 18704.37 | V72: 48216.99 | W72: 49952 | Y72: 5 | AD72: -3892.86 | AE72: -4547.37 | AF72: -4533 | AG72: -14.37 | AH72: -18704.37 | AI72: -48216.99 | AJ72: -21723.95 | AK72: -20665 | AL72: -49952 | AM72: -1058.95
B73: Contractual Services | C73: 4657.99 | D73: 4589 | E73: -68.99 | F73: -0.015033776 | H73: 26381.94 | I73: 25254 | J73: -1127.94 | K73: -0.044663816
A74: Utilities | O74: 1888.15 | S74: 9787.61 | T74: 1492779.8 | U74: 1453480.7 | V74: 26417.81 | W74: 25790 | Y74: 5 | Z74: 301371.65 | AA74: 297526.14 | AD74: -1888.15 | AE74: -2156.84 | AF74: -1945 | AG74: -211.84 | AH74: -9787.61 | AI74: -26417.81 | AJ74: -10860.97 | AK74: -10230 | AL74: -25790 | AM74: -630.97 | AN74: -1 | AO74: 1
A75: 7308 | B75: Utilities - Common Area | C75: 1910.53 | D75: 1945 | E75: 34.47 | F75: 0.017722365 | H75: 12771.5 | I75: 12175 | J75: -596.5 | K75: -0.04899384 | O75: 1391.61 | S75: 8023.55 | T75: 1492779.8 | U75: 1453480.7 | V75: 12961.59 | W75: 9000 | Y75: 5 | Z75: 301371.65 | AA75: 297526.14 | AD75: -1391.61 | AE75: 305.26 | AF75: -750 | AG75: 1055.26 | AH75: -8023.55 | AI75: -12961.59 | AJ75: -2296.38 | AK75: -3750 | AL75: -9000 | AM75: 1453.62 | AN75: -1 | AO75: 1
A76: 7309 | B76: Utilities - Vacants | C76: 209.27 | D76: 750 | E76: 540.73 | F76: 0.72097333 | H76: 2505.65 | I76: 4500 | J76: 1994.35 | K76: 0.44318889 | O76: 214.98 | S76: 2602.81 | T76: 1492779.8 | U76: 1453480.7 | V76: 3889.67 | W76: 4805 | Y76: 5 | Z76: 301371.65 | AA76: 297526.14 | AD76: -214.98 | AE76: -183.5 | AF76: -250 | AG76: 66.5 | AH76: -2602.81 | AI76: -3889.67 | AJ76: -1860.19 | AK76: -3130 | AL76: -4805 | AM76: 1269.81 | AN76: -1 | AO76: 1
A77: 7312 | B77: Utilities - Gas | C77: 160.2 | D77: 165 | E77: 4.8 | F77: 0.029090909 | H77: 2020.39 | I77: 3295 | J77: 1274.61 | K77: 0.38683156 | O77: 14277.32 | S77: 86373.38 | T77: 1492779.8 | U77: 1453480.7 | V77: 220242.03 | W77: 215526 | Y77: 5 | Z77: 301371.65 | AA77: 297526.14 | AD77: -14277.32 | AE77: -20647.28 | AF77: -15000 | AG77: -5647.28 | AH77: -86373.38 | AI77: -220242.03 | AJ77: -85427.14 | AK77: -89475 | AL77: -215526 | AM77: 4047.86 | AN77: -1 | AO77: 1
A78: 7315 | B78: Utilities - Water | C78: 21736.28 | D78: 16405 | E78: -5331.28 | F78: -0.32497897 | H78: 107163.42 | I78: 105880 | J78: -1283.42 | K78: -0.012121458 | O78: 3523.19 | S78: 10628.15 | T78: 1492779.8 | U78: 1453480.7 | V78: 30319.41 | W78: 26500 | Y78: 5 | Z78: 301371.65 | AA78: 297526.14 | AD78: -3523.19 | AE78: -3243.45 | AF78: -2500 | AG78: -743.45 | AH78: -10628.15 | AI78: -30319.41 | AJ78: -15224.79 | AK78: -10500 | AL78: -26500 | AM78: -4724.79 | AN78: -1 | AO78: 1
A79: 7320 | B79: Utilities - Trash Removal | C79: 2858.45 | D79: 2500 | E79: -358.45 | F79: -0.14338 | H79: 18083.24 | I79: 13000 | J79: -5083.24 | K79: -0.39101846 | O79: 2153.09 | S79: 8373.14 | T79: 1492779.8 | U79: 1453480.7 | V79: 27750.98 | W79: 35820 | Y79: 5 | Z79: 301371.65 | AA79: 297526.14 | AD79: -2153.09 | AE79: -2958.6 | AF79: -2985 | AG79: 26.4 | AH79: -8373.14 | AI79: -27750.98 | AJ79: -14793 | AK79: -14925 | AL79: -35820 | AM79: 132 | AN79: -1 | AO79: 1
A80: 7322 | B80: Utilities - Valet Trash Service | C80: 2958.6 | D80: 2985 | E80: 26.4 | F80: 0.0088442211 | H80: 17751.6 | I80: 17910 | J80: 158.4 | K80: 0.0088442211 | O80: 645.75 | S80: 2610.33 | T80: 1492779.8 | U80: 1453480.7 | V80: 12594.33 | W80: 16920 | Y80: 5 | Z80: 301371.65 | AA80: 297526.14 | AD80: -645.75 | AE80: -1425 | AF80: -1410 | AG80: -15 | AH80: -2610.33 | AI80: -12594.33 | AJ80: -7345 | AK80: -7050 | AL80: -16920 | AM80: -295 | AN80: -1 | AO80: 1
A81: 7335 | B81: Utilities - Utility Billing Service | C81: 1430 | D81: 1410 | E81: -20 | F81: -0.014184397 | H81: 8775 | I81: 8460 | J81: -315 | K81: -0.037234043 | O81: 24094.09 | S81: 128398.97 | V81: 334175.82 | W81: 334361 | Y81: 5 | AD81: -24094.09 | AE81: -30309.41 | AF81: -24840 | AG81: -5469.41 | AH81: -128398.97 | AI81: -334175.82 | AJ81: -137807.47 | AK81: -139060 | AL81: -334361 | AM81: 1252.53
B82: Utilities | C82: 31263.33 | D82: 26160 | E82: -5103.33 | F82: -0.19508142 | H82: 169070.8 | I82: 165220 | J82: -3850.8 | K82: -0.023307106
A83: Redecorating | O83: 510.47 | S83: 2936.85 | T83: 1492779.8 | U83: 1453480.7 | V83: 13408.79 | W83: 5940 | Y83: 5 | Z83: 301371.65 | AA83: 297526.14 | AD83: -510.47 | AE83: -265.41 | AF83: -495 | AG83: 229.59 | AH83: -2936.85 | AI83: -13408.79 | AJ83: -3898.69 | AK83: -2475 | AL83: -5940 | AM83: -1423.69 | AN83: -1 | AO83: 1
A84: 7443 | B84: Redecorating - General Cleaning | C84: 134 | D84: 495 | E84: 361 | F84: 0.72929293 | H84: 4032.69 | I84: 2970 | J84: -1062.69 | K84: -0.35780808 | O84: 5559.79 | S84: 18179.84 | T84: 1492779.8 | U84: 1453480.7 | V84: 56066.63 | W84: 45000 | Y84: 5 | Z84: 301371.65 | AA84: 297526.14 | AD84: -5559.79 | AE84: -2737.92 | AF84: -3750 | AG84: 1012.08 | AH84: -18179.84 | AI84: -56066.63 | AJ84: -22608.92 | AK84: -18750 | AL84: -45000 | AM84: -3858.92 | AN84: -1 | AO84: 1
A85: 7444 | B85: Redecorating - Painting | C85: 762.92 | D85: 3750 | E85: 2987.08 | F85: 0.79655467 | H85: 23371.84 | I85: 22500 | J85: -871.84 | K85: -0.038748444 | O85: 1855.75 | S85: 11764.33 | T85: 1492779.8 | U85: 1453480.7 | V85: 21566.17 | W85: 16200 | Y85: 5 | Z85: 301371.65 | AA85: 297526.14 | AD85: -1855.75 | AE85: -1193.35 | AF85: -1500 | AG85: 306.65 | AH85: -11764.33 | AI85: -21566.17 | AJ85: -9609.49 | AK85: -6600 | AL85: -16200 | AM85: -3009.49 | AN85: -1 | AO85: 1
A86: 7450 | B86: Redecorating - Carpet Cleaning Occupied | C86: 1583.39 | D86: 1500 | E86: -83.39 | F86: -0.055593333 | H86: 11192.88 | I86: 8100 | J86: -3092.88 | K86: -0.38183704 | O86: 551 | S86: 6690.59 | T86: 1492779.8 | U86: 1453480.7 | V86: 18853.1 | W86: 14400 | Y86: 5 | Z86: 301371.65 | AA86: 297526.14 | AD86: -551 | AE86: -1474.06 | AF86: -1200 | AG86: -274.06 | AH86: -6690.59 | AI86: -18853.1 | AJ86: -4465.56 | AK86: -6000 | AL86: -14400 | AM86: 1534.44 | AN86: -1 | AO86: 1
A87: 7451 | B87: Redecorating - Carpet Cleaning Vacant | C87: 1208.29 | D87: 1200 | E87: -8.29 | F87: -0.0069083333 | H87: 5673.85 | I87: 7200 | J87: 1526.15 | K87: 0.21196528 | O87: 0 | S87: 0 | T87: 1492779.8 | U87: 1453480.7 | V87: 0 | W87: 1000 | Y87: 5 | Z87: 301371.65 | AA87: 297526.14 | AD87: 0 | AE87: 0 | AF87: 0 | AG87: 0 | AH87: 0 | AI87: 0 | AJ87: 0 | AK87: -500 | AL87: -1000 | AM87: 500 | AN87: -1 | AO87: 1
A88: 7452 | B88: Redecorating - General Cleaning Common | C88: 0 | D88: 0 | E88: 0 | F88: 0 | H88: 0 | I88: 500 | J88: 500 | K88: 1 | O88: 130 | S88: 1110 | T88: 1492779.8 | U88: 1453480.7 | V88: 2260 | W88: 4500 | Y88: 5 | Z88: 301371.65 | AA88: 297526.14 | AD88: -130 | AE88: -1160 | AF88: -500 | AG88: -660 | AH88: -1110 | AI88: -2260 | AJ88: -2290 | AK88: -1750 | AL88: -4500 | AM88: -540 | AN88: -1 | AO88: 1
A89: 7453 | B89: Redecorating - General Cleaning Vacant | C89: 980 | D89: 500 | E89: -480 | F89: -0.96 | G89: Unfavorable variance due to ten vacant contract housekeeping. | H89: 3270 | I89: 2250 | J89: -1020 | K89: -0.45333333 | O89: 400 | S89: 700 | T89: 1492779.8 | U89: 1453480.7 | V89: 8920 | W89: 6000 | Y89: 5 | Z89: 301371.65 | AA89: 297526.14 | AD89: -400 | AE89: -2455 | AF89: -500 | AG89: -1955 | AH89: -700 | AI89: -8920 | AJ89: -5625 | AK89: -2500 | AL89: -6000 | AM89: -3125 | AN89: -1 | AO89: 1
A90: 7454 | B90: Redecorating - Sheetrock | C90: -690 | D90: 500 | E90: 1190 | F90: 2.38 | G90: Unfavorable variance due to eleven contract drywall repairs, more than budgeted for. | H90: 4935 | I90: 3000 | J90: -1935 | K90: -0.645 | O90: 9007.01 | S90: 41381.61 | V90: 121074.69 | W90: 93040 | Y90: 5 | AD90: -9007.01 | AE90: -9285.74 | AF90: -7945 | AG90: -1340.74 | AH90: -41381.61 | AI90: -121074.69 | AJ90: -48497.66 | AK90: -38575 | AL90: -93040 | AM90: -9922.66
B91: Redecorating | C91: 3978.6 | D91: 7945 | E91: 3966.4 | F91: 0.49923222 | H91: 52476.26 | I91: 46520 | J91: -5956.26 | K91: -0.12803654
A92: Maintenance | O92: 0 | S92: 0 | T92: 1492779.8 | U92: 1453480.7 | V92: 0 | W92: 1500 | Y92: 5 | Z92: 301371.65 | AA92: 297526.14 | AD92: 0 | AE92: -850 | AF92: -250 | AG92: -600 | AH92: 0 | AI92: 0 | AJ92: -1502.04 | AK92: -750 | AL92: -1500 | AM92: -752.04 | AN92: -1 | AO92: 1
A93: 7503 | B93: Maintenance - Entry Gate Maintenance | C93: 445 | D93: 0 | E93: -445 | F93: -1 | G93: An unfavorable variance is due to service for gate repairs on two call outs. | H93: 1947.04 | I93: 750 | J93: -1197.04 | K93: -1.5960533 | O93: 7441.55 | S93: 19033.18 | T93: 1492779.8 | U93: 1453480.7 | V93: 33685.5 | W93: 28200 | Y93: 5 | Z93: 301371.65 | AA93: 297526.14 | AD93: -7441.55 | AE93: -1792.76 | AF93: -2350 | AG93: 557.24 | AH93: -19033.18 | AI93: -33685.5 | AJ93: -11061.97 | AK93: -11750 | AL93: -28200 | AM93: 688.03 | AN93: -1 | AO93: 1
A94: 7504 | B94: Maintenance - Plumbing Maintenance | C94: 1559.24 | D94: 2350 | E94: 790.76 | F94: 0.33649362 | H94: 12621.21 | I94: 14100 | J94: 1478.79 | K94: 0.10487872 | O94: 1653.84 | S94: 8827.52 | T94: 1492779.8 | U94: 1453480.7 | V94: 15146.21 | W94: 13200 | Y94: 5 | Z94: 301371.65 | AA94: 297526.14 | AD94: -1653.84 | AE94: -175.85 | AF94: -1100 | AG94: 924.15 | AH94: -8827.52 | AI94: -15146.21 | AJ94: -4088.92 | AK94: -5500 | AL94: -13200 | AM94: 1411.08 | AN94: -1 | AO94: 1
A95: 7508 | B95: Maintenance - Electric Maintenance | C95: 338 | D95: 1100 | E95: 762 | F95: 0.69272727 | H95: 4426.92 | I95: 6600 | J95: 2173.08 | K95: 0.32925455 | O95: 1985.61 | S95: 4798.1 | T95: 1492779.8 | U95: 1453480.7 | V95: 19717.86 | W95: 13250 | Y95: 5 | Z95: 301371.65 | AA95: 297526.14 | AD95: -1985.61 | AE95: -1123.27 | AF95: -1000 | AG95: -123.27 | AH95: -4798.1 | AI95: -19717.86 | AJ95: -4238.06 | AK95: -4250 | AL95: -13250 | AM95: 11.94 | AN95: -1 | AO95: 1
A96: 7512 | B96: Maintenance - Heating & AC Maintenance | C96: 1086.38 | D96: 1500 | E96: 413.62 | F96: 0.27574667 | H96: 5324.44 | I96: 5750 | J96: 425.56 | K96: 0.074010435 | O96: 613.65 | S96: 2669.38 | T96: 1492779.8 | U96: 1453480.7 | V96: 5543.6 | W96: 6000 | Y96: 5 | Z96: 301371.65 | AA96: 297526.14 | AD96: -613.65 | AE96: -328.86 | AF96: -500 | AG96: 171.14 | AH96: -2669.38 | AI96: -5543.6 | AJ96: -2021.47 | AK96: -2500 | AL96: -6000 | AM96: 478.53 | AN96: -1 | AO96: 1
A97: 7516 | B97: Maintenance - Appliance Maintenance | C97: 606.88 | D97: 500 | E97: -106.88 | F97: -0.21376 | H97: 2628.35 | I97: 3000 | J97: 371.65 | K97: 0.12388333 | O97: 5720.85 | S97: 21573.87 | T97: 1492779.8 | U97: 1453480.7 | V97: 54236.12 | W97: 36000 | Y97: 5 | Z97: 301371.65 | AA97: 297526.14 | AD97: -5720.85 | AE97: -3900.11 | AF97: -3000 | AG97: -900.11 | AH97: -21573.87 | AI97: -54236.12 | AJ97: -20000.37 | AK97: -15000 | AL97: -36000 | AM97: -5000.37 | AN97: -1 | AO97: 1
A98: 7535 | B98: Maintenance - Maintenance & Repairs | C98: 2882.43 | D98: 3000 | E98: 117.57 | F98: 0.03919 | H98: 22882.8 | I98: 18000 | J98: -4882.8 | K98: -0.27126667 | O98: 891 | S98: 4218.17 | T98: 1492779.8 | U98: 1453480.7 | V98: 10489.98 | W98: 8400 | Y98: 5 | Z98: 301371.65 | AA98: 297526.14 | AD98: -891 | AE98: -800 | AF98: -700 | AG98: -100 | AH98: -4218.17 | AI98: -10489.98 | AJ98: -5119.18 | AK98: -3500 | AL98: -8400 | AM98: -1619.18 | AN98: -1 | AO98: 1
A99: 7536 | B99: Maintenance - Pest Control | C99: 1171.96 | D99: 700 | E99: -471.96 | F99: -0.67422857 | G99: An unfavorable variance is due to bed bug treatment for apartment #244 that was charged back to tenant. | H99: 6291.14 | I99: 4200 | J99: -2091.14 | K99: -0.49789048 | O99: 0 | S99: 209.52 | T99: 1492779.8 | U99: 1453480.7 | V99: 1135.52 | W99: 2400 | Y99: 5 | Z99: 301371.65 | AA99: 297526.14 | AD99: 0 | AE99: 0 | AF99: -200 | AG99: 200 | AH99: -209.52 | AI99: -1135.52 | AJ99: 0 | AK99: -1000 | AL99: -2400 | AM99: 1000 | AN99: -1 | AO99: 1
A100: 7537 | B100: Maintenance - Landscape Supplies | C100: 104.2 | D100: 200 | E100: 95.8 | F100: 0.479 | H100: 104.2 | I100: 1200 | J100: 1095.8 | K100: 0.91316667 | O100: 486.64 | S100: 1674.07 | T100: 1492779.8 | U100: 1453480.7 | V100: 3325.51 | W100: 2620 | Y100: 5 | Z100: 301371.65 | AA100: 297526.14 | AD100: -486.64 | AE100: -257.63 | AF100: -435 | AG100: 177.37 | AH100: -1674.07 | AI100: -3325.51 | AJ100: -616.76 | AK100: -875 | AL100: -2620 | AM100: 258.24 | AN100: -1 | AO100: 1
A101: 7539 | B101: Maintenance - Pool Maintenance | C101: 154.11 | D101: 435 | E101: 280.89 | F101: 0.64572414 | H101: 770.87 | I101: 1310 | J101: 539.13 | K101: 0.41154962 | O101: 0 | S101: 515.68 | T101: 1492779.8 | U101: 1453480.7 | V101: 1068.39 | W101: 1200 | Y101: 5 | Z101: 301371.65 | AA101: 297526.14 | AD101: 0 | AE101: -23.88 | AF101: 0 | AG101: -23.88 | AH101: -515.68 | AI101: -1068.39 | AJ101: -452.79 | AK101: -600 | AL101: -1200 | AM101: 147.21 | AN101: -1 | AO101: 1
A102: 7542 | B102: Maintenance - Uniforms | C102: 0 | D102: 0 | E102: 0 | F102: 0 | H102: 452.79 | I102: 600 | J102: 147.21 | K102: 0.24535 | O102: 18793.14 | S102: 63519.49 | V102: 144348.69 | W102: 112770 | Y102: 5 | AD102: -18793.14 | AE102: -9252.36 | AF102: -9535 | AG102: 282.64 | AH102: -63519.49 | AI102: -144348.69 | AJ102: -49101.56 | AK102: -45725 | AL102: -112770 | AM102: -3376.56
...

Sheet Teagen - CRES
A1: 2024 Actuals | B1: ='Teagen - Input'!C7 -> Jan 2024 | C1: ='Teagen - Input'!D7 -> Feb 2024 | D1: ='Teagen - Input'!E7 -> Mar 2024 | E1: ='Teagen - Input'!F7 -> Apr 2024 | F1: ='Teagen - Input'!G7 -> May 2024 | G1: ='Teagen - Input'!H7 -> Jun 2024 | H1: ='Teagen - Input'!I7 -> Jul 2024 | I1: ='Teagen - Input'!J7 -> Aug 2024 | ... M1: ='Teagen - Input'!N7 -> Dec 2024 | N1: YTD | P1: 1000
A2: Property Asking Rent | B2: =SUMIFS('Teagen - Input'!C:C,'Teagen - Input'!$AH:$AH,'Teagen - CRES'!$A2)/$P$1 -> 275.63379 | C2: =SUMIFS('Teagen - Input'!D:D,'Teagen - Input'!$AH:$AH,'Teagen - CRES'!$A2)/$P$1 -> 275.67173 | D2: =SUMIFS('Teagen - Input'!E:E,'Teagen - Input'!$AH:$AH,'Teagen - CRES'!$A2)/$P$1 -> 279.63521 | E2: =SUMIFS('Teagen - Input'!F:F,'Teagen - Input'!$AH:$AH,'Teagen - CRES'!$A2)/$P$1 -> 278.83564 | F2: =SUMIFS('Teagen - Input'!G:G,'Teagen - Input'!$AH:$AH,'Teagen - CRES'!$A2)/$P$1 -> 275.54436 | G2: =SUMIFS('Teagen - Input'!H:H,'Teagen - Input'!$AH:$AH,'Teagen - CRES'!$A2)/$P$1 -> 275.95953 | H2: =SUMIFS('Teagen - Input'!I:I,'Teagen - Input'!$AH:$AH,'Teagen - CRES'!$A2)/$P$1 -> 276.40572 | I2: =SUMIFS('Teagen - Input'!J:J,'Teagen - Input'!$AH:$AH,'Teagen - CRES'!$A2)/$P$1 -> 274.40638 | J2: =SUMIFS('Teagen - Input'!K:K,'Teagen - Input'!$AH:$AH,'Teagen - CRES'!$A2)/$P$1 -> 274.77606 | K2: =SUMIFS('Teagen - Input'!L:L,'Teagen - Input'!$AH:$AH,'Teagen - CRES'!$A2)/$P$1 -> 275.16013 | L2: =SUMIFS('Teagen - Input'!M:M,'Teagen - Input'!$AH:$AH,'Teagen - CRES'!$A2)/$P$1 -> 267.20342 | M2: =SUMIFS('Teagen - Input'!N:N,'Teagen - Input'!$AH:$AH,'Teagen - CRES'!$A2)/$P$1 -> 268.85527 | N2: =SUM(B2:M2) -> 3298.0872
A3: Loss to lease | B3: =SUMIFS('Teagen - Input'!C:C,'Teagen - Input'!$AH:$AH,'Teagen - CRES'!$A3)/$P$1 -> -20.70322 | C3: =SUMIFS('Teagen - Input'!D:D,'Teagen - Input'!$AH:$AH,'Teagen - CRES'!$A3)/$P$1 -> -18.6667 | D3: =SUMIFS('Teagen - Input'!E:E,'Teagen - Input'!$AH:$AH,'Teagen - CRES'!$A3)/$P$1 -> -21.24726 | E3: =SUMIFS('Teagen - Input'!F:F,'Teagen - Input'!$AH:$AH,'Teagen - CRES'!$A3)/$P$1 -> -18.60865 | F3: =SUMIFS('Teagen - Input'!G:G,'Teagen - Input'!$AH:$AH,'Teagen - CRES'!$A3)/$P$1 -> -16.89225 | G3: =SUMIFS('Teagen - Input'!H:H,'Teagen - Input'!$AH:$AH,'Teagen - CRES'!$A3)/$P$1 -> -17.79909 | H3: =SUMIFS('Teagen - Input'!I:I,'Teagen - Input'!$AH:$AH,'Teagen - CRES'!$A3)/$P$1 -> -18.06564 | I3: =SUMIFS('Teagen - Input'!J:J,'Teagen - Input'!$AH:$AH,'Teagen - CRES'!$A3)/$P$1 -> -16.17815 | J3: =SUMIFS('Teagen - Input'!K:K,'Teagen - Input'!$AH:$AH,'Teagen - CRES'!$A3)/$P$1 -> -14.46973 | K3: =SUMIFS('Teagen - Input'!L:L,'Teagen - Input'!$AH:$AH,'Teagen - CRES'!$A3)/$P$1 -> -15.89083 | L3: =SUMIFS('Teagen - Input'!M:M,'Teagen - Input'!$AH:$AH,'Teagen - CRES'!$A3)/$P$1 -> -8.27196 | M3: =SUMIFS('Teagen - Input'!N:N,'Teagen - Input'!$AH:$AH,'Teagen - CRES'!$A3)/$P$1 -> -9.5042 | N3: =SUM(B3:M3) -> -196.29768
A4: Gross Scheduled Rent | B4: =SUM(B2:B3) -> 254.93057 | C4: =SUM(C2:C3) -> 257.00503 | D4: =SUM(D2:D3) -> 258.38795 | E4: =SUM(E2:E3) -> 260.22699 | F4: =SUM(F2:F3) -> 258.65211 | G4: =SUM(G2:G3) -> 258.16044 | H4: =SUM(H2:H3) -> 258.34008 | I4: =SUM(I2:I3) -> 258.22823 | ... M4: =SUM(M2:M3) -> 259.35107 | N4: =SUM(B4:M4) -> 3101.7896
A5: Vacancy | B5: =SUMIFS('Teagen - Input'!C:C,'Teagen - Input'!$AH:$AH,'Teagen - CRES'!$A5)/$P$1 -> -16.2588 | C5: =SUMIFS('Teagen - Input'!D:D,'Teagen - Input'!$AH:$AH,'Teagen - CRES'!$A5)/$P$1 -> -15.47974 | D5: =SUMIFS('Teagen - Input'!E:E,'Teagen - Input'!$AH:$AH,'Teagen - CRES'!$A5)/$P$1 -> -15.97275 | E5: =SUMIFS('Teagen - Input'!F:F,'Teagen - Input'!$AH:$AH,'Teagen - CRES'!$A5)/$P$1 -> -22.85402 | F5: =SUMIFS('Teagen - Input'!G:G,'Teagen - Input'!$AH:$AH,'Teagen - CRES'!$A5)/$P$1 -> -21.02649 | G5: =SUMIFS('Teagen - Input'!H:H,'Teagen - Input'!$AH:$AH,'Teagen - CRES'!$A5)/$P$1 -> -21.36733 | H5: =SUMIFS('Teagen - Input'!I:I,'Teagen - Input'!$AH:$AH,'Teagen - CRES'!$A5)/$P$1 -> -15.56818 | I5: =SUMIFS('Teagen - Input'!J:J,'Teagen - Input'!$AH:$AH,'Teagen - CRES'!$A5)/$P$1 -> -18.87951 | J5: =SUMIFS('Teagen - Input'!K:K,'Teagen - Input'!$AH:$AH,'Teagen - CRES'!$A5)/$P$1 -> -22.09178 | K5: =SUMIFS('Teagen - Input'!L:L,'Teagen - Input'!$AH:$AH,'Teagen - CRES'!$A5)/$P$1 -> -19.60859 | L5: =SUMIFS('Teagen - Input'!M:M,'Teagen - Input'!$AH:$AH,'Teagen - CRES'!$A5)/$P$1 -> -14.27323 | M5: =SUMIFS('Teagen - Input'!N:N,'Teagen - Input'!$AH:$AH,'Teagen - CRES'!$A5)/$P$1 -> -15.85623 | N5: =SUM(B5:M5) -> -219.23665
A6: Non Revenue Units | B6: =SUMIFS('Teagen - Input'!C:C,'Teagen - Input'!$AH:$AH,'Teagen - CRES'!$A6)/$P$1 -> -1.065 | C6: =SUMIFS('Teagen - Input'!D:D,'Teagen - Input'!$AH:$AH,'Teagen - CRES'!$A6)/$P$1 -> -1.065 | D6: =SUMIFS('Teagen - Input'!E:E,'Teagen - Input'!$AH:$AH,'Teagen - CRES'!$A6)/$P$1 -> -1.065 | E6: =SUMIFS('Teagen - Input'!F:F,'Teagen - Input'!$AH:$AH,'Teagen - CRES'!$A6)/$P$1 -> -1.065 | F6: =SUMIFS('Teagen - Input'!G:G,'Teagen - Input'!$AH:$AH,'Teagen - CRES'!$A6)/$P$1 -> -1.065 | G6: =SUMIFS('Teagen - Input'!H:H,'Teagen - Input'!$AH:$AH,'Teagen - CRES'!$A6)/$P$1 -> -1.065 | H6: =SUMIFS('Teagen - Input'!I:I,'Teagen - Input'!$AH:$AH,'Teagen - CRES'!$A6)/$P$1 -> -1.065 | I6: =SUMIFS('Teagen - Input'!J:J,'Teagen - Input'!$AH:$AH,'Teagen - CRES'!$A6)/$P$1 -> -1.065 | J6: =SUMIFS('Teagen - Input'!K:K,'Teagen - Input'!$AH:$AH,'Teagen - CRES'!$A6)/$P$1 -> -1.065 | K6: =SUMIFS('Teagen - Input'!L:L,'Teagen - Input'!$AH:$AH,'Teagen - CRES'!$A6)/$P$1 -> -0.839 | L6: =SUMIFS('Teagen - Input'!M:M,'Teagen - Input'!$AH:$AH,'Teagen - CRES'!$A6)/$P$1 -> -0.839 | M6: =SUMIFS('Teagen - Input'!N:N,'Teagen - Input'!$AH:$AH,'Teagen - CRES'!$A6)/$P$1 -> -0.839 | N6: =SUM(B6:M6) -> -12.102
A7: Concessions | B7: =SUMIFS('Teagen - Input'!C:C,'Teagen - Input'!$AH:$AH,'Teagen - CRES'!$A7)/$P$1 -> -2.938 | C7: =SUMIFS('Teagen - Input'!D:D,'Teagen - Input'!$AH:$AH,'Teagen - CRES'!$A7)/$P$1 -> -1.67588 | D7: =SUMIFS('Teagen - Input'!E:E,'Teagen - Input'!$AH:$AH,'Teagen - CRES'!$A7)/$P$1 -> -2.87447 | E7: =SUMIFS('Teagen - Input'!F:F,'Teagen - Input'!$AH:$AH,'Teagen - CRES'!$A7)/$P$1 -> -7.75925 | F7: =SUMIFS('Teagen - Input'!G:G,'Teagen - Input'!$AH:$AH,'Teagen - CRES'!$A7)/$P$1 -> -3.02495 | G7: =SUMIFS('Teagen - Input'!H:H,'Teagen - Input'!$AH:$AH,'Teagen - CRES'!$A7)/$P$1 -> -9.48611 | H7: =SUMIFS('Teagen - Input'!I:I,'Teagen - Input'!$AH:$AH,'Teagen - CRES'!$A7)/$P$1 -> -9.02806 | I7: =SUMIFS('Teagen - Input'!J:J,'Teagen - Input'!$AH:$AH,'Teagen - CRES'!$A7)/$P$1 -> -11.80663 | J7: =SUMIFS('Teagen - Input'!K:K,'Teagen - Input'!$AH:$AH,'Teagen - CRES'!$A7)/$P$1 -> -12.83882 | K7: =SUMIFS('Teagen - Input'!L:L,'Teagen - Input'!$AH:$AH,'Teagen - CRES'!$A7)/$P$1 -> -6.39775 | L7: =SUMIFS('Teagen - Input'!M:M,'Teagen - Input'!$AH:$AH,'Teagen - CRES'!$A7)/$P$1 -> -10.6705 | M7: =SUMIFS('Teagen - Input'!N:N,'Teagen - Input'!$AH:$AH,'Teagen - CRES'!$A7)/$P$1 -> -5.6356 | N7: =SUM(B7:M7) -> -84.13602
A8: Delinquency | B8: =SUMIFS('Teagen - Input'!C:C,'Teagen - Input'!$AH:$AH,'Teagen - CRES'!$A8)/$P$1 -> -4.07438 | C8: =SUMIFS('Teagen - Input'!D:D,'Teagen - Input'!$AH:$AH,'Teagen - CRES'!$A8)/$P$1 -> -9.0226 | D8: =SUMIFS('Teagen - Input'!E:E,'Teagen - Input'!$AH:$AH,'Teagen - CRES'!$A8)/$P$1 -> -3.28008 | E8: =SUMIFS('Teagen - Input'!F:F,'Teagen - Input'!$AH:$AH,'Teagen - CRES'!$A8)/$P$1 -> -3.16113 | F8: =SUMIFS('Teagen - Input'!G:G,'Teagen - Input'!$AH:$AH,'Teagen - CRES'!$A8)/$P$1 -> -11.39538 | G8: =SUMIFS('Teagen - Input'!H:H,'Teagen - Input'!$AH:$AH,'Teagen - CRES'!$A8)/$P$1 -> -11.43588 | H8: =SUMIFS('Teagen - Input'!I:I,'Teagen - Input'!$AH:$AH,'Teagen - CRES'!$A8)/$P$1 -> -8.34867 | I8: =SUMIFS('Teagen - Input'!J:J,'Teagen - Input'!$AH:$AH,'Teagen - CRES'!$A8)/$P$1 -> -15.9644 | J8: =SUMIFS('Teagen - Input'!K:K,'Teagen - Input'!$AH:$AH,'Teagen - CRES'!$A8)/$P$1 -> -11.21149 | K8: =SUMIFS('Teagen - Input'!L:L,'Teagen - Input'!$AH:$AH,'Teagen - CRES'!$A8)/$P$1 -> -8.52261 | L8: =SUMIFS('Teagen - Input'!M:M,'Teagen - Input'!$AH:$AH,'Teagen - CRES'!$A8)/$P$1 -> -11.14594 | M8: =SUMIFS('Teagen - Input'!N:N,'Teagen - Input'!$AH:$AH,'Teagen - CRES'!$A8)/$P$1 -> -5.96215 | N8: =SUM(B8:M8) -> -103.52471
A9: Parking Garage Income | B9: =SUMIFS('Teagen - Input'!C:C,'Teagen - Input'!$AH:$AH,'Teagen - CRES'!$A9)/$P$1 -> 0 | C9: =SUMIFS('Teagen - Input'!D:D,'Teagen - Input'!$AH:$AH,'Teagen - CRES'!$A9)/$P$1 -> 0 | D9: =SUMIFS('Teagen - Input'!E:E,'Teagen - Input'!$AH:$AH,'Teagen - CRES'!$A9)/$P$1 -> 0 | E9: =SUMIFS('Teagen - Input'!F:F,'Teagen - Input'!$AH:$AH,'Teagen - CRES'!$A9)/$P$1 -> 0 | F9: =SUMIFS('Teagen - Input'!G:G,'Teagen - Input'!$AH:$AH,'Teagen - CRES'!$A9)/$P$1 -> 0 | G9: =SUMIFS('Teagen - Input'!H:H,'Teagen - Input'!$AH:$AH,'Teagen - CRES'!$A9)/$P$1 -> 0 | H9: =SUMIFS('Teagen - Input'!I:I,'Teagen - Input'!$AH:$AH,'Teagen - CRES'!$A9)/$P$1 -> 0 | I9: =SUMIFS('Teagen - Input'!J:J,'Teagen - Input'!$AH:$AH,'Teagen - CRES'!$A9)/$P$1 -> 0 | J9: =SUMIFS('Teagen - Input'!K:K,'Teagen - Input'!$AH:$AH,'Teagen - CRES'!$A9)/$P$1 -> 0 | K9: =SUMIFS('Teagen - Input'!L:L,'Teagen - Input'!$AH:$AH,'Teagen - CRES'!$A9)/$P$1 -> 0 | L9: =SUMIFS('Teagen - Input'!M:M,'Teagen - Input'!$AH:$AH,'Teagen - CRES'!$A9)/$P$1 -> 0 | M9: =SUMIFS('Teagen - Input'!N:N,'Teagen - Input'!$AH:$AH,'Teagen - CRES'!$A9)/$P$1 -> 0 | N9: =SUM(B9:M9) -> 0
A10: Utility Income | B10: =SUMIFS('Teagen - Input'!C:C,'Teagen - Input'!$AH:$AH,'Teagen - CRES'!$A10)/$P$1 -> 0 | C10: =SUMIFS('Teagen - Input'!D:D,'Teagen - Input'!$AH:$AH,'Teagen - CRES'!$A10)/$P$1 -> 0 | D10: =SUMIFS('Teagen - Input'!E:E,'Teagen - Input'!$AH:$AH,'Teagen - CRES'!$A10)/$P$1 -> 0 | E10: =SUMIFS('Teagen - Input'!F:F,'Teagen - Input'!$AH:$AH,'Teagen - CRES'!$A10)/$P$1 -> 0 | F10: =SUMIFS('Teagen - Input'!G:G,'Teagen - Input'!$AH:$AH,'Teagen - CRES'!$A10)/$P$1 -> 0 | G10: =SUMIFS('Teagen - Input'!H:H,'Teagen - Input'!$AH:$AH,'Teagen - CRES'!$A10)/$P$1 -> 0 | H10: =SUMIFS('Teagen - Input'!I:I,'Teagen - Input'!$AH:$AH,'Teagen - CRES'!$A10)/$P$1 -> 0 | I10: =SUMIFS('Teagen - Input'!J:J,'Teagen - Input'!$AH:$AH,'Teagen - CRES'!$A10)/$P$1 -> 0 | J10: =SUMIFS('Teagen - Input'!K:K,'Teagen - Input'!$AH:$AH,'Teagen - CRES'!$A10)/$P$1 -> 0 | K10: =SUMIFS('Teagen - Input'!L:L,'Teagen - Input'!$AH:$AH,'Teagen - CRES'!$A10)/$P$1 -> 0 | L10: =SUMIFS('Teagen - Input'!M:M,'Teagen - Input'!$AH:$AH,'Teagen - CRES'!$A10)/$P$1 -> 0 | M10: =SUMIFS('Teagen - Input'!N:N,'Teagen - Input'!$AH:$AH,'Teagen - CRES'!$A10)/$P$1 -> 0 | N10: =SUM(B10:M10) -> 0
A11: Other | B11: =SUMIFS('Teagen - Input'!C:C,'Teagen - Input'!$AH:$AH,'Teagen - CRES'!$A11)/$P$1 -> 69.04414 | C11: =SUMIFS('Teagen - Input'!D:D,'Teagen - Input'!$AH:$AH,'Teagen - CRES'!$A11)/$P$1 -> 67.94967 | D11: =SUMIFS('Teagen - Input'!E:E,'Teagen - Input'!$AH:$AH,'Teagen - CRES'!$A11)/$P$1 -> 66.5896 | E11: =SUMIFS('Teagen - Input'!F:F,'Teagen - Input'!$AH:$AH,'Teagen - CRES'!$A11)/$P$1 -> 66.88528 | F11: =SUMIFS('Teagen - Input'!G:G,'Teagen - Input'!$AH:$AH,'Teagen - CRES'!$A11)/$P$1 -> 79.23136 | G11: =SUMIFS('Teagen - Input'!H:H,'Teagen - Input'!$AH:$AH,'Teagen - CRES'!$A11)/$P$1 -> 75.75348 | H11: =SUMIFS('Teagen - Input'!I:I,'Teagen - Input'!$AH:$AH,'Teagen - CRES'!$A11)/$P$1 -> 88.06988 | I11: =SUMIFS('Teagen - Input'!J:J,'Teagen - Input'!$AH:$AH,'Teagen - CRES'!$A11)/$P$1 -> 73.52152 | J11: =SUMIFS('Teagen - Input'!K:K,'Teagen - Input'!$AH:$AH,'Teagen - CRES'!$A11)/$P$1 -> 93.18999 | K11: =SUMIFS('Teagen - Input'!L:L,'Teagen - Input'!$AH:$AH,'Teagen - CRES'!$A11)/$P$1 -> 82.69684 | L11: =SUMIFS('Teagen - Input'!M:M,'Teagen - Input'!$AH:$AH,'Teagen - CRES'!$A11)/$P$1 -> 75.99618 | M11: =SUMIFS('Teagen - Input'!N:N,'Teagen - Input'!$AH:$AH,'Teagen - CRES'!$A11)/$P$1 -> 96.54491 | N11: =SUM(B11:M11) -> 935.47285
A12: Effective Rental Income | B12: =SUM(B4:B11) -> 299.63853 | C12: =SUM(C4:C11) -> 297.71148 | D12: =SUM(D4:D11) -> 301.78525 | E12: =SUM(E4:E11) -> 292.27287 | F12: =SUM(F4:F11) -> 301.37165 | G12: =SUM(G4:G11) -> 290.5596 | H12: =SUM(H4:H11) -> 312.40005 | I12: =SUM(I4:I11) -> 284.03421 | ... M12: =SUM(M4:M11) -> 327.603 | N12: =SUM(B12:M12) -> 3618.263
A13: Other Income / Loss | N13: =SUM(B13:M13) -> 0
A14: Net Eff. Gross Income | B14: =SUM(B12:B13) -> 299.63853 | C14: =SUM(C12:C13) -> 297.71148 | D14: =SUM(D12:D13) -> 301.78525 | E14: =SUM(E12:E13) -> 292.27287 | F14: =SUM(F12:F13) -> 301.37165 | G14: =SUM(G12:G13) -> 290.5596 | H14: =SUM(H12:H13) -> 312.40005 | I14: =SUM(I12:I13) -> 284.03421 | ... M14: =SUM(M12:M13) -> 327.603 | N14: =SUM(B14:M14) -> 3618.263 | P14: =M14*1000 -> 327603
B16: =B1 -> Jan 2024 | C16: =C1 -> Feb 2024 | D16: =D1 -> Mar 2024 | E16: =E1 -> Apr 2024 | F16: =F1 -> May 2024 | G16: =G1 -> Jun 2024 | H16: =H1 -> Jul 2024 | I16: =I1 -> Aug 2024 | ... M16: =M1 -> Dec 2024 | N16: YTD | P16: =-1000 -> -1000
A17: General & Admin. | B17: =SUMIFS('Teagen - Input'!C:C,'Teagen - Input'!$AH:$AH,'Teagen - CRES'!$A17)/$P$16 -> -9.96468 | C17: =SUMIFS('Teagen - Input'!D:D,'Teagen - Input'!$AH:$AH,'Teagen - CRES'!$A17)/$P$16 -> -10.41391 | D17: =SUMIFS('Teagen - Input'!E:E,'Teagen - Input'!$AH:$AH,'Teagen - CRES'!$A17)/$P$16 -> -13.52323 | E17: =SUMIFS('Teagen - Input'!F:F,'Teagen - Input'!$AH:$AH,'Teagen - CRES'!$A17)/$P$16 -> -12.01446 | F17: =SUMIFS('Teagen - Input'!G:G,'Teagen - Input'!$AH:$AH,'Teagen - CRES'!$A17)/$P$16 -> -12.78404 | G17: =SUMIFS('Teagen - Input'!H:H,'Teagen - Input'!$AH:$AH,'Teagen - CRES'!$A17)/$P$16 -> -12.79431 | H17: =SUMIFS('Teagen - Input'!I:I,'Teagen - Input'!$AH:$AH,'Teagen - CRES'!$A17)/$P$16 -> -13.41284 | I17: =SUMIFS('Teagen - Input'!J:J,'Teagen - Input'!$AH:$AH,'Teagen - CRES'!$A17)/$P$16 -> -12.67755 | J17: =SUMIFS('Teagen - Input'!K:K,'Teagen - Input'!$AH:$AH,'Teagen - CRES'!$A17)/$P$16 -> -12.76643 | K17: =SUMIFS('Teagen - Input'!L:L,'Teagen - Input'!$AH:$AH,'Teagen - CRES'!$A17)/$P$16 -> -19.16404 | L17: =SUMIFS('Teagen - Input'!M:M,'Teagen - Input'!$AH:$AH,'Teagen - CRES'!$A17)/$P$16 -> -21.20195 | M17: =SUMIFS('Teagen - Input'!N:N,'Teagen - Input'!$AH:$AH,'Teagen - CRES'!$A17)/$P$16 -> -16.74149 | N17: =SUM(B17:M17) -> -167.45893
A18: Management Fee | B18: =SUMIFS('Teagen - Input'!C:C,'Teagen - Input'!$AH:$AH,'Teagen - CRES'!$A18)/$P$16 -> -8.98916 | C18: =SUMIFS('Teagen - Input'!D:D,'Teagen - Input'!$AH:$AH,'Teagen - CRES'!$A18)/$P$16 -> -8.93134 | D18: =SUMIFS('Teagen - Input'!E:E,'Teagen - Input'!$AH:$AH,'Teagen - CRES'!$A18)/$P$16 -> -9.05356 | E18: =SUMIFS('Teagen - Input'!F:F,'Teagen - Input'!$AH:$AH,'Teagen - CRES'!$A18)/$P$16 -> -8.76819 | F18: =SUMIFS('Teagen - Input'!G:G,'Teagen - Input'!$AH:$AH,'Teagen - CRES'!$A18)/$P$16 -> -9.04115 | G18: =SUMIFS('Teagen - Input'!H:H,'Teagen - Input'!$AH:$AH,'Teagen - CRES'!$A18)/$P$16 -> -8.71679 | H18: =SUMIFS('Teagen - Input'!I:I,'Teagen - Input'!$AH:$AH,'Teagen - CRES'!$A18)/$P$16 -> -9.372 | I18: =SUMIFS('Teagen - Input'!J:J,'Teagen - Input'!$AH:$AH,'Teagen - CRES'!$A18)/$P$16 -> -8.52103 | J18: =SUMIFS('Teagen - Input'!K:K,'Teagen - Input'!$AH:$AH,'Teagen - CRES'!$A18)/$P$16 -> -9.18868 | K18: =SUMIFS('Teagen - Input'!L:L,'Teagen - Input'!$AH:$AH,'Teagen - CRES'!$A18)/$P$16 -> -9.19795 | L18: =SUMIFS('Teagen - Input'!M:M,'Teagen - Input'!$AH:$AH,'Teagen - CRES'!$A18)/$P$16 -> -8.93997 | M18: =SUMIFS('Teagen - Input'!N:N,'Teagen - Input'!$AH:$AH,'Teagen - CRES'!$A18)/$P$16 -> -9.82809 | N18: =SUM(B18:M18) -> -108.54791
A19: Payroll | B19: =SUMIFS('Teagen - Input'!C:C,'Teagen - Input'!$AH:$AH,'Teagen - CRES'!$A19)/$P$16 -> -39.19178 | C19: =SUMIFS('Teagen - Input'!D:D,'Teagen - Input'!$AH:$AH,'Teagen - CRES'!$A19)/$P$16 -> -42.62675 | D19: =SUMIFS('Teagen - Input'!E:E,'Teagen - Input'!$AH:$AH,'Teagen - CRES'!$A19)/$P$16 -> -50.82453 | E19: =SUMIFS('Teagen - Input'!F:F,'Teagen - Input'!$AH:$AH,'Teagen - CRES'!$A19)/$P$16 -> -38.69892 | F19: =SUMIFS('Teagen - Input'!G:G,'Teagen - Input'!$AH:$AH,'Teagen - CRES'!$A19)/$P$16 -> -40.28256 | G19: =SUMIFS('Teagen - Input'!H:H,'Teagen - Input'!$AH:$AH,'Teagen - CRES'!$A19)/$P$16 -> -42.36205 | H19: =SUMIFS('Teagen - Input'!I:I,'Teagen - Input'!$AH:$AH,'Teagen - CRES'!$A19)/$P$16 -> -40.32682 | I19: =SUMIFS('Teagen - Input'!J:J,'Teagen - Input'!$AH:$AH,'Teagen - CRES'!$A19)/$P$16 -> -57.23505 | J19: =SUMIFS('Teagen - Input'!K:K,'Teagen - Input'!$AH:$AH,'Teagen - CRES'!$A19)/$P$16 -> -40.45247 | K19: =SUMIFS('Teagen - Input'!L:L,'Teagen - Input'!$AH:$AH,'Teagen - CRES'!$A19)/$P$16 -> -43.14146 | L19: =SUMIFS('Teagen - Input'!M:M,'Teagen - Input'!$AH:$AH,'Teagen - CRES'!$A19)/$P$16 -> -47.38759 | M19: =SUMIFS('Teagen - Input'!N:N,'Teagen - Input'!$AH:$AH,'Teagen - CRES'!$A19)/$P$16 -> -40.71223 | N19: =SUM(B19:M19) -> -523.24221
A20: Insurance | B20: =SUMIFS('Teagen - Input'!C:C,'Teagen - Input'!$AH:$AH,'Teagen - CRES'!$A20)/$P$16 -> -21.078 | C20: =SUMIFS('Teagen - Input'!D:D,'Teagen - Input'!$AH:$AH,'Teagen - CRES'!$A20)/$P$16 -> -21.078 | D20: =SUMIFS('Teagen - Input'!E:E,'Teagen - Input'!$AH:$AH,'Teagen - CRES'!$A20)/$P$16 -> -21.078 | E20: =SUMIFS('Teagen - Input'!F:F,'Teagen - Input'!$AH:$AH,'Teagen - CRES'!$A20)/$P$16 -> -21.078 | F20: =SUMIFS('Teagen - Input'!G:G,'Teagen - Input'!$AH:$AH,'Teagen - CRES'!$A20)/$P$16 -> -21.078 | G20: =SUMIFS('Teagen - Input'!H:H,'Teagen - Input'!$AH:$AH,'Teagen - CRES'!$A20)/$P$16 -> -21.078 | H20: =SUMIFS('Teagen - Input'!I:I,'Teagen - Input'!$AH:$AH,'Teagen - CRES'!$A20)/$P$16 -> -21.078 | I20: =SUMIFS('Teagen - Input'!J:J,'Teagen - Input'!$AH:$AH,'Teagen - CRES'!$A20)/$P$16 -> -21.078 | J20: =SUMIFS('Teagen - Input'!K:K,'Teagen - Input'!$AH:$AH,'Teagen - CRES'!$A20)/$P$16 -> -21.078 | K20: =SUMIFS('Teagen - Input'!L:L,'Teagen - Input'!$AH:$AH,'Teagen - CRES'!$A20)/$P$16 -> -21.078 | L20: =SUMIFS('Teagen - Input'!M:M,'Teagen - Input'!$AH:$AH,'Teagen - CRES'!$A20)/$P$16 -> -21.078 | M20: =SUMIFS('Teagen - Input'!N:N,'Teagen - Input'!$AH:$AH,'Teagen - CRES'!$A20)/$P$16 -> -21.078 | N20: =SUM(B20:M20) -> -252.936
A21: Property Taxes | B21: =SUMIFS('Teagen - Input'!C:C,'Teagen - Input'!$AH:$AH,'Teagen - CRES'!$A21)/$P$16 -> -28.259 | C21: =SUMIFS('Teagen - Input'!D:D,'Teagen - Input'!$AH:$AH,'Teagen - CRES'!$A21)/$P$16 -> -28.259 | D21: =SUMIFS('Teagen - Input'!E:E,'Teagen - Input'!$AH:$AH,'Teagen - CRES'!$A21)/$P$16 -> -28.259 | E21: =SUMIFS('Teagen - Input'!F:F,'Teagen - Input'!$AH:$AH,'Teagen - CRES'!$A21)/$P$16 -> -28.259 | F21: =SUMIFS('Teagen - Input'!G:G,'Teagen - Input'!$AH:$AH,'Teagen - CRES'!$A21)/$P$16 -> -27.23176 | G21: =SUMIFS('Teagen - Input'!H:H,'Teagen - Input'!$AH:$AH,'Teagen - CRES'!$A21)/$P$16 -> -27.23351 | H21: =SUMIFS('Teagen - Input'!I:I,'Teagen - Input'!$AH:$AH,'Teagen - CRES'!$A21)/$P$16 -> -27.23176 | I21: =SUMIFS('Teagen - Input'!J:J,'Teagen - Input'!$AH:$AH,'Teagen - CRES'!$A21)/$P$16 -> -27.23176 | J21: =SUMIFS('Teagen - Input'!K:K,'Teagen - Input'!$AH:$AH,'Teagen - CRES'!$A21)/$P$16 -> -27.23176 | K21: =SUMIFS('Teagen - Input'!L:L,'Teagen - Input'!$AH:$AH,'Teagen - CRES'!$A21)/$P$16 -> -29.43788 | L21: =SUMIFS('Teagen - Input'!M:M,'Teagen - Input'!$AH:$AH,'Teagen - CRES'!$A21)/$P$16 -> -29.43788 | M21: =SUMIFS('Teagen - Input'!N:N,'Teagen - Input'!$AH:$AH,'Teagen - CRES'!$A21)/$P$16 -> -25.70222 | N21: =SUM(B21:M21) -> -333.77453
A22: Leasing & Marketing | B22: =SUMIFS('Teagen - Input'!C:C,'Teagen - Input'!$AH:$AH,'Teagen - CRES'!$A22)/$P$16 -> -9.75602 | C22: =SUMIFS('Teagen - Input'!D:D,'Teagen - Input'!$AH:$AH,'Teagen - CRES'!$A22)/$P$16 -> -5.11471 | D22: =SUMIFS('Teagen - Input'!E:E,'Teagen - Input'!$AH:$AH,'Teagen - CRES'!$A22)/$P$16 -> -7.31381 | E22: =SUMIFS('Teagen - Input'!F:F,'Teagen - Input'!$AH:$AH,'Teagen - CRES'!$A22)/$P$16 -> -7.46223 | F22: =SUMIFS('Teagen - Input'!G:G,'Teagen - Input'!$AH:$AH,'Teagen - CRES'!$A22)/$P$16 -> -10.97251 | G22: =SUMIFS('Teagen - Input'!H:H,'Teagen - Input'!$AH:$AH,'Teagen - CRES'!$A22)/$P$16 -> -8.21778 | H22: =SUMIFS('Teagen - Input'!I:I,'Teagen - Input'!$AH:$AH,'Teagen - CRES'!$A22)/$P$16 -> -11.61656 | I22: =SUMIFS('Teagen - Input'!J:J,'Teagen - Input'!$AH:$AH,'Teagen - CRES'!$A22)/$P$16 -> -8.72145 | J22: =SUMIFS('Teagen - Input'!K:K,'Teagen - Input'!$AH:$AH,'Teagen - CRES'!$A22)/$P$16 -> -7.22623 | K22: =SUMIFS('Teagen - Input'!L:L,'Teagen - Input'!$AH:$AH,'Teagen - CRES'!$A22)/$P$16 -> -11.04197 | L22: =SUMIFS('Teagen - Input'!M:M,'Teagen - Input'!$AH:$AH,'Teagen - CRES'!$A22)/$P$16 -> -12.38631 | M22: =SUMIFS('Teagen - Input'!N:N,'Teagen - Input'!$AH:$AH,'Teagen - CRES'!$A22)/$P$16 -> -8.09524 | N22: =SUM(B22:M22) -> -107.92482
A23: Professional fees | B23: =SUMIFS('Teagen - Input'!C:C,'Teagen - Input'!$AH:$AH,'Teagen - CRES'!$A23)/$P$16 -> 1.9364 | C23: =SUMIFS('Teagen - Input'!D:D,'Teagen - Input'!$AH:$AH,'Teagen - CRES'!$A23)/$P$16 -> -0.329 | D23: =SUMIFS('Teagen - Input'!E:E,'Teagen - Input'!$AH:$AH,'Teagen - CRES'!$A23)/$P$16 -> -0.8935 | E23: =SUMIFS('Teagen - Input'!F:F,'Teagen - Input'!$AH:$AH,'Teagen - CRES'!$A23)/$P$16 -> -0.392 | F23: =SUMIFS('Teagen - Input'!G:G,'Teagen - Input'!$AH:$AH,'Teagen - CRES'!$A23)/$P$16 -> -0.02962 | G23: =SUMIFS('Teagen - Input'!H:H,'Teagen - Input'!$AH:$AH,'Teagen - CRES'!$A23)/$P$16 -> 1.57266 | H23: =SUMIFS('Teagen - Input'!I:I,'Teagen - Input'!$AH:$AH,'Teagen - CRES'!$A23)/$P$16 -> -2.72734 | I23: =SUMIFS('Teagen - Input'!J:J,'Teagen - Input'!$AH:$AH,'Teagen - CRES'!$A23)/$P$16 -> 1.066 | J23: =SUMIFS('Teagen - Input'!K:K,'Teagen - Input'!$AH:$AH,'Teagen - CRES'!$A23)/$P$16 -> -1.07094 | K23: =SUMIFS('Teagen - Input'!L:L,'Teagen - Input'!$AH:$AH,'Teagen - CRES'!$A23)/$P$16 -> -1.0274 | L23: =SUMIFS('Teagen - Input'!M:M,'Teagen - Input'!$AH:$AH,'Teagen - CRES'!$A23)/$P$16 -> -1.63098 | M23: =SUMIFS('Teagen - Input'!N:N,'Teagen - Input'!$AH:$AH,'Teagen - CRES'!$A23)/$P$16 -> -1.94649 | N23: =SUM(B23:M23) -> -5.47221
A24: Landscaping | B24: =SUMIFS('Teagen - Input'!C:C,'Teagen - Input'!$AH:$AH,'Teagen - CRES'!$A24)/$P$16 -> -1.357 | C24: =SUMIFS('Teagen - Input'!D:D,'Teagen - Input'!$AH:$AH,'Teagen - CRES'!$A24)/$P$16 -> -0.801 | D24: =SUMIFS('Teagen - Input'!E:E,'Teagen - Input'!$AH:$AH,'Teagen - CRES'!$A24)/$P$16 -> -0.94618 | E24: =SUMIFS('Teagen - Input'!F:F,'Teagen - Input'!$AH:$AH,'Teagen - CRES'!$A24)/$P$16 -> -1.215 | F24: =SUMIFS('Teagen - Input'!G:G,'Teagen - Input'!$AH:$AH,'Teagen - CRES'!$A24)/$P$16 -> -0.8 | G24: =SUMIFS('Teagen - Input'!H:H,'Teagen - Input'!$AH:$AH,'Teagen - CRES'!$A24)/$P$16 -> -1.27616 | H24: =SUMIFS('Teagen - Input'!I:I,'Teagen - Input'!$AH:$AH,'Teagen - CRES'!$A24)/$P$16 -> -4.71903 | I24: =SUMIFS('Teagen - Input'!J:J,'Teagen - Input'!$AH:$AH,'Teagen - CRES'!$A24)/$P$16 -> -0.595 | J24: =SUMIFS('Teagen - Input'!K:K,'Teagen - Input'!$AH:$AH,'Teagen - CRES'!$A24)/$P$16 -> -0.46879 | K24: =SUMIFS('Teagen - Input'!L:L,'Teagen - Input'!$AH:$AH,'Teagen - CRES'!$A24)/$P$16 -> -0.60843 | L24: =SUMIFS('Teagen - Input'!M:M,'Teagen - Input'!$AH:$AH,'Teagen - CRES'!$A24)/$P$16 -> -0.81876 | M24: =SUMIFS('Teagen - Input'!N:N,'Teagen - Input'!$AH:$AH,'Teagen - CRES'!$A24)/$P$16 -> -0.91146 | N24: =SUM(B24:M24) -> -14.51681
A25: Security & Life Safety | B25: =SUMIFS('Teagen - Input'!C:C,'Teagen - Input'!$AH:$AH,'Teagen - CRES'!$A25)/$P$16 -> -0.40204 | C25: =SUMIFS('Teagen - Input'!D:D,'Teagen - Input'!$AH:$AH,'Teagen - CRES'!$A25)/$P$16 -> -0.25 | D25: =SUMIFS('Teagen - Input'!E:E,'Teagen - Input'!$AH:$AH,'Teagen - CRES'!$A25)/$P$16 -> 0 | E25: =SUMIFS('Teagen - Input'!F:F,'Teagen - Input'!$AH:$AH,'Teagen - CRES'!$A25)/$P$16 -> 0 | F25: =SUMIFS('Teagen - Input'!G:G,'Teagen - Input'!$AH:$AH,'Teagen - CRES'!$A25)/$P$16 -> -0.85 | G25: =SUMIFS('Teagen - Input'!H:H,'Teagen - Input'!$AH:$AH,'Teagen - CRES'!$A25)/$P$16 -> -0.445 | H25: =SUMIFS('Teagen - Input'!I:I,'Teagen - Input'!$AH:$AH,'Teagen - CRES'!$A25)/$P$16 -> -0.5 | I25: =SUMIFS('Teagen - Input'!J:J,'Teagen - Input'!$AH:$AH,'Teagen - CRES'!$A25)/$P$16 -> -1.075 | J25: =SUMIFS('Teagen - Input'!K:K,'Teagen - Input'!$AH:$AH,'Teagen - CRES'!$A25)/$P$16 -> -0.73078 | K25: =SUMIFS('Teagen - Input'!L:L,'Teagen - Input'!$AH:$AH,'Teagen - CRES'!$A25)/$P$16 -> 1.15 | L25: =SUMIFS('Teagen - Input'!M:M,'Teagen - Input'!$AH:$AH,'Teagen - CRES'!$A25)/$P$16 -> 0 | M25: =SUMIFS('Teagen - Input'!N:N,'Teagen - Input'!$AH:$AH,'Teagen - CRES'!$A25)/$P$16 -> -0.2 | N25: =SUM(B25:M25) -> -3.30282
A26: Repairs & Maintenance | B26: =SUMIFS('Teagen - Input'!C:C,'Teagen - Input'!$AH:$AH,'Teagen - CRES'!$A26)/$P$16 -> -28.01181 | C26: =SUMIFS('Teagen - Input'!D:D,'Teagen - Input'!$AH:$AH,'Teagen - CRES'!$A26)/$P$16 -> -19.79009 | D26: =SUMIFS('Teagen - Input'!E:E,'Teagen - Input'!$AH:$AH,'Teagen - CRES'!$A26)/$P$16 -> -23.50649 | E26: =SUMIFS('Teagen - Input'!F:F,'Teagen - Input'!$AH:$AH,'Teagen - CRES'!$A26)/$P$16 -> -19.95809 | F26: =SUMIFS('Teagen - Input'!G:G,'Teagen - Input'!$AH:$AH,'Teagen - CRES'!$A26)/$P$16 -> -21.43547 | G26: =SUMIFS('Teagen - Input'!H:H,'Teagen - Input'!$AH:$AH,'Teagen - CRES'!$A26)/$P$16 -> -15.77363 | H26: =SUMIFS('Teagen - Input'!I:I,'Teagen - Input'!$AH:$AH,'Teagen - CRES'!$A26)/$P$16 -> -24.02175 | I26: =SUMIFS('Teagen - Input'!J:J,'Teagen - Input'!$AH:$AH,'Teagen - CRES'!$A26)/$P$16 -> -19.2137 | J26: =SUMIFS('Teagen - Input'!K:K,'Teagen - Input'!$AH:$AH,'Teagen - CRES'!$A26)/$P$16 -> -18.16488 | K26: =SUMIFS('Teagen - Input'!L:L,'Teagen - Input'!$AH:$AH,'Teagen - CRES'!$A26)/$P$16 -> -15.49057 | L26: =SUMIFS('Teagen - Input'!M:M,'Teagen - Input'!$AH:$AH,'Teagen - CRES'!$A26)/$P$16 -> -16.14859 | M26: =SUMIFS('Teagen - Input'!N:N,'Teagen - Input'!$AH:$AH,'Teagen - CRES'!$A26)/$P$16 -> -19.61054 | N26: =SUM(B26:M26) -> -241.12561
A27: Unit T/O Refurbishment | B27: =SUMIFS('Teagen - Input'!C:C,'Teagen - Input'!$AH:$AH,'Teagen - CRES'!$A27)/$P$16 -> 0 | C27: =SUMIFS('Teagen - Input'!D:D,'Teagen - Input'!$AH:$AH,'Teagen - CRES'!$A27)/$P$16 -> 0 | D27: =SUMIFS('Teagen - Input'!E:E,'Teagen - Input'!$AH:$AH,'Teagen - CRES'!$A27)/$P$16 -> 0 | E27: =SUMIFS('Teagen - Input'!F:F,'Teagen - Input'!$AH:$AH,'Teagen - CRES'!$A27)/$P$16 -> 0 | F27: =SUMIFS('Teagen - Input'!G:G,'Teagen - Input'!$AH:$AH,'Teagen - CRES'!$A27)/$P$16 -> 0 | G27: =SUMIFS('Teagen - Input'!H:H,'Teagen - Input'!$AH:$AH,'Teagen - CRES'!$A27)/$P$16 -> 0 | H27: =SUMIFS('Teagen - Input'!I:I,'Teagen - Input'!$AH:$AH,'Teagen - CRES'!$A27)/$P$16 -> 0 | I27: =SUMIFS('Teagen - Input'!J:J,'Teagen - Input'!$AH:$AH,'Teagen - CRES'!$A27)/$P$16 -> 0 | J27: =SUMIFS('Teagen - Input'!K:K,'Teagen - Input'!$AH:$AH,'Teagen - CRES'!$A27)/$P$16 -> 0 | K27: =SUMIFS('Teagen - Input'!L:L,'Teagen - Input'!$AH:$AH,'Teagen - CRES'!$A27)/$P$16 -> 0 | L27: =SUMIFS('Teagen - Input'!M:M,'Teagen - Input'!$AH:$AH,'Teagen - CRES'!$A27)/$P$16 -> 0 | M27: =SUMIFS('Teagen - Input'!N:N,'Teagen - Input'!$AH:$AH,'Teagen - CRES'!$A27)/$P$16 -> 0 | N27: =SUM(B27:M27) -> 0
A28: Utilities | B28: =SUMIFS('Teagen - Input'!C:C,'Teagen - Input'!$AH:$AH,'Teagen - CRES'!$A28)/$P$16 -> -11.67353 | C28: =SUMIFS('Teagen - Input'!D:D,'Teagen - Input'!$AH:$AH,'Teagen - CRES'!$A28)/$P$16 -> -25.22605 | D28: =SUMIFS('Teagen - Input'!E:E,'Teagen - Input'!$AH:$AH,'Teagen - CRES'!$A28)/$P$16 -> -19.02591 | E28: =SUMIFS('Teagen - Input'!F:F,'Teagen - Input'!$AH:$AH,'Teagen - CRES'!$A28)/$P$16 -> -27.75683 | F28: =SUMIFS('Teagen - Input'!G:G,'Teagen - Input'!$AH:$AH,'Teagen - CRES'!$A28)/$P$16 -> -24.10736 | G28: =SUMIFS('Teagen - Input'!H:H,'Teagen - Input'!$AH:$AH,'Teagen - CRES'!$A28)/$P$16 -> -25.44628 | H28: =SUMIFS('Teagen - Input'!I:I,'Teagen - Input'!$AH:$AH,'Teagen - CRES'!$A28)/$P$16 -> -24.49201 | I28: =SUMIFS('Teagen - Input'!J:J,'Teagen - Input'!$AH:$AH,'Teagen - CRES'!$A28)/$P$16 -> -20.41639 | J28: =SUMIFS('Teagen - Input'!K:K,'Teagen - Input'!$AH:$AH,'Teagen - CRES'!$A28)/$P$16 -> -20.52702 | K28: =SUMIFS('Teagen - Input'!L:L,'Teagen - Input'!$AH:$AH,'Teagen - CRES'!$A28)/$P$16 -> -22.63185 | L28: =SUMIFS('Teagen - Input'!M:M,'Teagen - Input'!$AH:$AH,'Teagen - CRES'!$A28)/$P$16 -> -21.11638 | M28: =SUMIFS('Teagen - Input'!N:N,'Teagen - Input'!$AH:$AH,'Teagen - CRES'!$A28)/$P$16 -> -26.25998 | N28: =SUM(B28:M28) -> -268.67959
... A31: Other | B31: =SUMIFS('Teagen - Input'!C:C,'Teagen - Input'!$AH:$AH,'Teagen - CRES'!$A31)/$P$16 -> 0 | C31: =SUMIFS('Teagen - Input'!D:D,'Teagen - Input'!$AH:$AH,'Teagen - CRES'!$A31)/$P$16 -> 0 | D31: =SUMIFS('Teagen - Input'!E:E,'Teagen - Input'!$AH:$AH,'Teagen - CRES'!$A31)/$P$16 -> 0 | E31: =SUMIFS('Teagen - Input'!F:F,'Teagen - Input'!$AH:$AH,'Teagen - CRES'!$A31)/$P$16 -> 0 | F31: =SUMIFS('Teagen - Input'!G:G,'Teagen - Input'!$AH:$AH,'Teagen - CRES'!$A31)/$P$16 -> 0 | G31: =SUMIFS('Teagen - Input'!H:H,'Teagen - Input'!$AH:$AH,'Teagen - CRES'!$A31)/$P$16 -> 0 | H31: =SUMIFS('Teagen - Input'!I:I,'Teagen - Input'!$AH:$AH,'Teagen - CRES'!$A31)/$P$16 -> 0 | I31: =SUMIFS('Teagen - Input'!J:J,'Teagen - Input'!$AH:$AH,'Teagen - CRES'!$A31)/$P$16 -> 0 | J31: =SUMIFS('Teagen - Input'!K:K,'Teagen - Input'!$AH:$AH,'Teagen - CRES'!$A31)/$P$16 -> 0 | K31: =SUMIFS('Teagen - Input'!L:L,'Teagen - Input'!$AH:$AH,'Teagen - CRES'!$A31)/$P$16 -> 0 | L31: =SUMIFS('Teagen - Input'!M:M,'Teagen - Input'!$AH:$AH,'Teagen - CRES'!$A31)/$P$16 -> 0 | M31: =SUMIFS('Teagen - Input'!N:N,'Teagen - Input'!$AH:$AH,'Teagen - CRES'!$A31)/$P$16 -> 0 | N31: =SUM(B31:M31) -> 0
A32: Total Expense | B32: =SUM(B17:B31) -> -162.25994 | C32: =SUM(C17:C31) -> -168.71817 | D32: =SUM(D17:D31) -> -180.62626 | E32: =SUM(E17:E31) -> -171.80477 | F32: =SUM(F17:F31) -> -174.81452 | G32: =SUM(G17:G31) -> -167.5879 | H32: =SUM(H17:H31) -> -186.08516 | I32: =SUM(I17:I31) -> -181.90098 | ... M32: =SUM(M17:M31) -> -177.43779 | N32: =SUM(B32:M32) -> -2100.3746 | P32: =1000*M32 -> -177437.79
B34: =B16 -> Jan 2024 | C34: =C16 -> Feb 2024 | D34: =D16 -> Mar 2024 | E34: =E16 -> Apr 2024 | F34: =F16 -> May 2024 | G34: =G16 -> Jun 2024 | H34: =H16 -> Jul 2024 | I34: =I16 -> Aug 2024 | ... M34: =M16 -> Dec 2024 | N34: YTD
A35: EBITDA (NOI) | B35: =SUM(B32,B14) -> 137.37859 | C35: =SUM(C32,C14) -> 128.99331 | D35: =SUM(D32,D14) -> 121.15899 | E35: =SUM(E32,E14) -> 120.4681 | F35: =SUM(F32,F14) -> 126.55713 | G35: =SUM(G32,G14) -> 122.9717 | H35: =SUM(H32,H14) -> 126.31489 | I35: =SUM(I32,I14) -> 102.13323 | ... N35: =SUM(N32,N14) -> 1517.8885 | P35: =1000*M35 -> 150165.21
B36: =IF((B35*$P$1)='Teagen - Input'!C163,"","ERROR") | C36: =IF((C35*$P$1)='Teagen - Input'!D163,"","ERROR") | D36: =IF((D35*$P$1)='Teagen - Input'!E163,"","ERROR") | E36: =IF((E35*$P$1)='Teagen - Input'!F163,"","ERROR") | F36: =IF((F35*$P$1)='Teagen - Input'!G163,"","ERROR") | G36: =IF((G35*$P$1)='Teagen - Input'!H163,"","ERROR") | H36: =IF((H35*$P$1)='Teagen - Input'!I163,"","ERROR") | I36: =IF((I35*$P$1)='Teagen - Input'!J163,"","ERROR") | ... M36: =IF((M35*$P$1)='Teagen - Input'!N163,"","ERROR")
B37: =B34 -> Jan 2024 | C37: =C34 -> Feb 2024 | D37: =D34 -> Mar 2024 | E37: =E34 -> Apr 2024 | F37: =F34 -> May 2024 | G37: =G34 -> Jun 2024 | H37: =H34 -> Jul 2024 | I37: =I34 -> Aug 2024 | ... M37: =M34 -> Dec 2024 | N37: YTD
A38: Repl. Reserve Fund | B38: =SUMIFS('Teagen - Input'!C:C,'Teagen - Input'!$AH:$AH,'Teagen - CRES'!$A38)/$P$16 -> -46.73647 | C38: =SUMIFS('Teagen - Input'!D:D,'Teagen - Input'!$AH:$AH,'Teagen - CRES'!$A38)/$P$16 -> -35.52805 | D38: =SUMIFS('Teagen - Input'!E:E,'Teagen - Input'!$AH:$AH,'Teagen - CRES'!$A38)/$P$16 -> -18.3556 | E38: =SUMIFS('Teagen - Input'!F:F,'Teagen - Input'!$AH:$AH,'Teagen - CRES'!$A38)/$P$16 -> -40.65021 | F38: =SUMIFS('Teagen - Input'!G:G,'Teagen - Input'!$AH:$AH,'Teagen - CRES'!$A38)/$P$16 -> -15.70004 | G38: =SUMIFS('Teagen - Input'!H:H,'Teagen - Input'!$AH:$AH,'Teagen - CRES'!$A38)/$P$16 -> -16.26228 | H38: =SUMIFS('Teagen - Input'!I:I,'Teagen - Input'!$AH:$AH,'Teagen - CRES'!$A38)/$P$16 -> -21.23273 | I38: =SUMIFS('Teagen - Input'!J:J,'Teagen - Input'!$AH:$AH,'Teagen - CRES'!$A38)/$P$16 -> -27.55792 | J38: =SUMIFS('Teagen - Input'!K:K,'Teagen - Input'!$AH:$AH,'Teagen - CRES'!$A38)/$P$16 -> -24.98127 | K38: =SUMIFS('Teagen - Input'!L:L,'Teagen - Input'!$AH:$AH,'Teagen - CRES'!$A38)/$P$16 -> -20.74701 | L38: =SUMIFS('Teagen - Input'!M:M,'Teagen - Input'!$AH:$AH,'Teagen - CRES'!$A38)/$P$16 -> -16.78633 | M38: =SUMIFS('Teagen - Input'!N:N,'Teagen - Input'!$AH:$AH,'Teagen - CRES'!$A38)/$P$16 -> -44.36704 | N38: =SUM(B38:M38) -> -328.90495
A39: State Franchise Fee | B39: =SUMIFS('Teagen - Input'!C:C,'Teagen - Input'!$AH:$AH,'Teagen - CRES'!$A39)/$P$16 -> 0 | C39: =SUMIFS('Teagen - Input'!D:D,'Teagen - Input'!$AH:$AH,'Teagen - CRES'!$A39)/$P$16 -> 0 | D39: =SUMIFS('Teagen - Input'!E:E,'Teagen - Input'!$AH:$AH,'Teagen - CRES'!$A39)/$P$16 -> 0 | E39: =SUMIFS('Teagen - Input'!F:F,'Teagen - Input'!$AH:$AH,'Teagen - CRES'!$A39)/$P$16 -> 0 | F39: =SUMIFS('Teagen - Input'!G:G,'Teagen - Input'!$AH:$AH,'Teagen - CRES'!$A39)/$P$16 -> 0 | G39: =SUMIFS('Teagen - Input'!H:H,'Teagen - Input'!$AH:$AH,'Teagen - CRES'!$A39)/$P$16 -> 0 | H39: =SUMIFS('Teagen - Input'!I:I,'Teagen - Input'!$AH:$AH,'Teagen - CRES'!$A39)/$P$16 -> 0 | I39: =SUMIFS('Teagen - Input'!J:J,'Teagen - Input'!$AH:$AH,'Teagen - CRES'!$A39)/$P$16 -> 0 | J39: =SUMIFS('Teagen - Input'!K:K,'Teagen - Input'!$AH:$AH,'Teagen - CRES'!$A39)/$P$16 -> 0 | K39: =SUMIFS('Teagen - Input'!L:L,'Teagen - Input'!$AH:$AH,'Teagen - CRES'!$A39)/$P$16 -> 0 | L39: =SUMIFS('Teagen - Input'!M:M,'Teagen - Input'!$AH:$AH,'Teagen - CRES'!$A39)/$P$16 -> 0 | M39: =SUMIFS('Teagen - Input'!N:N,'Teagen - Input'!$AH:$AH,'Teagen - CRES'!$A39)/$P$16 -> 0 | N39: =SUM(B39:M39) -> 0
A40: Partnership Professional Fees | B40: =SUMIFS('Teagen - Input'!C:C,'Teagen - Input'!$AH:$AH,'Teagen - CRES'!$A40)/$P$16 -> -0.71291 | C40: =SUMIFS('Teagen - Input'!D:D,'Teagen - Input'!$AH:$AH,'Teagen - CRES'!$A40)/$P$16 -> -0.8581 | D40: =SUMIFS('Teagen - Input'!E:E,'Teagen - Input'!$AH:$AH,'Teagen - CRES'!$A40)/$P$16 -> -1.19727 | E40: =SUMIFS('Teagen - Input'!F:F,'Teagen - Input'!$AH:$AH,'Teagen - CRES'!$A40)/$P$16 -> -2.02563 | F40: =SUMIFS('Teagen - Input'!G:G,'Teagen - Input'!$AH:$AH,'Teagen - CRES'!$A40)/$P$16 -> -0.95697 | G40: =SUMIFS('Teagen - Input'!H:H,'Teagen - Input'!$AH:$AH,'Teagen - CRES'!$A40)/$P$16 -> -14.43212 | H40: =SUMIFS('Teagen - Input'!I:I,'Teagen - Input'!$AH:$AH,'Teagen - CRES'!$A40)/$P$16 -> -0.44245 | I40: =SUMIFS('Teagen - Input'!J:J,'Teagen - Input'!$AH:$AH,'Teagen - CRES'!$A40)/$P$16 -> -1.13027 | J40: =SUMIFS('Teagen - Input'!K:K,'Teagen - Input'!$AH:$AH,'Teagen - CRES'!$A40)/$P$16 -> -0.05052 | K40: =SUMIFS('Teagen - Input'!L:L,'Teagen - Input'!$AH:$AH,'Teagen - CRES'!$A40)/$P$16 -> -1.32771 | L40: =SUMIFS('Teagen - Input'!M:M,'Teagen - Input'!$AH:$AH,'Teagen - CRES'!$A40)/$P$16 -> -7.03508 | M40: =SUMIFS('Teagen - Input'!N:N,'Teagen - Input'!$AH:$AH,'Teagen - CRES'!$A40)/$P$16 -> -0.43627 | N40: =SUM(B40:M40) -> -30.6053
A41: Asset Management Fees | B41: =SUMIFS('Teagen - Input'!C:C,'Teagen - Input'!$AH:$AH,'Teagen - CRES'!$A41)/$P$16 -> -2.24729 | C41: =SUMIFS('Teagen - Input'!D:D,'Teagen - Input'!$AH:$AH,'Teagen - CRES'!$A41)/$P$16 -> -2.23284 | D41: =SUMIFS('Teagen - Input'!E:E,'Teagen - Input'!$AH:$AH,'Teagen - CRES'!$A41)/$P$16 -> -2.26339 | E41: =SUMIFS('Teagen - Input'!F:F,'Teagen - Input'!$AH:$AH,'Teagen - CRES'!$A41)/$P$16 -> -2.19205 | F41: =SUMIFS('Teagen - Input'!G:G,'Teagen - Input'!$AH:$AH,'Teagen - CRES'!$A41)/$P$16 -> -2.26029 | G41: =SUMIFS('Teagen - Input'!H:H,'Teagen - Input'!$AH:$AH,'Teagen - CRES'!$A41)/$P$16 -> -2.1792 | H41: =SUMIFS('Teagen - Input'!I:I,'Teagen - Input'!$AH:$AH,'Teagen - CRES'!$A41)/$P$16 -> -2.343 | I41: =SUMIFS('Teagen - Input'!J:J,'Teagen - Input'!$AH:$AH,'Teagen - CRES'!$A41)/$P$16 -> -2.13026 | J41: =SUMIFS('Teagen - Input'!K:K,'Teagen - Input'!$AH:$AH,'Teagen - CRES'!$A41)/$P$16 -> -2.29717 | K41: =SUMIFS('Teagen - Input'!L:L,'Teagen - Input'!$AH:$AH,'Teagen - CRES'!$A41)/$P$16 -> -2.29949 | L41: =SUMIFS('Teagen - Input'!M:M,'Teagen - Input'!$AH:$AH,'Teagen - CRES'!$A41)/$P$16 -> -2.23499 | M41: =SUMIFS('Teagen - Input'!N:N,'Teagen - Input'!$AH:$AH,'Teagen - CRES'!$A41)/$P$16 -> -2.45702 | N41: =SUM(B41:M41) -> -27.13699
A42: Debt Service | B42: =SUMIFS('Teagen - Input'!C:C,'Teagen - Input'!$AH:$AH,'Teagen - CRES'!$A42)/$P$16 -> -91.21585 | C42: =SUMIFS('Teagen - Input'!D:D,'Teagen - Input'!$AH:$AH,'Teagen - CRES'!$A42)/$P$16 -> -88.87795 | D42: =SUMIFS('Teagen - Input'!E:E,'Teagen - Input'!$AH:$AH,'Teagen - CRES'!$A42)/$P$16 -> -88.29433 | E42: =SUMIFS('Teagen - Input'!F:F,'Teagen - Input'!$AH:$AH,'Teagen - CRES'!$A42)/$P$16 -> -90.57945 | F42: =SUMIFS('Teagen - Input'!G:G,'Teagen - Input'!$AH:$AH,'Teagen - CRES'!$A42)/$P$16 -> -90.385 | G42: =SUMIFS('Teagen - Input'!H:H,'Teagen - Input'!$AH:$AH,'Teagen - CRES'!$A42)/$P$16 -> -92.5139 | H42: =SUMIFS('Teagen - Input'!I:I,'Teagen - Input'!$AH:$AH,'Teagen - CRES'!$A42)/$P$16 -> -94.86974 | I42: =SUMIFS('Teagen - Input'!J:J,'Teagen - Input'!$AH:$AH,'Teagen - CRES'!$A42)/$P$16 -> -96.94518 | J42: =SUMIFS('Teagen - Input'!K:K,'Teagen - Input'!$AH:$AH,'Teagen - CRES'!$A42)/$P$16 -> -97.40967 | K42: =SUMIFS('Teagen - Input'!L:L,'Teagen - Input'!$AH:$AH,'Teagen - CRES'!$A42)/$P$16 -> -97.06548 | L42: =SUMIFS('Teagen - Input'!M:M,'Teagen - Input'!$AH:$AH,'Teagen - CRES'!$A42)/$P$16 -> -96.38939 | M42: =SUMIFS('Teagen - Input'!N:N,'Teagen - Input'!$AH:$AH,'Teagen - CRES'!$A42)/$P$16 -> -117.53171 | N42: =SUM(B42:M42) -> -1142.0776
A43: Other 2 | B43: =SUMIFS('Teagen - Input'!C:C,'Teagen - Input'!$AH:$AH,'Teagen - CRES'!$A43)/$P$16 -> 0 | C43: =SUMIFS('Teagen - Input'!D:D,'Teagen - Input'!$AH:$AH,'Teagen - CRES'!$A43)/$P$16 -> 0 | D43: =SUMIFS('Teagen - Input'!E:E,'Teagen - Input'!$AH:$AH,'Teagen - CRES'!$A43)/$P$16 -> 0 | E43: =SUMIFS('Teagen - Input'!F:F,'Teagen - Input'!$AH:$AH,'Teagen - CRES'!$A43)/$P$16 -> 0 | F43: =SUMIFS('Teagen - Input'!G:G,'Teagen - Input'!$AH:$AH,'Teagen - CRES'!$A43)/$P$16 -> 0 | G43: =SUMIFS('Teagen - Input'!H:H,'Teagen - Input'!$AH:$AH,'Teagen - CRES'!$A43)/$P$16 -> 0 | H43: =SUMIFS('Teagen - Input'!I:I,'Teagen - Input'!$AH:$AH,'Teagen - CRES'!$A43)/$P$16 -> 0 | I43: =SUMIFS('Teagen - Input'!J:J,'Teagen - Input'!$AH:$AH,'Teagen - CRES'!$A43)/$P$16 -> 0 | J43: =SUMIFS('Teagen - Input'!K:K,'Teagen - Input'!$AH:$AH,'Teagen - CRES'!$A43)/$P$16 -> 0 | K43: =SUMIFS('Teagen - Input'!L:L,'Teagen - Input'!$AH:$AH,'Teagen - CRES'!$A43)/$P$16 -> 0 | L43: =SUMIFS('Teagen - Input'!M:M,'Teagen - Input'!$AH:$AH,'Teagen - CRES'!$A43)/$P$16 -> 0 | M43: =SUMIFS('Teagen - Input'!N:N,'Teagen - Input'!$AH:$AH,'Teagen - CRES'!$A43)/$P$16 -> 0 | N43: =SUM(B43:M43) -> 0
A44: Total Below Line | B44: =SUM(B38:B43) -> -140.91252 | C44: =SUM(C38:C43) -> -127.49694 | D44: =SUM(D38:D43) -> -110.11059 | E44: =SUM(E38:E43) -> -135.44734 | F44: =SUM(F38:F43) -> -109.3023 | G44: =SUM(G38:G43) -> -125.3875 | H44: =SUM(H38:H43) -> -118.88792 | I44: =SUM(I38:I43) -> -127.76363 | ... M44: =SUM(M38:M43) -> -164.79204 | N44: =SUM(B44:M44) -> -1528.7249
A45: Renovations | B45: =SUMIFS('Teagen - Input'!C:C,'Teagen - Input'!$AH:$AH,'Teagen - CRES'!$A45)/$P$16 -> 1.3642421e-15 | C45: =SUMIFS('Teagen - Input'!D:D,'Teagen - Input'!$AH:$AH,'Teagen - CRES'!$A45)/$P$16 -> 6.3664629e-15 | D45: =SUMIFS('Teagen - Input'!E:E,'Teagen - Input'!$AH:$AH,'Teagen - CRES'!$A45)/$P$16 -> 2.7284841e-15 | E45: =SUMIFS('Teagen - Input'!F:F,'Teagen - Input'!$AH:$AH,'Teagen - CRES'!$A45)/$P$16 -> -1.3642421e-14 | F45: =SUMIFS('Teagen - Input'!G:G,'Teagen - Input'!$AH:$AH,'Teagen - CRES'!$A45)/$P$16 -> -1.4551915e-14 | G45: =SUMIFS('Teagen - Input'!H:H,'Teagen - Input'!$AH:$AH,'Teagen - CRES'!$A45)/$P$16 -> -2.7284841e-15 | H45: =SUMIFS('Teagen - Input'!I:I,'Teagen - Input'!$AH:$AH,'Teagen - CRES'!$A45)/$P$16 -> -9.094947e-16 | I45: =SUMIFS('Teagen - Input'!J:J,'Teagen - Input'!$AH:$AH,'Teagen - CRES'!$A45)/$P$16 -> -3.6379788e-15 | J45: =SUMIFS('Teagen - Input'!K:K,'Teagen - Input'!$AH:$AH,'Teagen - CRES'!$A45)/$P$16 -> 4.5474735e-15 | K45: =SUMIFS('Teagen - Input'!L:L,'Teagen - Input'!$AH:$AH,'Teagen - CRES'!$A45)/$P$16 -> 1.8189894e-15 | L45: =SUMIFS('Teagen - Input'!M:M,'Teagen - Input'!$AH:$AH,'Teagen - CRES'!$A45)/$P$16 -> 1.8189894e-15 | M45: =SUMIFS('Teagen - Input'!N:N,'Teagen - Input'!$AH:$AH,'Teagen - CRES'!$A45)/$P$16 -> -3.6379788e-15 | N45: =SUM(B45:M45) -> -2.0463631e-14
B46: =B37 -> Jan 2024 | C46: =C37 -> Feb 2024 | D46: =D37 -> Mar 2024 | E46: =E37 -> Apr 2024 | F46: =F37 -> May 2024 | G46: =G37 -> Jun 2024 | H46: =H37 -> Jul 2024 | I46: =I37 -> Aug 2024 | ... M46: =M37 -> Dec 2024 | N46: YTD
A47: Monthly Cash Flow | B47: =SUM(B44,B35) -> -3.53393 | C47: =SUM(C44,C35) -> 1.49637 | D47: =SUM(D44,D35) -> 11.0484 | E47: =SUM(E44,E35) -> -14.97924 | F47: =SUM(F44,F35) -> 17.25483 | G47: =SUM(G44,G35) -> -2.4158 | H47: =SUM(H44,H35) -> 7.42697 | I47: =SUM(I44,I35) -> -25.6304 | ... M47: =SUM(M44,M35) -> -14.62683 | N47: =SUM(B47:M47) -> -10.83644
B49: =B1 -> Jan 2024 | C49: =C1 -> Feb 2024 | D49: =D1 -> Mar 2024 | E49: =E1 -> Apr 2024 | F49: =F1 -> May 2024 | G49: =G1 -> Jun 2024 | H49: =H1 -> Jul 2024 | I49: =I1 -> Aug 2024 | ... M49: =M1 -> Dec 2024
A50: Operating Account Balance
A51: Interest Reserve Account
A52: Undeposited Funds
A53: Security Deposits
A54: Total Cash | B54: =IF(B36="","",SUM(B50:B53)) | C54: =IF(C36="","",SUM(C50:C53)) | D54: =IF(D36="","",SUM(D50:D53)) | E54: =IF(E36="","",SUM(E50:E53)) | F54: =IF(F36="","",SUM(F50:F53)) | G54: =IF(G36="","",SUM(G50:G53)) | H54: =IF(H36="","",SUM(H50:H53)) | I54: =IF(I36="","",SUM(I50:I53)) | ... M54: =IF(M36="","",SUM(M50:M53))
A55: Open AR
A56: Escrow - Taxes
A57: Escrow - Insurance
A58: Escrow - Other
A59: Escrow - RR
A60: Open AP
A62: Total Equity
A63: Total Debt

Sheet Tides on McDowell - Variance
A2: P/L Report
A3: Tides on McDowell
A4: Jun 2024
A5: Accrual Basis
C7: Jun 2024 | H7: YTD ( Jan 2024 - Jun 2024 )
A8: Account | B8: Account Name | C8: Actual | D8: Budget | E8: $ Variance | F8: % Variance | G8: Variance Notes | H8: Actual | I8: Budget | J8: $ Variance | K8: % Variance | M8: Income Statement Budget Vs Actual: Per Sq.Ft. | N8: Income Statement Budget Vs Actual: Per Unit | O8: Income Statement Budget Vs Actual: Mar 2023 | P8: Income Statement Budget Vs Actual: Actual | Q8: Income Statement Budget Vs Actual: Budget | R8: Income Statement Budget Vs Actual: Per Sq.Ft. | S8: Income Statement Budget Vs Actual: YTD ( 2023 ) | T8: Income Statement Budget Vs Actual: % of Income | U8: Income Statement Budget Vs Actual: % of Income | V8: Income Statement Budget Vs Actual: Prior Year End | W8: Income Statement Budget Vs Actual: Annual Budget | X8: Income Statement Budget Vs Actual: Per Sq.Ft. (Annualized) | Y8: Income Statement Budget Vs Actual: GL Account Type Id | Z8: Income Statement Budget Vs Actual: % of Income | AA8: Income Statement Budget Vs Actual: % of Income | AB8: Income Statement Budget Vs Actual: % of Income | AC8: Income Statement Budget Vs Actual: % of Income | AD8: Income Statement Budget Vs Actual: Prior Mtd Actual Changed Sign | AE8: Income Statement Budget Vs Actual: Mtd Actual Changed Sign | AF8: Income Statement Budget Vs Actual: Mtd Budget Changed Sign | AG8: Income Statement Budget Vs Actual: Mtd Variance Temp | AH8: Income Statement Budget Vs Actual: Prior Ytd Actual Changed Sign | AI8: Income Statement Budget Vs Actual: Prior Year Actual Changed Sign | AJ8: Income Statement Budget Vs Actual: Ytd Actual Changed Sign | AK8: Income Statement Budget Vs Actual: Ytd Budget Changed Sign | AL8: Income Statement Budget Vs Actual: Annual Budget Changed Sign | AM8: Income Statement Budget Vs Actual: Ytd Variance Temp | AN8: Income Statement Budget Vs Actual: Income Expense Converter | AO8: Income Statement Budget Vs Actual: Variance Converter
A9: Income
A10: Rental Income
A11: 5001 | B11: Market Rent | C11: 333057 | D11: 390270.58 | E11: -57213.58 | F11: -0.14659978 | G11: This reflects lower than budgeted market rents due to pricing in line with current comps rates. | H11: 2016155.3 | I11: 2300476 | J11: -284320.61 | K11: -0.12359208 | O11: 371732 | S11: 1117511.6 | T11: 955092.21 | U11: 1021393.9 | V11: 4396476 | W11: 4701254.9 | Y11: 4 | Z11: 330077.29 | AA11: 350787.57 | AD11: 371732 | AE11: 337628 | AF11: 382038.73 | AG11: -44410.73 | AH11: 1117511.6 | AI11: 4396476 | AJ11: 1011007.3 | AK11: 1137900.8 | AL11: 4701254.9 | AM11: -126893.44 | AN11: 1 | AO11: 1
A12: 5002 | B12: Gain/Loss To Lease | C12: 751.16 | D12: -32255 | E12: 33006.16 | F12: 1.0232882 | G12: This reflect slight gain to lease due to current effective rates being higher than current market rents. | H12: 16213.15 | I12: -192327.46 | J12: 208540.61 | K12: 1.0842997 | O12: -40437.36 | S12: -134054.83 | T12: 955092.21 | U12: 1021393.9 | V12: -340257.95 | W12: -387557.93 | Y12: 4 | Z12: 330077.29 | AA12: 350787.57 | AD12: -40437.36 | AE12: 4611.85 | AF12: -32014.29 | AG12: 36626.14 | AH12: -134054.83 | AI12: -340257.95 | AJ12: 10153.16 | AK12: -95803.57 | AL12: -387557.93 | AM12: 105956.73 | AN12: 1 | AO12: 1
B13: Rental Income | C13: 333808.16 | D13: 358015.58 | E13: -24207.42 | F13: -0.067615549 | H13: 2032368.5 | I13: 2108148.5 | J13: -75780 | K13: -0.035946235 | O13: 331294.64 | S13: 983456.76 | V13: 4056218.1 | W13: 4313696.9 | Y13: 4 | AD13: 331294.64 | AE13: 342239.85 | AF13: 350024.44 | AG13: -7784.59 | AH13: 983456.76 | AI13: 4056218.1 | AJ13: 1021160.5 | AK13: 1042097.2 | AL13: 4313696.9 | AM13: -20936.71
A14: Vacancy, Losses & Concessions
A15: 5102 | B15: Delinquent Rent/Bad Debt | C15: -15928.02 | D15: -6500 | E15: -9428.02 | F15: -1.4504646 | G15: This reflects bad debt for delinquent accounts for outstanding balances at month end. | H15: -84421.25 | I15: -39000 | J15: -45421.25 | K15: -1.1646474 | O15: -10000 | S15: -53493.47 | T15: 955092.21 | U15: 1021393.9 | V15: -390902.75 | W15: -78000 | Y15: 4 | Z15: 330077.29 | AA15: 350787.57 | AD15: -10000 | AE15: -6720.88 | AF15: -6500 | AG15: -220.88 | AH15: -53493.47 | AI15: -390902.75 | AJ15: -29595.77 | AK15: -19500 | AL15: -78000 | AM15: -10095.77 | AN15: 1 | AO15: 1
A16: 5950 | B16: Bad Debt Recovery | C16: 0 | D16: 0 | E16: 0 | F16: 0 | H16: 2785.4 | I16: 0 | J16: 2785.4 | K16: 1 | O16: 0 | S16: 0 | T16: 955092.21 | U16: 1021393.9 | V16: 0 | W16: 0 | Y16: 4 | Z16: 330077.29 | AA16: 350787.57 | AD16: 0 | AE16: 2785.4 | AF16: 0 | AG16: 2785.4 | AH16: 0 | AI16: 0 | AJ16: 2785.4 | AK16: 0 | AL16: 0 | AM16: 2785.4 | AN16: 1 | AO16: 1
A17: 5103 | B17: Rental Concessions | C17: -2537.52 | D17: -2000 | E17: -537.52 | F17: -0.26876 | H17: -43670.07 | I17: -12000 | J17: -31670.07 | K17: -2.6391725 | O17: 0 | S17: 0 | T17: 955092.21 | U17: 1021393.9 | V17: -12127.5 | W17: -24000 | Y17: 4 | Z17: 330077.29 | AA17: 350787.57 | AD17: 0 | AE17: -13492.5 | AF17: -2000 | AG17: -11492.5 | AH17: 0 | AI17: -12127.5 | AJ17: -40821.05 | AK17: -6000 | AL17: -24000 | AM17: -34821.05 | AN17: 1 | AO17: 1
A18: 5104 | B18: Vacancy Loss | C18: -49054.65 | D18: -37947.06 | E18: -11107.59 | F18: -0.2927128 | G18: This reflects higher than budgeted vacancy loss due to increased skips/evictions by tenants losing jobs and relocating. | H18: -299063.6 | I18: -248772.09 | J18: -50291.51 | K18: -0.20215897 | O18: -25852.27 | S18: -78100.53 | T18: 955092.21 | U18: 1021393.9 | V18: -533553.63 | W18: -421034.26 | Y18: 4 | Z18: 330077.29 | AA18: 350787.57 | AD18: -25852.27 | AE18: -50895.72 | AF18: -37663.87 | AG18: -13231.85 | AH18: -78100.53 | AI18: -533553.63 | AJ18: -163982.14 | AK18: -135214.57 | AL18: -421034.26 | AM18: -28767.57 | AN18: 1 | AO18: 1
A19: 5107 | B19: Employee Rent Discount | C19: -413.1 | D19: 0 | E19: -413.1 | F19: -1 | H19: -4043.1 | I19: 0 | J19: -4043.1 | K19: -1 | O19: 0 | S19: 0 | T19: 955092.21 | U19: 1021393.9 | V19: -720 | W19: 0 | Y19: 4 | Z19: 330077.29 | AA19: 350787.57 | AD19: 0 | AE19: -870 | AF19: 0 | AG19: -870 | AH19: 0 | AI19: -720 | AJ19: -2610 | AK19: 0 | AL19: 0 | AM19: -2610 | AN19: 1 | AO19: 1
A20: 5109 | B20: Model Vacancy Loss | C20: -1375 | D20: -1500 | E20: 125 | F20: 0.083333333 | H20: -8250 | I20: -9000 | J20: 750 | K20: 0.083333333 | O20: 0 | S20: 0 | T20: 955092.21 | U20: 1021393.9 | V20: 0 | W20: -18000 | Y20: 4 | Z20: 330077.29 | AA20: 350787.57 | AD20: 0 | AE20: -1375 | AF20: -1500 | AG20: 125 | AH20: 0 | AI20: 0 | AJ20: -4125 | AK20: -4500 | AL20: -18000 | AM20: 375 | AN20: 1 | AO20: 1
B21: Vacancy, Losses & Concessions | C21: -69308.29 | D21: -47947.06 | E21: -21361.23 | F21: -0.44551699 | H21: -436662.62 | I21: -308772.09 | J21: -127890.53 | K21: -0.41419071 | O21: -35852.27 | S21: -131594 | V21: -937303.88 | W21: -541034.26 | Y21: 4 | AD21: -35852.27 | AE21: -70568.7 | AF21: -47663.87 | AG21: -22904.83 | AH21: -131594 | AI21: -937303.88 | AJ21: -238348.56 | AK21: -165214.57 | AL21: -541034.26 | AM21: -73133.99
B22: Net Rental Income | C22: 264499.87 | D22: 310068.52 | E22: -45568.65 | F22: -0.14696316 | H22: 1595705.9 | I22: 1799376.4 | J22: -203670.53 | K22: -0.11318951 | O22: 295442.37 | S22: 851862.76 | V22: 3118914.2 | W22: 3772662.7 | Y22: 4 | AD22: 295442.37 | AE22: 271671.15 | AF22: 302360.57 | AG22: -30689.42 | AH22: 851862.76 | AI22: 3118914.2 | AJ22: 782811.94 | AK22: 876882.64 | AL22: 3772662.7 | AM22: -94070.7
A23: Other Income
A24: 5007 | B24: Other Income - Monthly Pet Rent | C24: 1065.43 | D24: 900 | E24: 165.43 | F24: 0.18381111 | H24: 6643.46 | I24: 5400 | J24: 1243.46 | K24: 0.23027037 | O24: 460 | S24: 1509 | T24: 955092.21 | U24: 1021393.9 | V24: 6751.85 | W24: 12750 | Y24: 4 | Z24: 330077.29 | AA24: 350787.57 | AD24: 460 | AE24: 1015.5 | AF24: 900 | AG24: 115.5 | AH24: 1509 | AI24: 6751.85 | AJ24: 3372.34 | AK24: 2700 | AL24: 12750 | AM24: 672.34 | AN24: 1 | AO24: 1
A25: 5008 | B25: Other Income - Covered Parking | C25: 7412.22 | D25: 4830 | E25: 2582.22 | F25: 0.53462112 | G25: This reflects increased collections in parking due to increasing covered parking to $45/month. | H25: 29830.45 | I25: 15480 | J25: 14350.45 | K25: 0.92703165 | O25: 295 | S25: 447.33 | T25: 955092.21 | U25: 1021393.9 | V25: 2453.68 | W25: 63360 | Y25: 4 | Z25: 330077.29 | AA25: 350787.57 | AD25: 295 | AE25: 4716.5 | AF25: 2130 | AG25: 2586.5 | AH25: 447.33 | AI25: 2453.68 | AJ25: 10186.86 | AK25: 3690 | AL25: 63360 | AM25: 6496.86 | AN25: 1 | AO25: 1
A26: 5013 | B26: Other Income - Washer/Dryer Rental | C26: 3990.14 | D26: 0 | E26: 3990.14 | F26: 1 | G26: This reflects washer/dryer collections charged at $50 per unit. | H26: 18182.39 | I26: 0 | J26: 18182.39 | K26: 1 | O26: 0 | S26: 0 | T26: 955092.21 | U26: 1021393.9 | V26: 2561.57 | W26: 0 | Y26: 4 | Z26: 330077.29 | AA26: 350787.57 | AD26: 0 | AE26: 2932.92 | AF26: 0 | AG26: 2932.92 | AH26: 0 | AI26: 2561.57 | AJ26: 6949.99 | AK26: 0 | AL26: 0 | AM26: 6949.99 | AN26: 1 | AO26: 1
A27: 5202 | B27: Other Income - Cable TV Income | C27: 2762.34 | D27: 0 | E27: 2762.34 | F27: 1 | H27: 4233.02 | I27: 2950 | J27: 1283.02 | K27: 0.43492203 | O27: 0 | S27: 0 | T27: 955092.21 | U27: 1021393.9 | V27: 0 | W27: 5900 | Y27: 4 | Z27: 330077.29 | AA27: 350787.57 | AD27: 0 | AE27: 0 | AF27: 0 | AG27: 0 | AH27: 0 | AI27: 0 | AJ27: 0 | AK27: 1475 | AL27: 5900 | AM27: -1475 | AN27: 1 | AO27: 1
A28: 5204 | B28: Other Income - Loss Damage Waiver | C28: 3391.32 | D28: 3699 | E28: -307.68 | F28: -0.083179238 | G28: This reflects monthly RLL insurance reimbursements at $15 per unit. | H28: 20654.69 | I28: 21947.4 | J28: -1292.71 | K28: -0.058900371 | O28: 0 | S28: 0 | T28: 955092.21 | U28: 1021393.9 | V28: 7864.69 | W28: 44757.9 | Y28: 4 | Z28: 330077.29 | AA28: 350787.57 | AD28: 0 | AE28: 3420.78 | AF28: 3699 | AG28: -278.22 | AH28: 0 | AI28: 7864.69 | AJ28: 10120.25 | AK28: 10850.4 | AL28: 44757.9 | AM28: -730.15 | AN28: 1 | AO28: 1
A29: 5211 | B29: Other Income - Water/Sewer Reimbursements | C29: 17337.14 | D29: 20388.6 | E29: -3051.46 | F29: -0.14966501 | G29: This reflects water sewer reimbursements for the month. | H29: 114521.96 | I29: 125935.12 | J29: -11413.16 | K29: -0.090627301 | O29: 15855.77 | S29: 54638.7 | T29: 955092.21 | U29: 1021393.9 | V29: 227078.89 | W29: 267336.18 | Y29: 4 | Z29: 330077.29 | AA29: 350787.57 | AD29: 15855.77 | AE29: 18676.13 | AF29: 19377 | AG29: -700.87 | AH29: 54638.7 | AI29: 227078.89 | AJ29: 61865.07 | AK29: 63499.42 | AL29: 267336.18 | AM29: -1634.35 | AN29: 1 | AO29: 1
A30: 5212 | B30: Other Income - Trash Reimbursements | C30: 9080.11 | D30: 4725 | E30: 4355.11 | F30: 0.9217164 | G30: This reflects trash reimbursements collected at $35 per month. | H30: 41501.02 | I30: 20475 | J30: 21026.02 | K30: 1.0269118 | O30: 2494.69 | S30: 6997.3 | T30: 955092.21 | U30: 1021393.9 | V30: 30299 | W30: 59850 | Y30: 4 | Z30: 330077.29 | AA30: 350787.57 | AD30: 2494.69 | AE30: 6996.58 | AF30: 3150 | AG30: 3846.58 | AH30: 6997.3 | AI30: 30299 | AJ30: 15746.74 | AK30: 7875 | AL30: 59850 | AM30: 7871.74 | AN30: 1 | AO30: 1
A31: 5220 | B31: Other Income - Pest Control Reimbursement | C31: 1589.65 | D31: 1077 | E31: 512.65 | F31: 0.47599814 | H31: 7119.39 | I31: 5487 | J31: 1632.39 | K31: 0.29750137 | O31: 598.46 | S31: 1840.93 | T31: 955092.21 | U31: 1021393.9 | V31: 7282.32 | W31: 13314 | Y31: 4 | Z31: 330077.29 | AA31: 350787.57 | AD31: 598.46 | AE31: 1142.17 | AF31: 882 | AG31: 260.17 | AH31: 1840.93 | AI31: 7282.32 | AJ31: 2773.39 | AK31: 2451 | AL31: 13314 | AM31: 322.39 | AN31: 1 | AO31: 1
A32: 5804 | B32: Other Income - Amenity Fee | C32: 2817.19 | D32: 3699 | E32: -881.81 | F32: -0.23839146 | H32: 18355.22 | I32: 21947.4 | J32: -3592.18 | K32: -0.16367223 | O32: 3474.73 | S32: 10328.23 | T32: 955092.21 | U32: 1021393.9 | V32: 39846.64 | W32: 44757.9 | Y32: 4 | Z32: 330077.29 | AA32: 350787.57 | AD32: 3474.73 | AE32: 2995.36 | AF32: 3699 | AG32: -703.64 | AH32: 10328.23 | AI32: 39846.64 | AJ32: 8637.94 | AK32: 10850.4 | AL32: 44757.9 | AM32: -2212.46 | AN32: 1 | AO32: 1
A33: 5805 | B33: Other Income - Late Charges | C33: 6477.35 | D33: 6000 | E33: 477.35 | F33: 0.079558333 | H33: 43251.87 | I33: 36000 | J33: 7251.87 | K33: 0.20144083 | O33: 11475 | S33: 35878.95 | T33: 955092.21 | U33: 1021393.9 | V33: 117831.01 | W33: 66000 | Y33: 4 | Z33: 330077.29 | AA33: 350787.57 | AD33: 11475 | AE33: 5715 | AF33: 6000 | AG33: -285 | AH33: 35878.95 | AI33: 117831.01 | AJ33: 24622.74 | AK33: 18000 | AL33: 66000 | AM33: 6622.74 | AN33: 1 | AO33: 1
A34: 5810 | B34: Other Income - Laundry Income | C34: 460.49 | D34: 175 | E34: 285.49 | F34: 1.6313714 | H34: 1305.39 | I34: 350 | J34: 955.39 | K34: 2.7296857 | O34: 266.18 | S34: 459.63 | T34: 955092.21 | U34: 1021393.9 | V34: 627.11 | W34: 1050 | Y34: 4 | Z34: 330077.29 | AA34: 350787.57 | AD34: 266.18 | AE34: 0 | AF34: 175 | AG34: -175 | AH34: 459.63 | AI34: 627.11 | AJ34: 0 | AK34: 175 | AL34: 1050 | AM34: -175 | AN34: 1 | AO34: 1
A35: 5860 | B35: Other Income - Parcel Services Income | C35: 434.24 | D35: 0 | E35: 434.24 | F35: 1 | H35: 576.83 | I35: 0 | J35: 576.83 | K35: 1 | O35: 0 | S35: 0 | T35: 955092.21 | U35: 1021393.9 | V35: 1406.68 | W35: 33480 | Y35: 4 | Z35: 330077.29 | AA35: 350787.57 | AD35: 0 | AE35: 2527.93 | AF35: 1215 | AG35: 1312.93 | AH35: 0 | AI35: 1406.68 | AJ35: 5684.31 | AK35: 2295 | AL35: 33480 | AM35: 3389.31 | AN35: 1 | AO35: 1
A36: 5861 | B36: Other Income - Lease Lock | C36: 4237.35 | D36: 2565 | E36: 1672.35 | F36: 0.6519883 | G36: This reflects lease lock collections charged at $45 per month. | H36: 17037.6 | I36: 8640 | J36: 8397.6 | K36: 0.97194444 | O36: 7702 | S36: 19353.7 | T36: 955092.21 | U36: 1021393.9 | V36: 72999.95 | W36: 1200 | Y36: 4 | Z36: 330077.29 | AA36: 350787.57 | AD36: 7702 | AE36: 125 | AF36: 100 | AG36: 25 | AH36: 19353.7 | AI36: 72999.95 | AJ36: 1622.05 | AK36: 300 | AL36: 1200 | AM36: 1322.05 | AN36: 1 | AO36: 1
A37: 5890 | B37: Other Income - Miscellaneous Income | C37: 74.44 | D37: 100 | E37: -25.56 | F37: -0.2556 | H37: 1946.49 | I37: 600 | J37: 1346.49 | K37: 2.24415 | O37: 0 | S37: 50 | T37: 955092.21 | U37: 1021393.9 | V37: 1275 | W37: 375 | Y37: 4 | Z37: 330077.29 | AA37: 350787.57 | AD37: 0 | AE37: 225 | AF37: 0 | AG37: 225 | AH37: 50 | AI37: 1275 | AJ37: 450 | AK37: 150 | AL37: 375 | AM37: 300 | AN37: 1 | AO37: 1
A38: 5891 | B38: Other Income - NSF Charges | C38: 375 | D38: 0 | E38: 375 | F38: 1 | H38: 1050 | I38: 300 | J38: 750 | K38: 2.5 | O38: 0 | S38: 0 | T38: 955092.21 | U38: 1021393.9 | V38: 0 | W38: 1200 | Y38: 4 | Z38: 330077.29 | AA38: 350787.57 | AD38: 0 | AE38: 1000 | AF38: 200 | AG38: 800 | AH38: 0 | AI38: 0 | AJ38: 1200 | AK38: 200 | AL38: 1200 | AM38: 1000 | AN38: 1 | AO38: 1
A39: 5892 | B39: Other Income - Non-Refundable Pet Fee | C39: 350 | D39: 200 | E39: 150 | F39: 0.75 | H39: 2550 | I39: 400 | J39: 2150 | K39: 5.375 | O39: 0 | S39: 1708.1 | T39: 955092.21 | U39: 1021393.9 | V39: 62917.75 | W39: 27000 | Y39: 4 | Z39: 330077.29 | AA39: 350787.57 | AD39: 0 | AE39: 3064.8 | AF39: 2500 | AG39: 564.8 | AH39: 1708.1 | AI39: 62917.75 | AJ39: 6071.14 | AK39: 7500 | AL39: 27000 | AM39: -1428.86 | AN39: 1 | AO39: 1
A40: 5893 | B40: Other Income - Damages | C40: 6763.82 | D40: 2500 | E40: 4263.82 | F40: 1.705528 | G40: This reflects move out collections for carpet, vinyl, utilities, resurfacing and misc. charges for move out damages. | H40: 25725.45 | I40: 15000 | J40: 10725.45 | K40: 0.71503 | O40: 0 | S40: 600 | T40: 955092.21 | U40: 1021393.9 | V40: 600 | W40: 1500 | Y40: 4 | Z40: 330077.29 | AA40: 350787.57 | AD40: 0 | AE40: 0 | AF40: 250 | AG40: -250 | AH40: 600 | AI40: 600 | AJ40: 0 | AK40: 250 | AL40: 1500 | AM40: -250 | AN40: 1 | AO40: 1
A41: 5894 | B41: Other Income - Transfer Fee | C41: 0 | D41: 250 | E41: -250 | F41: -1 | H41: 0 | I41: 500 | J41: -500 | K41: -1 | O41: 1735 | S41: 3100 | T41: 955092.21 | U41: 1021393.9 | V41: 13355.8 | W41: 12800 | Y41: 4 | Z41: 330077.29 | AA41: 350787.57 | AD41: 1735 | AE41: 3450 | AF41: 1200 | AG41: 2250 | AH41: 3100 | AI41: 13355.8 | AJ41: 9696.21 | AK41: 3400 | AL41: 12800 | AM41: 6296.21 | AN41: 1 | AO41: 1
A42: 5896 | B42: Other Income - Application Fee | C42: 1885.96 | D42: 1100 | E42: 785.96 | F42: 0.71450909 | H42: 16307.17 | I42: 6800 | J42: 9507.17 | K42: 1.3981132 | O42: 0 | S42: 0 | T42: 955092.21 | U42: 1021393.9 | V42: 0 | W42: 2400 | Y42: 4 | Z42: 330077.29 | AA42: 350787.57 | AD42: 0 | AE42: 0 | AF42: 200 | AG42: -200 | AH42: 0 | AI42: 0 | AJ42: 0 | AK42: 600 | AL42: 2400 | AM42: -600 | AN42: 1 | AO42: 1
A43: 5897 | B43: Other Income - Non-Refundable Gate/Pool/Fitness Fee | C43: 6506.17 | D43: 200 | E43: 6306.17 | F43: 31.53085 | G43: This reflects collections for gate fees charged during the month at $50 per unit. | H43: 7238.92 | I43: 1200 | J43: 6038.92 | K43: 5.0324333 | O43: 2830 | S43: 5742 | T43: 955092.21 | U43: 1021393.9 | V43: 11858.07 | W43: 9000 | Y43: 4 | Z43: 330077.29 | AA43: 350787.57 | AD43: 2830 | AE43: 402.47 | AF43: 750 | AG43: -347.53 | AH43: 5742 | AI43: 11858.07 | AJ43: 3130.85 | AK43: 2250 | AL43: 9000 | AM43: 880.85 | AN43: 1 | AO43: 1
A44: 5898 | B44: Other Income - Cancellation Fee | C44: 2500 | D44: 750 | E44: 1750 | F44: 2.3333333 | G44: This reflects application cancellations and lease breakage fees during the month. | H44: 9622.85 | I44: 4500 | J44: 5122.85 | K44: 1.1384111 | O44: 0 | S44: 0 | T44: 955092.21 | U44: 1021393.9 | V44: 650 | W44: 19750 | Y44: 4 | Z44: 330077.29 | AA44: 350787.57 | AD44: 0 | AE44: 0 | AF44: 2000 | AG44: -2000 | AH44: 0 | AI44: 650 | AJ44: 150.39 | AK44: 6000 | AL44: 19750 | AM44: -5849.61 | AN44: 1 | AO44: 1
A45: 5899 | B45: Other Income - Non-Refundable Redecorating Fee | C45: 2332.51 | D45: 2000 | E45: 332.51 | F45: 0.166255 | H45: 11720.71 | I45: 12000 | J45: -279.29 | K45: -0.023274167 | O45: 47186.83 | S45: 142653.87 | V45: 607660.01 | W45: 687780.98 | Y45: 4 | AD45: 47186.83 | AE45: 58406.14 | AF45: 48427 | AG45: 9979.14 | AH45: 142653.87 | AI45: 607660.01 | AJ45: 172280.27 | AK45: 144511.22 | AL45: 687780.98 | AM45: 27769.05
B46: Other Income | C46: 81842.87 | D46: 55158.6 | E46: 26684.27 | F46: 0.48377352 | H46: 399374.88 | I46: 305911.92 | J46: 93462.96 | K46: 0.30552245 | O46: 342629.2 | S46: 994516.63 | V46: 3726574.2 | W46: 4460443.7 | Y46: 4 | AD46: 342629.2 | AE46: 330077.29 | AF46: 350787.57 | AG46: -20710.28 | AH46: 994516.63 | AI46: 3726574.2 | AJ46: 955092.21 | AK46: 1021393.9 | AL46: 4460443.7 | AM46: -66301.65
B47: Income | C47: 346342.74 | D47: 365227.12 | E47: -18884.38 | F47: -0.051705854 | H47: 1995080.7 | I47: 2105288.3 | J47: -110207.57 | K47: -0.05234797
A48: Operating Expenses
A49: Payroll & Related
A50: Payroll | O50: 9197.79 | S50: 25281.57 | T50: 955092.21 | U50: 1021393.9 | V50: 78228.54 | W50: 71442 | Y50: 5 | Z50: 330077.29 | AA50: 350787.57 | AD50: -9197.79 | AE50: -7788.46 | AF50: -7905 | AG50: 116.54 | AH50: -25281.57 | AI50: -78228.54 | AJ50: -18173.08 | AK50: -18445 | AL50: -71442 | AM50: 271.92 | AN50: -1 | AO50: 1
